Workbook

Sheet 筆記
A1: 高科大 | B1: 不影響現流部分，其中有一項是不動產、廠房及設備與應付未付數同額增加明細(+)133,340千元，分別帳列應付款、其他長期負債(其他長期應付款)406
A3: 本年度預計舉借數合計359,601千元，與現金流量綜計表長期負債增加數509,601千元，差異數150,000 千元，係因現金流量綜計表所列長期負債增加數，尚包括國立大學校院校務基金(綜計)以前年度長期借款 保留數150,000千元；本年度預計償還數合計200,284千元，與現金流量綜計表長期負債減少數200,735 千元，差異數451千元，係因現金流量綜計表所列長期負債減少數，除長期借款外，尚包括本年度減少 國立大學校院校務基金(綜計)應付租賃款451千元。

Sheet 大學-自己調整
A1: 國立大學校院校務基金(彙計表) | K1: =L1+2 | L1: 0
A2: 預計平衡表與現金流量表勾稽底稿
A3: 中華民國116年度
G4: G欄=B欄期初數+C至F欄調整項目 | J4: J欄=教育部「現流表」原始資料 | L4: L欄=教育部「平衡表」期末數
A5: 科目 | B5: 115.12.31 | C5: 調整項目 | G5: 116.12.31 | H5: 現金流量表勾稽項目
B6: 預計數 | D6: 借方 | F6: 貸方 | G6: 預計數 | L6: 教育部 平衡表 | M6: M欄=自行調整後平衡表期末數與教育部之平衡表期末數之差異數
A7: 資產 | H7: ▼業務活動之現金流量 | K7: 自己拉現流表公式 | M7: 差異數要再加(減) | O7: O欄=教育部「平衡表」之比較增減 | Q7: Q欄=自行調整調整項目借貸方合計淨值，用來跟教育部之比較增減勾稽
A8: 流動資產 | B8: =SUM(臺大:東專!B7) | D8: =SUM(臺大:東專!D7) | F8: =SUM(臺大:東專!F7) | G8: =SUM(臺大:東專!G7) | H8: 本期賸餘（短絀） | I8: A | J8: =SUM(臺大:東專!J7) | K8: =-SUMIF($C$7:$C$127,I8,$D$7:$D$127)+SUMIF($E$7:$E$127,I8,$F$7:$F$127) | L8: =VLOOKUP(A8,$A$139:$AW$244,$K$1,FALSE) | M8: =L8-G8 | O8: =L8-B8 | Q8: =D8-F8 | S8: =K8-J8
A9: 現金 | B9: =SUM(臺大:東專!B8) | C9: B | D9: =SUM(臺大:東專!D8) | E9: B | F9: =SUM(臺大:東專!F8) | G9: =SUM(臺大:東專!G8) | H9: 利息股利之調整 | J9: =SUM(臺大:東專!J8) | K9: =SUM(K10:K12) | L9: =VLOOKUP(A9,$A$139:$AW$244,$K$1,FALSE) | M9: =L9-G9 | O9: =L9-B9 | Q9: =D9-F9 | S9: =J9-K9
A10: 流動金融資產 | B10: =SUM(臺大:東專!B9) | C10: 231 | D10: =SUM(臺大:東專!D9) | E10: 211 | F10: =SUM(臺大:東專!F9) | G10: =SUM(臺大:東專!G9) | H10: 利息收入 | J10: =SUM(臺大:東專!J9) | K10: =J10 | L10: =VLOOKUP(A10,$A$139:$AW$244,$K$1,FALSE) | M10: =L10-G10 | O10: =L10-B10 | Q10: =D10-F10 | S10: =J10-K10
B11: =SUM(臺大:東專!B10) | C11: 125 | D11: =SUM(臺大:東專!D10) | F11: =SUM(臺大:東專!F10) | G11: =SUM(臺大:東專!G10) | H11: 股利收入 | J11: =SUM(臺大:東專!J10) | K11: =J11 | O11: =L11-B12 | Q11: =D12-F12 | S11: =J11-K11
A12: 應收款項 | B12: =SUM(臺大:東專!B11) | C12: 151 | D12: =SUM(臺大:東專!D11) | E12: 151 | F12: =SUM(臺大:東專!F11) | G12: =SUM(臺大:東專!G11) | H12: 利息費用 | J12: =SUM(臺大:東專!J11) | K12: =J12 | L12: =VLOOKUP(A12,$A$139:$AW$244,$K$1,FALSE) | M12: =L12-G12 | O12: =L12-B13 | Q12: =D13-F13 | S12: =J12-K12
B13: =SUM(臺大:東專!B12) | D13: =SUM(臺大:東專!D12) | F13: =SUM(臺大:東專!F12) | G13: =SUM(臺大:東專!G12) | H13: 未計利息股利之本期賸餘（短絀） | J13: =SUM(臺大:東專!J12) | K13: =K8+K9 | O13: =L13-B14 | Q13: =D14-F14 | S13: =J13-K13
A14: 存貨 | B14: =SUM(臺大:東專!B13) | C14: 151 | D14: =SUM(臺大:東專!D13) | E14: 151 | F14: =SUM(臺大:東專!F13) | G14: =SUM(臺大:東專!G13) | H14: 調整項目 | J14: =SUM(臺大:東專!J13) | K14: =SUM(K15,K25,K28,K35,K34) | L14: =VLOOKUP(A14,$A$139:$AW$244,$K$1,FALSE) | M14: =L14-G14 | O14: =L14-B15 | Q14: =D15-F15 | S14: =J14-K14
A15: 生產性生物資產－流動 | B15: =SUM(臺大:東專!B14) | C15: 151 | D15: =SUM(臺大:東專!D14) | E15: 151 | F15: =SUM(臺大:東專!F14) | G15: =SUM(臺大:東專!G14) | H15: 折舊、減損及折耗 | J15: =SUM(臺大:東專!J14) | K15: =SUM(K16:K24) | L15: =VLOOKUP(A15,$A$139:$AW$244,$K$1,FALSE) | M15: =L15-G15 | O15: =L15-B16 | Q15: =D16-F16 | S15: =J15-K15
A16: 預付款項 | B16: =SUM(臺大:東專!B15) | C16: 151 | D16: =SUM(臺大:東專!D15) | E16: 151 | F16: =SUM(臺大:東專!F15) | G16: =SUM(臺大:東專!G15) | H16: 土地改良物 | I16: 101 | J16: =SUM(臺大:東專!J15) | K16: =-SUMIF($C$7:$C$127,I16,$D$7:$D$127)+SUMIF($E$7:$E$127,I16,$F$7:$F$127) | L16: =VLOOKUP(A16,$A$139:$AW$244,$K$1,FALSE) | M16: =L16-G16 | O16: =L16-B17 | Q16: =D17-F17 | S16: =J16-K16
A17: 短期貸墊款 | B17: =SUM(臺大:東專!B16) | C17: 151 | D17: =SUM(臺大:東專!D16) | E17: 212 | F17: =SUM(臺大:東專!F16) | G17: =SUM(臺大:東專!G16) | H17: 房屋及建築 | I17: 102 | J17: =SUM(臺大:東專!J16) | K17: =-SUMIF($C$7:$C$127,I17,$D$7:$D$127)+SUMIF($E$7:$E$127,I17,$F$7:$F$127) | L17: =VLOOKUP(A17,$A$139:$AW$244,$K$1,FALSE) | M17: =L17-G17 | O17: =L17-B18 | Q17: =D18-F18 | S17: =J17-K17
A18: 投資、長期應收款、貸墊款及準備金 | B18: =SUM(臺大:東專!B17) | D18: =SUM(臺大:東專!D17) | F18: =SUM(臺大:東專!F17) | G18: =SUM(臺大:東專!G17) | H18: 機械及設備 | I18: 103 | J18: =SUM(臺大:東專!J17) | K18: =-SUMIF($C$7:$C$127,I18,$D$7:$D$127)+SUMIF($E$7:$E$127,I18,$F$7:$F$127) | L18: =VLOOKUP(A18,$A$139:$AW$244,$K$1,FALSE) | M18: =L18-G18 | O18: =L18-B19 | Q18: =D19-F19 | S18: =J18-K18
A19: 採權益法之投資 | B19: =SUM(臺大:東專!B18) | D19: =SUM(臺大:東專!D18) | F19: =SUM(臺大:東專!F18) | G19: =SUM(臺大:東專!G18) | H19: 交通及運輸設備 | I19: 104 | J19: =SUM(臺大:東專!J18) | K19: =-SUMIF($C$7:$C$127,I19,$D$7:$D$127)+SUMIF($E$7:$E$127,I19,$F$7:$F$127) | L19: =VLOOKUP(A19,$A$139:$AW$244,$K$1,FALSE) | M19: =L19-G19 | O19: =L19-B20 | Q19: =D20-F20 | S19: =J19-K19
A20: 非流動金融資產 | B20: =SUM(臺大:東專!B19) | C20: 241 | D20: =SUM(臺大:東專!D19) | E20: 221 | F20: =SUM(臺大:東專!F19) | G20: =SUM(臺大:東專!G19) | H20: 什項設備 | I20: 105 | J20: =SUM(臺大:東專!J19) | K20: =-SUMIF($C$7:$C$127,I20,$D$7:$D$127)+SUMIF($E$7:$E$127,I20,$F$7:$F$127) | L20: =VLOOKUP(A20,$A$139:$AW$244,$K$1,FALSE) | M20: =L20-G20 | O20: =L20-B21 | Q20: =D21-F21 | S20: =J20-K20
A21: 長期應收款 | B21: =SUM(臺大:東專!B20) | D21: =SUM(臺大:東專!D20) | F21: =SUM(臺大:東專!F20) | G21: =SUM(臺大:東專!G20) | H21: 租賃資產 | I21: 106 | J21: =SUM(臺大:東專!J20) | K21: =-SUMIF($C$7:$C$127,I21,$D$7:$D$127)+SUMIF($E$7:$E$127,I21,$F$7:$F$127) | L21: =VLOOKUP(A21,$A$139:$AW$244,$K$1,FALSE) | M21: =L21-G21 | O21: =L21-B22 | Q21: =D22-F22 | S21: =J21-K21
A22: 準備金 | B22: =SUM(臺大:東專!B21) | C22: 242 | D22: =SUM(臺大:東專!D21) | E22: 222 | F22: =SUM(臺大:東專!F21) | G22: =SUM(臺大:東專!G21) | H22: 租賃權益改良 | I22: 107 | J22: =SUM(臺大:東專!J21) | K22: =-SUMIF($C$7:$C$127,I22,$D$7:$D$127)+SUMIF($E$7:$E$127,I22,$F$7:$F$127) | L22: =VLOOKUP(A22,$A$139:$AW$244,$K$1,FALSE) | M22: =L22-G22 | O22: =L22-B23 | Q22: =D23-F23 | S22: =J22-K22
B23: =SUM(臺大:東專!B22) | C23: 401 | D23: =SUM(臺大:東專!D22) | E23: 402 | F23: =SUM(臺大:東專!F22) | G23: =SUM(臺大:東專!G22) | H23: 代管資產 | I23: 108 | J23: =SUM(臺大:東專!J22) | K23: =-SUMIF($C$7:$C$127,I23,$D$7:$D$127)+SUMIF($E$7:$E$127,I23,$F$7:$F$127) | O23: =L23-B24 | Q23: =D24-F24 | S23: =J23-K23
B24: =SUM(臺大:東專!B23) | C24: 403 | D24: =SUM(臺大:東專!D23) | F24: =SUM(臺大:東專!F23) | G24: =SUM(臺大:東專!G23) | H24: 生產性生物資產－非流動 | I24: 109 | J24: =SUM(臺大:東專!J23) | K24: =-SUMIF($C$7:$C$127,I24,$D$7:$D$127)+SUMIF($E$7:$E$127,I24,$F$7:$F$127) | O24: =L24-B25 | Q24: =D25-F25 | S24: =J24-K24
B25: =SUM(臺大:東專!B24) | C25: C | D25: =SUM(臺大:東專!D24) | F25: =SUM(臺大:東專!F24) | G25: =SUM(臺大:東專!G24) | H25: 攤銷 | J25: =SUM(臺大:東專!J24) | K25: =SUM(K26:K27) | O25: =L25-B26 | Q25: =D26-F26 | S25: =J25-K25
B26: =SUM(臺大:東專!B25) | C26: 125 | D26: =SUM(臺大:東專!D25) | F26: =SUM(臺大:東專!F25) | G26: =SUM(臺大:東專!G25) | H26: 攤銷電腦軟體 | I26: 111 | J26: =SUM(臺大:東專!J25) | K26: =-SUMIF($C$7:$C$127,I26,$D$7:$D$127)+SUMIF($E$7:$E$127,I26,$F$7:$F$127) | O26: =L26-B27 | Q26: =D27-F27 | S26: =J26-K26
A27: 不動產、廠房及設備 | B27: =SUM(臺大:東專!B26) | D27: =SUM(臺大:東專!D26) | F27: =SUM(臺大:東專!F26) | G27: =SUM(臺大:東專!G26) | H27: 其他攤銷費用 | I27: 112 | J27: =SUM(臺大:東專!J26) | K27: =-SUMIF($C$7:$C$127,I27,$D$7:$D$127)+SUMIF($E$7:$E$127,I27,$F$7:$F$127) | L27: =VLOOKUP(A27,$A$139:$AW$244,$K$1,FALSE) | M27: =L27-G27 | O27: =L27-B27 | Q27: =D27-F27 | S27: =J27-K27
A28: 土地 | B28: =SUM(臺大:東專!B27) | C28: 121 | D28: =SUM(臺大:東專!D27) | F28: =SUM(臺大:東專!F27) | G28: =SUM(臺大:東專!G27) | H28: 其他 | J28: =SUM(臺大:東專!J27) | K28: =K29+K30+K33 | L28: =VLOOKUP(A28,$A$139:$AW$244,$K$1,FALSE) | M28: =L28-G28 | O28: =L28-B28 | Q28: =D28-F28 | S28: =J28-K28
B29: =SUM(臺大:東專!B28) | D29: =SUM(臺大:東專!D28) | F29: =SUM(臺大:東專!F28) | G29: =SUM(臺大:東專!G28) | H29: 應付退休及離職金 | I29: 122 | J29: =SUM(臺大:東專!J28) | K29: =-SUMIF($C$7:$C$127,I29,$D$7:$D$127)+SUMIF($E$7:$E$127,I29,$F$7:$F$127) | O29: =L29-B29 | Q29: =D29-F29 | S29: =J29-K29
A30: 土地改良物 | B30: =SUM(臺大:東專!B29) | C30: 251 | D30: =SUM(臺大:東專!D29) | E30: 101 | F30: =SUM(臺大:東專!F29) | G30: =SUM(臺大:東專!G29) | H30: 遞延收入 | J30: =SUM(臺大:東專!J29) | K30: =K31+K32 | L30: =VLOOKUP(A30,$A$139:$AW$244,$K$1,FALSE) | M30: =L30-G30 | O30: =L30-B30 | Q30: =D30-F30 | S30: =J30-K30
B31: =SUM(臺大:東專!B30) | C31: 404 | D31: =SUM(臺大:東專!D30) | F31: =SUM(臺大:東專!F30) | G31: =SUM(臺大:東專!G30) | H31: 遞延收入-其他補助收入 | I31: 123 | J31: =SUM(臺大:東專!J30) | K31: =-SUMIF($C$7:$C$127,I31,$D$7:$D$127)+SUMIF($E$7:$E$127,I31,$F$7:$F$127) | O31: =L31-B31 | Q31: =D31-F31 | S31: =J31-K31
B32: =SUM(臺大:東專!B31) | D32: =SUM(臺大:東專!D31) | F32: =SUM(臺大:東專!F31) | G32: =SUM(臺大:東專!G31) | H32: 遞延收入-受贈收入 | I32: 124 | J32: =SUM(臺大:東專!J31) | K32: =-SUMIF($C$7:$C$127,I32,$D$7:$D$127)+SUMIF($E$7:$E$127,I32,$F$7:$F$127) | O32: =L32-B32 | Q32: =D32-F32 | S32: =J32-K32
B33: =SUM(臺大:東專!B32) | D33: =SUM(臺大:東專!D32) | F33: =SUM(臺大:東專!F32) | G33: =SUM(臺大:東專!G32) | H33: 其他 | I33: 125 | J33: =SUM(臺大:東專!J32) | K33: =-SUMIF($C$7:$C$127,I33,$D$7:$D$127)+SUMIF($E$7:$E$127,I33,$F$7:$F$127) | O33: =L33-B33 | Q33: =D33-F33 | S33: =J33-K33
A34: 房屋及建築 | B34: =SUM(臺大:東專!B33) | C34: 252 | D34: =SUM(臺大:東專!D33) | E34: 102 | F34: =SUM(臺大:東專!F33) | G34: =SUM(臺大:東專!G33) | H34: 流動資產淨減（淨增） | I34: 151 | J34: =SUM(臺大:東專!J33) | K34: =-SUMIF($C$7:$C$127,I34,$D$7:$D$127)+SUMIF($E$7:$E$127,I34,$F$7:$F$127) | L34: =VLOOKUP(A34,$A$139:$AW$244,$K$1,FALSE) | M34: =L34-G34 | O34: =L34-B34 | Q34: =D34-F34 | S34: =J34-K34
B35: =SUM(臺大:東專!B34) | C35: 405 | D35: =SUM(臺大:東專!D34) | F35: =SUM(臺大:東專!F34) | G35: =SUM(臺大:東專!G34) | H35: 流動負債淨增（淨減） | I35: 161 | J35: =SUM(臺大:東專!J34) | K35: =-SUMIF($C$7:$C$127,I35,$D$7:$D$127)+SUMIF($E$7:$E$127,I35,$F$7:$F$127) | O35: =L35-B35 | Q35: =D35-F35 | S35: =J35-K35
B36: =SUM(臺大:東專!B35) | D36: =SUM(臺大:東專!D35) | F36: =SUM(臺大:東專!F35) | G36: =SUM(臺大:東專!G35) | H36: 未計利息股利之現金流入（流出） | J36: =SUM(臺大:東專!J35) | K36: =K13+K14 | O36: =L36-B36 | Q36: =D36-F36 | S36: =J36-K36
B37: =SUM(臺大:東專!B36) | D37: =SUM(臺大:東專!D36) | F37: =SUM(臺大:東專!F36) | G37: =SUM(臺大:東專!G36) | H37: 收取利息 | J37: =SUM(臺大:東專!J36) | K37: =J37 | O37: =L37-B37 | Q37: =D37-F37 | S37: =J37-K37
A38: 機械及設備 | B38: =SUM(臺大:東專!B37) | C38: 253 | D38: =SUM(臺大:東專!D37) | E38: 103 | F38: =SUM(臺大:東專!F37) | G38: =SUM(臺大:東專!G37) | H38: 收取股利 | J38: =SUM(臺大:東專!J37) | K38: =J38 | L38: =VLOOKUP(A38,$A$139:$AW$244,$K$1,FALSE) | M38: =L38-G38 | O38: =L38-B38 | Q38: =D38-F38 | S38: =J38-K38
B39: =SUM(臺大:東專!B38) | C39: 407 | D39: =SUM(臺大:東專!D38) | F39: =SUM(臺大:東專!F38) | G39: =SUM(臺大:東專!G38) | H39: 支付利息 | J39: =SUM(臺大:東專!J38) | K39: =J39 | O39: =L39-B39 | Q39: =D39-F39 | S39: =J39-K39
B40: =SUM(臺大:東專!B39) | C40: 409 | D40: =SUM(臺大:東專!D39) | E40: 412 | F40: =SUM(臺大:東專!F39) | G40: =SUM(臺大:東專!G39) | H40: ▼業務活動之淨現金流入（流出） | J40: =SUM(臺大:東專!J39) | K40: =J40 | O40: =L40-B40 | Q40: =D40-F40 | S40: =J40-K40
B41: =SUM(臺大:東專!B40) | D41: =SUM(臺大:東專!D40) | F41: =SUM(臺大:東專!F40) | G41: =SUM(臺大:東專!G40) | H41: ▼投資活動之現金流量 | J41: =SUM(臺大:東專!J40) | K41: =SUM(K42,K45,K48,K49,K50,K52,K55,K65) | O41: =L41-B41 | Q41: =D41-F41 | S41: =J41-K41
B42: =SUM(臺大:東專!B41) | D42: =SUM(臺大:東專!D41) | F42: =SUM(臺大:東專!F41) | G42: =SUM(臺大:東專!G41) | H42: 減少流動金融資產及短期貸墊款 | J42: =SUM(臺大:東專!J41) | K42: =K43+K44 | M42: =L42-G42 | O42: =L42-B42 | Q42: =D42-F42 | S42: =J42-K42
A43: 交通及運輸設備 | B43: =SUM(臺大:東專!B42) | C43: 254 | D43: =SUM(臺大:東專!D42) | E43: 104 | F43: =SUM(臺大:東專!F42) | G43: =SUM(臺大:東專!G42) | H43: 減少流動金融資產 | I43: 211 | J43: =SUM(臺大:東專!J42) | K43: =-SUMIF($C$7:$C$127,I43,$D$7:$D$127)+SUMIF($E$7:$E$135,I43,$F$7:$F$127) | L43: =VLOOKUP(A43,$A$139:$AW$244,$K$1,FALSE) | M43: =L43-G43 | O43: =L43-B43 | Q43: =D43-F43 | S43: =J43-K43
B44: =SUM(臺大:東專!B43) | C44: 410 | D44: =SUM(臺大:東專!D43) | E44: 413 | F44: =SUM(臺大:東專!F43) | G44: =SUM(臺大:東專!G43) | H44: 減少短期墊款 | I44: 212 | J44: =SUM(臺大:東專!J43) | K44: =-SUMIF($C$7:$C$127,I44,$D$7:$D$127)+SUMIF($E$7:$E$135,I44,$F$7:$F$127) | M44: =L44-G44 | O44: =L44-B44 | Q44: =D44-F44 | S44: =J44-K44
B45: =SUM(臺大:東專!B44) | D45: =SUM(臺大:東專!D44) | F45: =SUM(臺大:東專!F44) | G45: =SUM(臺大:東專!G44) | H45: 減少投資、長期應收款、貸墊款及準備金 | J45: =SUM(臺大:東專!J44) | K45: =SUM(K46:K47) | M45: =L45-G45 | O45: =L45-B45 | Q45: =D45-F45 | S45: =J45-K45
A46: 什項設備 | B46: =SUM(臺大:東專!B45) | C46: 255 | D46: =SUM(臺大:東專!D45) | E46: 105 | F46: =SUM(臺大:東專!F45) | G46: =SUM(臺大:東專!G45) | H46: 減少投資 | I46: 221 | J46: =SUM(臺大:東專!J45) | K46: =-SUMIF($C$7:$C$127,I46,$D$7:$D$127)+SUMIF($E$7:$E$135,I46,$F$7:$F$127) | L46: =VLOOKUP(A46,$A$139:$AW$244,$K$1,FALSE) | M46: =L46-G46 | O46: =L46-B46 | Q46: =D46-F46 | S46: =J46-K46
B47: =SUM(臺大:東專!B46) | C47: 408 | D47: =SUM(臺大:東專!D46) | F47: =SUM(臺大:東專!F46) | G47: =SUM(臺大:東專!G46) | H47: 減少準備金 | I47: 222 | J47: =SUM(臺大:東專!J46) | K47: =-SUMIF($C$7:$C$127,I47,$D$7:$D$127)+SUMIF($E$7:$E$135,I47,$F$7:$F$127) | O47: =L47-B47 | Q47: =D47-F47 | S47: =J47-K47
B48: =SUM(臺大:東專!B47) | C48: 411 | D48: =SUM(臺大:東專!D47) | E48: 414 | F48: =SUM(臺大:東專!F47) | G48: =SUM(臺大:東專!G47) | H48: 收取利息 | J48: =SUM(臺大:東專!J47) | K48: =J48 | O48: =L48-B48 | Q48: =D48-F48 | S48: =J48-K48
B49: =SUM(臺大:東專!B48) | C49: 406 | D49: =SUM(臺大:東專!D48) | F49: =SUM(臺大:東專!F48) | G49: =SUM(臺大:東專!G48) | H49: 收取股利 | J49: =SUM(臺大:東專!J48) | K49: =J49 | O49: =L49-B49 | Q49: =D49-F49 | S49: =J49-K49
A50: 租賃資產 | B50: =SUM(臺大:東專!B49) | D50: =SUM(臺大:東專!D49) | E50: 106 | F50: =SUM(臺大:東專!F49) | G50: =SUM(臺大:東專!G49) | H50: 增加流動金融資產及短期貸墊款 | J50: =SUM(臺大:東專!J49) | K50: =K51 | L50: =VLOOKUP(A50,$A$139:$AW$244,$K$1,FALSE) | M50: =L50-G50 | S50: =J50-K50
A51: 租賃權益改良 | B51: =SUM(臺大:東專!B50) | C51: 257 | D51: =SUM(臺大:東專!D50) | E51: 107 | F51: =SUM(臺大:東專!F50) | G51: =SUM(臺大:東專!G50) | H51: 增加流動金融資產 | I51: 231 | J51: =SUM(臺大:東專!J50) | K51: =-SUMIF($C$7:$C$127,I51,$D$7:$D$127)+SUMIF($E$7:$E$135,I51,$F$7:$F$127) | L51: =VLOOKUP(A51,$A$139:$AW$244,$K$1,FALSE) | M51: =L51-G51 | O51: =L51-B50 | Q51: =D50-F50 | S51: =J51-K51
A52: 購建中固定資產 | B52: =SUM(臺大:東專!B51) | C52: 256 | D52: =SUM(臺大:東專!D51) | E52: 404 | F52: =SUM(臺大:東專!F51) | G52: =SUM(臺大:東專!G51) | H52: 增加投資、長期應收款、貸墊款及準備金 | J52: =SUM(臺大:東專!J51) | K52: =SUM(K53:K54) | L52: =VLOOKUP(A52,$A$139:$AW$244,$K$1,FALSE) | M52: =L52-G52 | O52: =L52-B51 | Q52: =D51-F51 | S52: =J52-K52
B53: =SUM(臺大:東專!B52) | D53: =SUM(臺大:東專!D52) | E53: 405 | F53: =SUM(臺大:東專!F52) | G53: =SUM(臺大:東專!G52) | H53: 增加投資 | I53: 241 | J53: =SUM(臺大:東專!J52) | K53: =-SUMIF($C$7:$C$127,I53,$D$7:$D$127)+SUMIF($E$7:$E$135,I53,$F$7:$F$127) | O53: =L53-B52 | Q53: =D52-F52 | S53: =J53-K53
B54: =SUM(臺大:東專!B53) | D54: =SUM(臺大:東專!D53) | E54: 406 | F54: =SUM(臺大:東專!F53) | G54: =SUM(臺大:東專!G53) | H54: 增加準備金 | I54: 242 | J54: =SUM(臺大:東專!J53) | K54: =-SUMIF($C$7:$C$127,I54,$D$7:$D$127)+SUMIF($E$7:$E$135,I54,$F$7:$F$127) | M54: =L54-G54 | O54: =L54-B53 | Q54: =D53-F53 | S54: =J54-K54
A55: 生物資產－非流動 | B55: =SUM(臺大:東專!B54) | D55: =SUM(臺大:東專!D54) | F55: =SUM(臺大:東專!F54) | G55: =SUM(臺大:東專!G54) | H55: 增加不動產、廠房及設備、礦產資源 | J55: =SUM(臺大:東專!J54) | K55: =K56 | L55: =VLOOKUP(A55,$A$139:$AW$244,$K$1,FALSE) | M55: =L55-G55 | O55: =L55-B54 | Q55: =D54-F54 | S55: =J55-K55
A56: 生產性生物資產－非流動 | B56: =SUM(臺大:東專!B55) | D56: =SUM(臺大:東專!D55) | E56: 109 | F56: =SUM(臺大:東專!F55) | G56: =SUM(臺大:東專!G55) | H56: 增加不動產、廠房及設備 | J56: =SUM(臺大:東專!J55) | K56: =K57 | L56: =VLOOKUP(A56,$A$139:$AW$244,$K$1,FALSE) | M56: =L56-G56 | O56: =L56-B55 | Q56: =D55-F55 | S56: =J56-K56
A57: 無形資產 | B57: =SUM(臺大:東專!B56) | D57: =SUM(臺大:東專!D56) | F57: =SUM(臺大:東專!F56) | G57: =SUM(臺大:東專!G56) | H57: 固定資產之增置 | J57: =SUM(臺大:東專!J56) | K57: =SUM(K58:K64) | L57: =VLOOKUP(A57,$A$139:$AW$244,$K$1,FALSE) | M57: =L57-G57 | O57: =L57-B56 | Q57: =D56-F56 | S57: =J57-K57
A58: 無形資產 | B58: =SUM(臺大:東專!B57) | D58: =SUM(臺大:東專!D57) | E58: 111 | F58: =SUM(臺大:東專!F57) | G58: =SUM(臺大:東專!G57) | H58: 土地改良物 | I58: 251 | J58: =SUM(臺大:東專!J57) | K58: =-SUMIF($C$7:$C$127,I58,$D$7:$D$127)+SUMIF($E$7:$E$127,I58,$F$7:$F$127) | L58: =VLOOKUP(A58,$A$139:$AW$244,$K$1,FALSE) | M58: =L58-G58 | O58: =L58-B57 | Q58: =D57-F57 | S58: =J58-K58
B59: =SUM(臺大:東專!B58) | C59: 415 | D59: =SUM(臺大:東專!D58) | E59: 416 | F59: =SUM(臺大:東專!F58) | G59: =SUM(臺大:東專!G58) | H59: 房屋及建築 | I59: 252 | J59: =SUM(臺大:東專!J58) | K59: =-SUMIF($C$7:$C$127,I59,$D$7:$D$127)+SUMIF($E$7:$E$127,I59,$F$7:$F$127) | O59: =L59-B58 | Q59: =D58-F58 | S59: =J59-K59
B60: =SUM(臺大:東專!B59) | C60: 258 | D60: =SUM(臺大:東專!D59) | E60: 112 | F60: =SUM(臺大:東專!F59) | G60: =SUM(臺大:東專!G59) | H60: 機械及設備 | I60: 253 | J60: =SUM(臺大:東專!J59) | K60: =-SUMIF($C$7:$C$127,I60,$D$7:$D$127)+SUMIF($E$7:$E$127,I60,$F$7:$F$127) | O60: =L60-B59 | Q60: =D59-F59 | S60: =J60-K60
B61: =SUM(臺大:東專!B60) | D61: =SUM(臺大:東專!D60) | F61: =SUM(臺大:東專!F60) | G61: =SUM(臺大:東專!G60) | H61: 交通及運輸設備 | I61: 254 | J61: =SUM(臺大:東專!J60) | K61: =-SUMIF($C$7:$C$127,I61,$D$7:$D$127)+SUMIF($E$7:$E$127,I61,$F$7:$F$127) | O61: =L61-B60 | Q61: =D60-F60 | S61: =J61-K61
A62: 其他資產 | B62: =SUM(臺大:東專!B61) | D62: =SUM(臺大:東專!D61) | F62: =SUM(臺大:東專!F61) | G62: =SUM(臺大:東專!G61) | H62: 什項設備 | I62: 255 | J62: =SUM(臺大:東專!J61) | K62: =-SUMIF($C$7:$C$127,I62,$D$7:$D$127)+SUMIF($E$7:$E$127,I62,$F$7:$F$127) | L62: =VLOOKUP(A62,$A$139:$AW$244,$K$1,FALSE) | M62: =L62-G62 | O62: =L62-B61 | Q62: =D61-F61 | S62: =J62-K62
A63: 遞延資產 | B63: =SUM(臺大:東專!B62) | D63: =SUM(臺大:東專!D62) | E63: 112 | F63: =SUM(臺大:東專!F62) | G63: =SUM(臺大:東專!G62) | H63: 購建中固定資產 | I63: 256 | J63: =SUM(臺大:東專!J62) | K63: =-SUMIF($C$7:$C$127,I63,$D$7:$D$127)+SUMIF($E$7:$E$127,I63,$F$7:$F$127) | L63: =VLOOKUP(A63,$A$139:$AW$244,$K$1,FALSE) | M63: =L63-G63 | O63: =L63-B62 | Q63: =D62-F62 | S63: =J63-K63
B64: =SUM(臺大:東專!B63) | D64: =SUM(臺大:東專!D63) | F64: =SUM(臺大:東專!F63) | G64: =SUM(臺大:東專!G63) | H64: 租賃權益改良 | I64: 257 | J64: =SUM(臺大:東專!J63) | K64: =-SUMIF($C$7:$C$127,I64,$D$7:$D$127)+SUMIF($E$7:$E$127,I64,$F$7:$F$127) | O64: =L64-B63 | Q64: =D63-F63 | S64: =J64-K64
B65: =SUM(臺大:東專!B64) | C65: 259 | D65: =SUM(臺大:東專!D64) | F65: =SUM(臺大:東專!F64) | G65: =SUM(臺大:東專!G64) | H65: 增加無形資產及其他資產 | J65: =SUM(臺大:東專!J64) | K65: =K66+K67 | O65: =L65-B64 | Q65: =D64-F64 | S65: =J65-K65
A66: 什項資產 | B66: =SUM(臺大:東專!B65) | C66: 417 | D66: =SUM(臺大:東專!D65) | E66: 108 | F66: =SUM(臺大:東專!F65) | G66: =SUM(臺大:東專!G65) | H66: 增加無形資產 | I66: 258 | J66: =SUM(臺大:東專!J65) | K66: =-SUMIF($C$7:$C$127,I66,$D$7:$D$127)+SUMIF($E$7:$E$127,I66,$F$7:$F$127) | L66: =VLOOKUP(A66,$A$139:$AW$244,$K$1,FALSE) | M66: =L66-G66 | O66: =L66-B66 | Q66: =D66-F66 | S66: =J66-K66
B67: =SUM(臺大:東專!B66) | D67: =SUM(臺大:東專!D66) | F67: =SUM(臺大:東專!F66) | G67: =SUM(臺大:東專!G66) | H67: 增加其他資產 | J67: =SUM(臺大:東專!J66) | K67: =K68 | O67: =L67-B67 | Q67: =D67-F67 | S67: =J67-K67
B68: =SUM(臺大:東專!B67) | D68: =SUM(臺大:東專!D67) | F68: =SUM(臺大:東專!F67) | G68: =SUM(臺大:東專!G67) | H68: 增加遞延費用 | I68: 259 | J68: =SUM(臺大:東專!J67) | K68: =-SUMIF($C$7:$C$127,I68,$D$7:$D$127)+SUMIF($E$7:$E$127,I68,$F$7:$F$127) | O68: =L68-B68 | Q68: =D68-F68 | S68: =J68-K68
B69: =SUM(臺大:東專!B68) | D69: =SUM(臺大:東專!D68) | F69: =SUM(臺大:東專!F68) | G69: =SUM(臺大:東專!G68) | H69: ▼投資活動之淨現金流入（流出） | J69: =SUM(臺大:東專!J68) | K69: =J69 | O69: =L69-B69 | Q69: =D69-F69 | S69: =J69-K69
A70: 合 計 | B70: =SUM(臺大:東專!B69) | D70: =SUM(臺大:東專!D69) | F70: =SUM(臺大:東專!F69) | G70: =SUM(臺大:東專!G69) | H70: ▼籌資活動之現金流量 | J70: =SUM(臺大:東專!J69) | K70: =K71+K73+K75+K82+K84+K80 | L70: =B246 | M70: =L70-G70 | O70: =L70-B70 | Q70: =D70-F70 | S70: =J70-K70
A71: 負債 | B71: =SUM(臺大:東專!B70) | D71: =SUM(臺大:東專!D70) | F71: =SUM(臺大:東專!F70) | G71: =SUM(臺大:東專!G70) | H71: 增加短期債務、流動金融負債及其他負債 | J71: =SUM(臺大:東專!J70) | K71: =K72 | L71: =VLOOKUP(A71,$A$250:$AW$299,$K$1,FALSE) | M71: =L71-G71 | O71: =L71-B71 | Q71: =D71-F71 | S71: =J71-K71
A72: 流動負債 | B72: =SUM(臺大:東專!B71) | D72: =SUM(臺大:東專!D71) | F72: =SUM(臺大:東專!F71) | G72: =SUM(臺大:東專!G71) | H72: 增加其他負債 | I72: 311 | J72: =SUM(臺大:東專!J71) | K72: =-SUMIF($C$7:$C$127,I72,$D$7:$D$127)+SUMIF($E$7:$E$127,I72,$F$7:$F$127) | L72: =VLOOKUP(A72,$A$250:$AW$299,$K$1,FALSE) | M72: =L72-G72 | O72: =L72-B72 | Q72: =D72-F72 | S72: =J72-K72
A73: 短期債務 | B73: =SUM(臺大:東專!B72) | C73: 322 | D73: =SUM(臺大:東專!D72) | E73: 418 | F73: =SUM(臺大:東專!F72) | G73: =SUM(臺大:東專!G72) | H73: 增加長期負債 | J73: =SUM(臺大:東專!J72) | K73: =K74 | L73: =VLOOKUP(A73,$A$250:$AW$299,$K$1,FALSE) | M73: =L73-G73 | O73: =L73-B73 | Q73: =D73-F73 | S73: =J73-K73
B74: =SUM(臺大:東專!B73) | C74: 316 | D74: =SUM(臺大:東專!D73) | F74: =SUM(臺大:東專!F73) | G74: =SUM(臺大:東專!G73) | H74: 增加長期債務 | I74: 312 | J74: =SUM(臺大:東專!J73) | K74: =-SUMIF($C$7:$C$127,I74,$D$7:$D$127)+SUMIF($E$7:$E$127,I74,$F$7:$F$127) | M74: =L74-G74 | O74: =L74-B73 | Q74: =D73-F73 | S74: =J74-K74
A75: 應付款項 | B75: =SUM(臺大:東專!B74) | D75: =SUM(臺大:東專!D74) | E75: 161 | F75: =SUM(臺大:東專!F74) | G75: =SUM(臺大:東專!G74) | H75: 增加基金、公積及填補短絀 | J75: =SUM(臺大:東專!J74) | K75: =SUM(K76) | L75: =VLOOKUP(A75,$A$250:$AW$299,$K$1,FALSE) | M75: =L75-G75 | O75: =L75-B74 | Q75: =D74-F74 | S75: =J75-K75
B76: =SUM(臺大:東專!B75) | D76: =SUM(臺大:東專!D75) | E76: 418 | F76: =SUM(臺大:東專!F75) | G76: =SUM(臺大:東專!G75) | H76: 增加基金 | J76: =SUM(臺大:東專!J75) | K76: =SUM(K77:K79) | M76: =L76-G76 | O76: =L76-B75 | Q76: =D75-F75 | S76: =J76-K76
A77: 預收款項 | B77: =SUM(臺大:東專!B76) | C77: 161 | D77: =SUM(臺大:東專!D76) | E77: 161 | F77: =SUM(臺大:東專!F76) | G77: =SUM(臺大:東專!G76) | H77: 國庫撥款增置固定資產 | I77: 313 | J77: =SUM(臺大:東專!J76) | K77: =-SUMIF($C$7:$C$127,I77,$D$7:$D$127)+SUMIF($E$7:$E$127,I77,$F$7:$F$127) | L77: =VLOOKUP(A77,$A$250:$AW$299,$K$1,FALSE) | M77: =L77-G77 | O77: =L77-B76 | Q77: =D76-F76 | S77: =J77-K77
B78: =SUM(臺大:東專!B77) | D78: =SUM(臺大:東專!D77) | F78: =SUM(臺大:東專!F77) | G78: =SUM(臺大:東專!G77) | H78: 國庫增撥無形資產 | I78: 314 | J78: =SUM(臺大:東專!J77) | K78: =-SUMIF($C$7:$C$127,I78,$D$7:$D$127)+SUMIF($E$7:$E$127,I78,$F$7:$F$127) | M78: =L78-G78 | O78: =L78-B77 | Q78: =D77-F77 | S78: =J78-K78
A79: 長期負債 | B79: =SUM(臺大:東專!B78) | D79: =SUM(臺大:東專!D78) | F79: =SUM(臺大:東專!F78) | G79: =SUM(臺大:東專!G78) | H79: 國庫增撥遞延資產 | I79: 315 | J79: =SUM(臺大:東專!J78) | K79: =-SUMIF($C$7:$C$127,I79,$D$7:$D$127)+SUMIF($E$7:$E$127,I79,$F$7:$F$127) | L79: =VLOOKUP(A79,$A$250:$AW$299,$K$1,FALSE) | M79: =L79-G79 | O79: =L79-B78 | Q79: =D78-F78 | S79: =J79-K79
H80: 減少短期債務、流動金融負債及其他負債 | J80: =SUM(臺大:東專!J79) | K80: =K81
H81: 減少短期債務 | I81: 316 | J81: =SUM(臺大:東專!J80) | K81: =-SUMIF($C$7:$C$127,I81,$D$7:$D$127)+SUMIF($E$7:$E$127,I81,$F$7:$F$127)
A82: 長期債務 | B82: =SUM(臺大:東專!B81) | C82: 418 | D82: =SUM(臺大:東專!D81) | E82: 312 | F82: =SUM(臺大:東專!F81) | G82: =SUM(臺大:東專!G81) | H82: 減少長期負債 | J82: =SUM(臺大:東專!J81) | K82: =K83 | L82: =VLOOKUP(A82,$A$250:$AW$299,$K$1,FALSE) | M82: =L82-G82 | O82: =L82-B79 | Q82: =D79-F79 | S82: =J82-K82
B83: =SUM(臺大:東專!B82) | C83: 322 | D83: =SUM(臺大:東專!D82) | E83: 406 | F83: =SUM(臺大:東專!F82) | G83: =SUM(臺大:東專!G82) | H83: 減少長期債務 | I83: 322 | J83: =SUM(臺大:東專!J82) | K83: =-SUMIF($C$7:$C$127,I83,$D$7:$D$127)+SUMIF($E$7:$E$127,I83,$F$7:$F$127) | M83: =L83-G83 | S83: =J83-K83
A84: 其他負債 | B84: =SUM(臺大:東專!B83) | D84: =SUM(臺大:東專!D83) | F84: =SUM(臺大:東專!F83) | G84: =SUM(臺大:東專!G83) | H84: 支付利息 | J84: =SUM(臺大:東專!J83) | K84: =J84 | L84: =VLOOKUP(A84,$A$250:$AW$299,$K$1,FALSE) | M84: =L84-G84 | O84: =L84-B82 | Q84: =D82-F82 | S84: =J84-K84
A85: 什項負債 | B85: =SUM(臺大:東專!B84) | C85: 321 | D85: =SUM(臺大:東專!D84) | F85: =SUM(臺大:東專!F84) | G85: =SUM(臺大:東專!G84) | H85: ▼籌資活動之淨現金流入（流出） | J85: =SUM(臺大:東專!J84) | K85: =K70 | L85: =VLOOKUP(A85,$A$250:$AW$299,$K$1,FALSE) | M85: =L85-G85 | O85: =L85-B83 | Q85: =D83-F83 | S85: =J85-K85
B86: =SUM(臺大:東專!B85) | C86: 402 | D86: =SUM(臺大:東專!D85) | E86: 122 | F86: =SUM(臺大:東專!F85) | G86: =SUM(臺大:東專!G85) | H86: ▼現金及約當現金之淨增（淨減） | I86: B | J86: =SUM(臺大:東專!J85) | K86: =J86 | M86: =L86-G86 | O86: =L86-B84 | Q86: =D84-F84 | S86: =J86-K86
B87: =SUM(臺大:東專!B86) | D87: =SUM(臺大:東專!D86) | E87: 401 | F87: =SUM(臺大:東專!F86) | G87: =SUM(臺大:東專!G86) | H87: ▼期初現金及約當現金 | J87: =SUM(臺大:東專!J86) | K87: =B9 | M87: =L87-G87 | O87: =L87-B85 | Q87: =D85-F85 | S87: =J87-K87
B88: =SUM(臺大:東專!B87) | D88: =SUM(臺大:東專!D87) | F88: =SUM(臺大:東專!F87) | G88: =SUM(臺大:東專!G87) | H88: ▼期末現金及約當現金 | J88: =SUM(臺大:東專!J87) | K88: =G9 | M88: =L88-G88 | O88: =L88-B86 | Q88: =D86-F86 | S88: =J88-K88
B89: =SUM(臺大:東專!B88) | D89: =SUM(臺大:東專!D88) | F89: =SUM(臺大:東專!F88) | G89: =SUM(臺大:東專!G88) | H89: ▼不影響現金流量之投資與籌資活動 | J89: =SUM(臺大:東專!J88) | K89: 0 | M89: =L89-G89 | O89: =L89-B87 | Q89: =D87-F87 | S89: =J89-K89
B90: =SUM(臺大:東專!B89) | D90: =SUM(臺大:東專!D89) | F90: =SUM(臺大:東專!F89) | G90: =SUM(臺大:東專!G89) | H90: 退休離職準備金與應付退休及離職金同額增加(+)或減少(-)之金額 | J90: =SUM(臺大:東專!J89) | K90: =K91+K92 | M90: =L90-G90 | O90: =L90-B88 | Q90: =D88-F88 | S90: =J90-K90
A91: 遞延負債 | B91: =SUM(臺大:東專!B90) | C91: 124 | D91: =SUM(臺大:東專!D90) | E91: 311 | F91: =SUM(臺大:東專!F90) | G91: =SUM(臺大:東專!G90) | H91: 退休離職準備金與應付退休及離職金同額增加之金額(+) | I91: 401 | J91: =SUM(臺大:東專!J90) | K91: =(SUMIF($C$7:$C$127,I91,$D$7:$D$127)+SUMIF($E$7:$E$127,I91,$F$7:$F$127))/2 | L91: =VLOOKUP(A91,$A$250:$AW$299,$K$1,FALSE) | M91: =L91-G91 | O91: =L91-B89 | Q91: =D89-F89 | S91: =J91-K91
B92: =SUM(臺大:東專!B91) | C92: 123 | D92: =SUM(臺大:東專!D91) | E92: 403 | F92: =SUM(臺大:東專!F91) | G92: =SUM(臺大:東專!G91) | H92: 退休離職準備金與應付退休及離職金同額減少之金額(-) | I92: 402 | J92: =SUM(臺大:東專!J91) | K92: =-(SUMIF($C$7:$C$127,I92,$D$7:$D$127)+SUMIF($E$7:$E$127,I92,$F$7:$F$127))/2 | M92: =L92-G92 | O92: =L92-B90 | Q92: =D90-F90 | S92: =J92-K92
B93: =SUM(臺大:東專!B92) | D93: =SUM(臺大:東專!D92) | E93: 407 | F93: =SUM(臺大:東專!F92) | G93: =SUM(臺大:東專!G92) | H93: 其他準備金與遞延收入同額增加之金額 | J93: =SUM(臺大:東專!J92) | K93: =K94 | M93: =L93-G93 | O93: =L93-B91 | Q93: =D91-F91 | S93: =J93-K93
B94: =SUM(臺大:東專!B93) | D94: =SUM(臺大:東專!D93) | E94: 408 | F94: =SUM(臺大:東專!F93) | G94: =SUM(臺大:東專!G93) | H94: 其他準備金與遞延收入同額增加之金額 | I94: 403 | J94: =SUM(臺大:東專!J93) | K94: =(SUMIF($C$7:$C$127,I94,$D$7:$D$127)+SUMIF($E$7:$E$127,I94,$F$7:$F$127))/2 | M94: =L94-G94 | O94: =L94-B92 | Q94: =D92-F92 | S94: =J94-K94
E95: 410 | F95: =SUM(臺大:東專!F94) | H95: 以前年度購建中固定資產科目，調整轉入不動產、廠房及設備科目之 | J95: =SUM(臺大:東專!J94) | K95: =K96 | M95: =L95-G95 | O95: =L95-B93 | Q95: =D93-F93 | S95: =J95-K95
B96: =SUM(臺大:東專!B96) | D96: =SUM(臺大:東專!D96) | F96: =SUM(臺大:東專!F95) | G96: =SUM(臺大:東專!G96) | H96: 調整轉入不動產、廠房及設備科目明細 | J96: =SUM(臺大:東專!J95) | K96: =K97+K98+K99 | M96: =L96-G96 | S96: =J96-K96
F97: =SUM(臺大:東專!F96) | H97: 土地改良物 | I97: 404 | J97: =SUM(臺大:東專!J96) | K97: =(SUMIF($C$7:$C$127,I97,$D$7:$D$127)+SUMIF($E$7:$E$127,I97,$F$7:$F$127))/2 | L97: =VLOOKUP(A98,$A$250:$AW$299,$K$1,FALSE) | M97: =L97-G98 | O97: =L97-B94 | Q97: =D94-F94 | S97: =J97-K97
A98: 淨值 | B98: =SUM(臺大:東專!B97) | D98: =SUM(臺大:東專!D97) | F98: =SUM(臺大:東專!F97) | G98: =SUM(臺大:東專!G97) | H98: 房屋及建築 | I98: 405 | J98: =SUM(臺大:東專!J97) | K98: =(SUMIF($C$7:$C$127,I98,$D$7:$D$127)+SUMIF($E$7:$E$127,I98,$F$7:$F$127))/2 | L98: =VLOOKUP(A99,$A$250:$AW$299,$K$1,FALSE) | M98: =L98-G99 | O98: =L98-B96 | Q98: =D96-F96 | S98: =J98-K98
A99: 基金 | B99: =SUM(臺大:東專!B98) | D99: =SUM(臺大:東專!D98) | F99: =SUM(臺大:東專!F98) | G99: =SUM(臺大:東專!G98) | H99: 什項設備 | I99: 406 | J99: =SUM(臺大:東專!J98) | K99: =(SUMIF($C$7:$C$127,I99,$D$7:$D$127)+SUMIF($E$7:$E$127,I99,$F$7:$F$127))/2 | L99: =VLOOKUP(A100,$A$250:$AW$299,$K$1,FALSE) | M99: =L99-G100 | O99: =L99-B98 | Q99: =D98-F98 | S99: =J99-K99
A100: 基金 | B100: =SUM(臺大:東專!B99) | D100: =SUM(臺大:東專!D99) | E100: 313 | F100: =SUM(臺大:東專!F99) | G100: =SUM(臺大:東專!G99) | H100: 不動產、廠房及設備與遞延收入同額增加(+)或減少(-)之金額 | J100: =SUM(臺大:東專!J99) | K100: =K101 | M100: =L100-G101 | O100: =L100-B99 | Q100: =D99-F99 | S100: =J100-K100
...

Sheet 臺大
A1: =OFFSET(A139,0,K1-1) | K1: =L1+2 | L1: 1
A2: 預計平衡表與現金流量表勾稽底稿
A3: 中華民國115年度
A4: 科目 | B4: 114.12.31 | C4: 調整項目 | G4: 115.12.31 | H4: 現金流量表勾稽項目
B5: 預計數 | D5: 借方 | F5: 貸方 | G5: 預計數
A6: 資產 | H6: ▼業務活動之現金流量 | L6: 114年12月 | M6: 差異數要再加(減) | O6: 比較增減 | Q6: 調整項目
A7: 流動資產 | B7: =SUM(B8:B16) | G7: =SUM(G8:G16) | H7: 本期賸餘（短絀） | I7: A | J7: =OFFSET(A480,0,$K$1-1) | K7: =-SUMIF($C$7:$C$127,I7,$D$7:$D$127)+SUMIF($E$7:$E$127,I7,$F$7:$F$127) | L7: =VLOOKUP(A7,$A$140:$AX$249,$K$1,FALSE) | M7: =L7-G7 | O7: =L7-B7 | P7: =J7-K7 | Q7: =D7-F7
A8: 現金 | B8: =VLOOKUP(A8,$A$309:$AX$418,$K$1,FALSE) | C8: B | D8: =IF(G8-B8>0,G8-B8,"0") | E8: B | F8: =IF(G8-B8<0,B8-G8,"0") | G8: =J87 | H8: 利息股利之調整 | J8: =OFFSET(A481,0,$K$1-1) | K8: =SUM(K9:K11) | L8: =VLOOKUP(A8,$A$140:$AX$249,$K$1,FALSE) | M8: =L8-G8 | O8: =L8-B8 | P8: =J8-K8 | Q8: =D8-F8
A9: 流動金融資產 | B9: =VLOOKUP(A9,$A$309:$AX$418,$K$1,FALSE) | C9: 231 | D9: =J50*-1 | E9: 211 | F9: =J42 | G9: =B9+D9-F9+D10-F10 | H9: 利息收入 | J9: =OFFSET(A482,0,$K$1-1) | K9: =J9 | L9: =VLOOKUP(A9,$A$140:$AX$249,$K$1,FALSE) | M9: =L9-G9 | O9: =L9-B9 | P9: =J9-K9 | Q9: =D9-F9
C10: 125 | H10: 股利收入 | J10: =OFFSET(A483,0,$K$1-1) | K10: =J10 | M10: =L10-G10 | O10: =L10-B10 | P10: =J10-K10 | Q10: =D10-F10
A11: 應收款項 | B11: =VLOOKUP(A11,$A$309:$AX$418,$K$1,FALSE) | C11: 151 | E11: 151 | G11: =B11+D11-F11 | H11: 利息費用 | J11: =OFFSET(A484,0,$K$1-1) | K11: =J11 | L11: =VLOOKUP(A11,$A$140:$AX$249,$K$1,FALSE) | M11: =L11-G11 | O11: =L11-B11 | P11: =J11-K11 | Q11: =D11-F11
A12: 0 | H12: 未計利息股利之本期賸餘（短絀） | J12: =OFFSET(A485,0,$K$1-1) | K12: =K7+K8 | M12: =L12-G12 | O12: =L12-B12 | P12: =J12-K12 | Q12: =D12-F12
A13: 存貨 | B13: =VLOOKUP(A13,$A$309:$AX$418,$K$1,FALSE) | C13: 151 | E13: 151 | G13: =B13+D13-F13 | H13: 調整項目 | J13: =OFFSET(A486,0,$K$1-1) | K13: =SUM(K14,K24,K27,K34,K33) | L13: =VLOOKUP(A13,$A$140:$AX$249,$K$1,FALSE) | M13: =L13-G13 | O13: =L13-B13 | P13: =J13-K13 | Q13: =D13-F13
A14: 生產性生物資產－流動 | B14: =VLOOKUP(A14,$A$309:$AX$418,$K$1,FALSE) | C14: 151 | E14: 151 | G14: =B14+D14-F14 | H14: 折舊、減損及折耗 | J14: =OFFSET(A487,0,$K$1-1) | K14: =SUM(K15:K23) | L14: =VLOOKUP(A14,$A$140:$AX$249,$K$1,FALSE) | M14: =L14-G14 | O14: =L14-B14 | P14: =J14-K14 | Q14: =D14-F14
A15: 預付款項 | B15: =VLOOKUP(A15,$A$309:$AX$418,$K$1,FALSE) | C15: 151 | E15: 151 | G15: =B15+D15-F15 | H15: 土地改良物 | I15: 101 | J15: =OFFSET(A488,0,$K$1-1) | K15: =-SUMIF($C$7:$C$127,I15,$D$7:$D$127)+SUMIF($E$7:$E$127,I15,$F$7:$F$127) | L15: =VLOOKUP(A15,$A$140:$AX$249,$K$1,FALSE) | M15: =L15-G15 | O15: =L15-B15 | P15: =J15-K15 | Q15: =D15-F15
A16: 短期貸墊款 | B16: =VLOOKUP(A16,$A$309:$AX$418,$K$1,FALSE) | C16: 151 | E16: 212 | F16: =J43 | G16: =B16+D16-F16 | H16: 房屋及建築 | I16: 102 | J16: =OFFSET(A489,0,$K$1-1) | K16: =-SUMIF($C$7:$C$127,I16,$D$7:$D$127)+SUMIF($E$7:$E$127,I16,$F$7:$F$127) | L16: =VLOOKUP(A16,$A$140:$AX$249,$K$1,FALSE) | M16: =L16-G16 | O16: =L16-B16 | P16: =J16-K16 | Q16: =D16-F16
A17: 投資、長期應收款、貸墊款及準備金 | B17: =SUM(B18:B21) | G17: =SUM(G18:G21) | H17: 機械及設備 | I17: 103 | J17: =OFFSET(A490,0,$K$1-1) | K17: =-SUMIF($C$7:$C$127,I17,$D$7:$D$127)+SUMIF($E$7:$E$127,I17,$F$7:$F$127) | L17: =VLOOKUP(A17,$A$140:$AX$249,$K$1,FALSE) | M17: =L17-G17 | O17: =L17-B17 | P17: =J17-K17 | Q17: =D17-F17
A18: 採權益法之投資 | B18: =VLOOKUP(A18,$A$309:$AX$418,$K$1,FALSE) | G18: =D18+F18+B18 | H18: 交通及運輸設備 | I18: 104 | J18: =OFFSET(A491,0,$K$1-1) | K18: =-SUMIF($C$7:$C$127,I18,$D$7:$D$127)+SUMIF($E$7:$E$127,I18,$F$7:$F$127) | L18: =VLOOKUP(A18,$A$140:$AX$249,$K$1,FALSE) | M18: =L18-G18 | O18: =L18-B18 | P18: =J18-K18 | Q18: =D18-F18
A19: 非流動金融資產 | B19: =VLOOKUP(A19,$A$309:$AX$418,$K$1,FALSE) | C19: 241 | D19: =J52*-1 | E19: 221 | F19: =J45 | G19: =B19+D19-F19 | H19: 什項設備 | I19: 105 | J19: =OFFSET(A492,0,$K$1-1) | K19: =-SUMIF($C$7:$C$127,I19,$D$7:$D$127)+SUMIF($E$7:$E$127,I19,$F$7:$F$127) | L19: =VLOOKUP(A19,$A$140:$AX$249,$K$1,FALSE) | M19: =L19-G19 | O19: =L19-B19 | P19: =J19-K19 | Q19: =D19-F19
A20: 長期應收款 | B20: =VLOOKUP(A20,$A$309:$AX$418,$K$1,FALSE) | G20: =B20+D20-F20 | H20: 租賃資產 | I20: 106 | J20: =OFFSET(A493,0,$K$1-1) | K20: =-SUMIF($C$7:$C$127,I20,$D$7:$D$127)+SUMIF($E$7:$E$127,I20,$F$7:$F$127) | L20: =VLOOKUP(A20,$A$140:$AX$249,$K$1,FALSE) | M20: =L20-G20 | O20: =L20-B20 | P20: =J20-K20 | Q20: =D20-F20
A21: 準備金 | B21: =VLOOKUP(A21,$A$309:$AX$418,$K$1,FALSE) | C21: 242 | D21: =J53*-1 | E21: 222 | F21: =J46 | G21: =B21+SUM(D21:D25)-SUM(F21:F25) | H21: 租賃權益改良 | I21: 107 | J21: =OFFSET(A494,0,$K$1-1) | K21: =-SUMIF($C$7:$C$127,I21,$D$7:$D$127)+SUMIF($E$7:$E$127,I21,$F$7:$F$127) | L21: =VLOOKUP(A21,$A$140:$AX$249,$K$1,FALSE) | M21: =L21-G21 | O21: =L21-B21 | P21: =J21-K21 | Q21: =D21-F21
A22: 0 | C22: 401 | D22: =J90 | E22: 402 | F22: =-J91 | H22: 代管資產 | I22: 108 | J22: =OFFSET(A495,0,$K$1-1) | K22: =-SUMIF($C$7:$C$127,I22,$D$7:$D$127)+SUMIF($E$7:$E$127,I22,$F$7:$F$127) | M22: =L22-G22 | O22: =L22-B22 | P22: =J22-K22 | Q22: =D22-F22
A23: 0 | C23: 403 | D23: =J93 | H23: 生產性生物資產－非流動 | I23: 109 | J23: =OFFSET(A496,0,$K$1-1) | K23: =-SUMIF($C$7:$C$127,I23,$D$7:$D$127)+SUMIF($E$7:$E$127,I23,$F$7:$F$127) | M23: =L23-G23 | O23: =L23-B23 | P23: =J23-K23 | Q23: =D23-F23
A24: 0 | H24: 攤銷 | J24: =OFFSET(A497,0,$K$1-1) | K24: =SUM(K25:K26) | M24: =L24-G24 | O24: =L24-B24 | P24: =J24-K24 | Q24: =D24-F24
C25: 125 | D25: =J32*-1 | H25: 攤銷電腦軟體 | I25: 111 | J25: =OFFSET(A498,0,$K$1-1) | K25: =-SUMIF($C$7:$C$127,I25,$D$7:$D$127)+SUMIF($E$7:$E$127,I25,$F$7:$F$127) | M25: =L25-G25 | O25: =L25-B25 | P25: =J25-K25 | Q25: =D25-F25
A26: 不動產、廠房及設備 | B26: =SUM(B27:B52) | G26: =SUM(G27:G52) | H26: 其他攤銷費用 | I26: 112 | J26: =OFFSET(A499,0,$K$1-1) | K26: =-SUMIF($C$7:$C$127,I26,$D$7:$D$127)+SUMIF($E$7:$E$127,I26,$F$7:$F$127) | L26: =VLOOKUP(A26,$A$140:$AX$249,$K$1,FALSE) | M26: =L26-G26 | O26: =L26-B26 | P26: =J26-K26 | Q26: =D26-F26
A27: 土地 | B27: =VLOOKUP(A27,$A$309:$AX$418,$K$1,FALSE) | C27: 121 | G27: =B27+SUM(D27)-SUM(F27) | H27: 其他 | J27: =OFFSET(A500,0,$K$1-1) | K27: =K28+K29+K32 | L27: =VLOOKUP(A27,$A$140:$AX$249,$K$1,FALSE) | M27: =L27-G27 | O27: =L27-B27 | P27: =J27-K27 | Q27: =D27-F27
A28: 0 | H28: 應付退休及離職金 | I28: 122 | J28: =OFFSET(A501,0,$K$1-1) | K28: =-SUMIF($C$7:$C$127,I28,$D$7:$D$127)+SUMIF($E$7:$E$127,I28,$F$7:$F$127) | M28: =L28-G28 | O28: =L28-B28 | P28: =J28-K28 | Q28: =D28-F28
A29: 土地改良物 | B29: =VLOOKUP(A29,$A$309:$AX$418,$K$1,FALSE) | C29: 251 | D29: =J57*-1 | E29: 101 | F29: =J15 | G29: =B29+SUM(D29:D32)-SUM(F29:F32) | H29: 遞延收入 | J29: =OFFSET(A502,0,$K$1-1) | K29: =SUM(K30:K31) | L29: =VLOOKUP(A29,$A$140:$AX$249,$K$1,FALSE) | M29: =L29-G29 | O29: =L29-B29 | P29: =J29-K29 | Q29: =D29-F29
A30: 0 | C30: 404 | D30: =J96 | H30: 遞延收入-其他補助收入 | I30: 123 | J30: =OFFSET(A503,0,$K$1-1) | K30: =-SUMIF($C$7:$C$127,I30,$D$7:$D$127)+SUMIF($E$7:$E$127,I30,$F$7:$F$127) | M30: =L30-G30 | O30: =L30-B30 | P30: =J30-K30 | Q30: =D30-F30
A31: 0 | H31: 遞延收入-受贈收入 | I31: 124 | J31: =OFFSET(A504,0,$K$1-1) | K31: =-SUMIF($C$7:$C$127,I31,$D$7:$D$127)+SUMIF($E$7:$E$127,I31,$F$7:$F$127) | M31: =L31-G31 | O31: =L31-B31 | P31: =J31-K31 | Q31: =D31-F31
A32: 0 | H32: 其他 | I32: 125 | J32: =OFFSET(A505,0,$K$1-1) | M32: =L32-G32 | O32: =L32-B32 | P32: =J32-K32 | Q32: =D32-F32
A33: 房屋及建築 | B33: =VLOOKUP(A33,$A$309:$AX$418,$K$1,FALSE) | C33: 252 | D33: =J58*-1 | E33: 102 | F33: =J16 | G33: =B33+SUM(D33:D36)-SUM(F33:F36) | H33: 流動資產淨減（淨增） | I33: 151 | J33: =OFFSET(A506,0,$K$1-1) | K33: =-SUMIF($C$7:$C$127,I33,$D$7:$D$127)+SUMIF($E$7:$E$127,I33,$F$7:$F$127) | L33: =VLOOKUP(A33,$A$140:$AX$249,$K$1,FALSE) | M33: =L33-G33 | O33: =L33-B33 | P33: =J33-K33 | Q33: =D33-F33
A34: 0 | C34: 405 | D34: =J97 | H34: 流動負債淨增（淨減） | I34: 161 | J34: =OFFSET(A507,0,$K$1-1) | K34: =-SUMIF($C$7:$C$127,I34,$D$7:$D$127)+SUMIF($E$7:$E$127,I34,$F$7:$F$127) | M34: =L34-G34 | O34: =L34-B34 | P34: =J34-K34 | Q34: =D34-F34
A35: 0 | H35: 未計利息股利之現金流入（流出） | J35: =OFFSET(A508,0,$K$1-1) | K35: =K12+K13 | M35: =L35-G35 | O35: =L35-B35 | P35: =J35-K35 | Q35: =D35-F35
A36: 0 | H36: 收取利息 | J36: =OFFSET(A509,0,$K$1-1) | K36: =J36 | M36: =L36-G36 | O36: =L36-B36 | P36: =J36-K36 | Q36: =D36-F36
A37: 機械及設備 | B37: =VLOOKUP(A37,$A$309:$AX$418,$K$1,FALSE) | C37: 253 | D37: =J59*-1 | E37: 103 | F37: =J17 | G37: =B37+SUM(D37:D41)-SUM(F37:F41) | H37: 收取股利 | J37: =OFFSET(A510,0,$K$1-1) | K37: =J37 | L37: =VLOOKUP(A37,$A$140:$AX$249,$K$1,FALSE) | M37: =L37-G37 | O37: =L37-B37 | P37: =J37-K37 | Q37: =D37-F37
A38: 0 | C38: 407 | D38: =J101 | H38: 支付利息 | J38: =OFFSET(A511,0,$K$1-1) | K38: =J38 | M38: =L38-G38 | O38: =L38-B38 | P38: =J38-K38 | Q38: =D38-F38
A39: 0 | C39: 409 | D39: =J105 | E39: 412 | F39: =-J109 | H39: ▼業務活動之淨現金流入（流出） | J39: =OFFSET(A512,0,$K$1-1) | K39: =K36+K37+K38+K35 | M39: =L39-G39 | O39: =L39-B39 | P39: =J39-K39 | Q39: =D39-F39
A40: 0 | H40: ▼投資活動之現金流量 | J40: =OFFSET(A513,0,$K$1-1) | K40: =SUM(K41,K44,K47,K48,K49,K51,K54,K64) | M40: =L40-G40 | O40: =L40-B40 | P40: =J40-K40 | Q40: =D40-F40
H41: 減少流動金融資產及短期貸墊款 | J41: =OFFSET(A514,0,$K$1-1) | K41: =K42+K43 | M41: =L41-G41 | O41: =L41-B41 | P41: =J41-K41 | Q41: =D41-F41
A42: 交通及運輸設備 | B42: =VLOOKUP(A42,$A$309:$AX$418,$K$1,FALSE) | C42: 254 | D42: =J60*-1 | E42: 104 | F42: =J18 | G42: =B42+SUM(D42:D44)-SUM(F42:F44) | H42: 減少流動金融資產 | I42: 211 | J42: =OFFSET(A515,0,$K$1-1) | K42: =-SUMIF($C$7:$C$127,I42,$D$7:$D$127)+SUMIF($E$7:$E$135,I42,$F$7:$F$127) | L42: =VLOOKUP(A42,$A$140:$AX$249,$K$1,FALSE) | M42: =L42-G42 | O42: =L42-B42 | P42: =J42-K42 | Q42: =D42-F42
C43: 410 | D43: =J106 | E43: 413 | F43: =J110*-1 | H43: 減少短期墊款 | I43: 212 | J43: =OFFSET(A516,0,$K$1-1) | K43: =-SUMIF($C$7:$C$127,I43,$D$7:$D$127)+SUMIF($E$7:$E$135,I43,$F$7:$F$127) | M43: =L43-G43 | O43: =L43-B43 | P43: =J43-K43 | Q43: =D43-F43
H44: 減少投資、長期應收款、貸墊款及準備金 | J44: =OFFSET(A517,0,$K$1-1) | K44: =SUM(K45:K46) | M44: =L44-G44 | O44: =L44-B44 | P44: =J44-K44 | Q44: =D44-F44
A45: 什項設備 | B45: =VLOOKUP(A45,$A$309:$AX$418,$K$1,FALSE) | C45: 255 | D45: =J61*-1 | E45: 105 | F45: =J19 | G45: =B45+SUM(D45:D48)-SUM(F45:F48) | H45: 減少投資 | I45: 221 | J45: =OFFSET(A518,0,$K$1-1) | K45: =-SUMIF($C$7:$C$127,I45,$D$7:$D$127)+SUMIF($E$7:$E$135,I45,$F$7:$F$127) | L45: =VLOOKUP(A45,$A$140:$AX$249,$K$1,FALSE) | M45: =L45-G45 | O45: =L45-B45 | P45: =J45-K45 | Q45: =D45-F45
A46: 0 | C46: 408 | D46: =J102 | H46: 減少準備金 | I46: 222 | J46: =OFFSET(A519,0,$K$1-1) | K46: =-SUMIF($C$7:$C$127,I46,$D$7:$D$127)+SUMIF($E$7:$E$135,I46,$F$7:$F$127) | M46: =L46-G46 | O46: =L46-B46 | P46: =J46-K46 | Q46: =D46-F46
A47: 0 | C47: 411 | D47: =J107 | E47: 414 | F47: =-J111 | H47: 收取利息 | J47: =OFFSET(A520,0,$K$1-1) | K47: =J47 | M47: =L47-G47 | O47: =L47-B47 | P47: =J47-K47 | Q47: =D47-F47
A48: 0 | C48: 406 | D48: =J98 | H48: 收取股利 | J48: =OFFSET(A521,0,$K$1-1) | K48: =J48 | M48: =L48-G48 | O48: =L48-B48 | P48: =J48-K48 | Q48: =D48-F48
A49: 租賃資產 | B49: =VLOOKUP(A49,$A$309:$AX$413,$K$1,FALSE) | E49: 106 | F49: =J20 | G49: =B49+D49-F49 | H49: 增加流動金融資產及短期貸墊款 | J49: =OFFSET(A522,0,$K$1-1) | K49: =K50 | L49: =VLOOKUP(A49,$A$140:$AX$249,$K$1,FALSE) | M49: =L49-G49 | O49: =L49-B49 | P49: =J49-K49 | Q49: =D49-F49
A50: 租賃權益改良 | B50: =VLOOKUP(A50,$A$309:$AX$418,$K$1,FALSE) | C50: 257 | D50: =J63*-1 | E50: 107 | F50: =J21 | G50: =B50+D50-F50 | H50: 增加流動金融資產 | I50: 231 | J50: =OFFSET(A523,0,$K$1-1) | K50: =-SUMIF($C$7:$C$127,I50,$D$7:$D$127)+SUMIF($E$7:$E$135,I50,$F$7:$F$127) | L50: =VLOOKUP(A50,$A$140:$AX$249,$K$1,FALSE) | M50: =L50-G50 | O50: =L50-B49 | P50: =J50-K50 | Q50: =D49-F49
A51: 購建中固定資產 | B51: =VLOOKUP(A51,$A$309:$AX$418,$K$1,FALSE) | C51: 256 | D51: =J62*-1 | E51: 404 | F51: =J96 | G51: =B51+SUM(D51:D53)-SUM(F51:F53) | H51: 增加投資、長期應收款、貸墊款及準備金 | J51: =OFFSET(A524,0,$K$1-1) | K51: =SUM(K52:K53) | L51: =VLOOKUP(A51,$A$140:$AX$249,$K$1,FALSE) | M51: =L51-G51 | O51: =L51-B50 | P51: =J51-K51 | Q51: =D50-F50
E52: 405 | F52: =J97 | H52: 增加投資 | I52: 241 | J52: =OFFSET(A525,0,$K$1-1) | K52: =-SUMIF($C$7:$C$127,I52,$D$7:$D$127)+SUMIF($E$7:$E$135,I52,$F$7:$F$127) | M52: =L52-G52 | O52: =L52-B51 | P52: =J52-K52 | Q52: =D51-F51
E53: 406 | F53: =J98 | H53: 增加準備金 | I53: 242 | J53: =OFFSET(A526,0,$K$1-1) | K53: =-SUMIF($C$7:$C$127,I53,$D$7:$D$127)+SUMIF($E$7:$E$135,I53,$F$7:$F$127) | M53: =L53-G52 | O53: =L53-B52 | P53: =J53-K53 | Q53: =D52-F52
A54: 生物資產－非流動 | B54: =SUM(B55) | G54: =SUM(G55) | H54: 增加不動產、廠房及設備、礦產資源 | J54: =OFFSET(A527,0,$K$1-1) | K54: =K55 | L54: =VLOOKUP(A54,$A$140:$AX$249,$K$1,FALSE) | M54: =L54-G54 | O54: =L54-B54 | P54: =J54-K54 | Q54: =D54-F54
A55: 生產性生物資產－非流動 | B55: =VLOOKUP(A55,$A$309:$AX$418,$K$1,FALSE) | E55: 109 | F55: =J23 | G55: =B55+SUM(D55:D55)-SUM(F55:F55) | H55: 增加不動產、廠房及設備 | J55: =OFFSET(A528,0,$K$1-1) | K55: =K56 | L55: =VLOOKUP(A55,$A$140:$AX$249,$K$1,FALSE) | M55: =L55-G55 | O55: =L55-B55 | P55: =J55-K55 | Q55: =D55-F55
A56: 無形資產 | B56: =SUM(B57) | G56: =SUM(G57) | H56: 固定資產之增置 | J56: =OFFSET(A529,0,$K$1-1) | K56: =SUM(K57:K63) | L56: =VLOOKUP(A56,$A$140:$AX$249,$K$1,FALSE) | M56: =L56-G56 | O56: =L56-B56 | P56: =J56-K56 | Q56: =D56-F56
A57: 無形資產 | B57: =VLOOKUP(A57,$A$309:$AX$418,$K$1,FALSE) | E57: 111 | F57: =J25 | G57: =B57+SUM(D57:D59)-SUM(F57:F59) | H57: 土地改良物 | I57: 251 | J57: =OFFSET(A530,0,$K$1-1) | K57: =-SUMIF($C$7:$C$127,I57,$D$7:$D$127)+SUMIF($E$7:$E$127,I57,$F$7:$F$127) | L57: =VLOOKUP(A57,$A$140:$AX$249,$K$1,FALSE) | M57: =L57-G57 | O57: =L57-B57 | P57: =J57-K57 | Q57: =D57-F57
A58: 0 | C58: 415 | D58: =J113 | E58: 416 | F58: =J114*-1 | H58: 房屋及建築 | I58: 252 | J58: =OFFSET(A531,0,$K$1-1) | K58: =-SUMIF($C$7:$C$127,I58,$D$7:$D$127)+SUMIF($E$7:$E$127,I58,$F$7:$F$127) | M58: =L58-G58 | O58: =L58-B58 | P58: =J58-K58 | Q58: =D58-F58
A59: 0 | C59: 258 | D59: =J65*-1 | E59: 112 | H59: 機械及設備 | I59: 253 | J59: =OFFSET(A532,0,$K$1-1) | K59: =-SUMIF($C$7:$C$127,I59,$D$7:$D$127)+SUMIF($E$7:$E$127,I59,$F$7:$F$127) | M59: =L59-G59 | O59: =L59-B59 | P59: =J59-K59 | Q59: =D59-F59
A60: 0 | H60: 交通及運輸設備 | I60: 254 | J60: =OFFSET(A533,0,$K$1-1) | K60: =-SUMIF($C$7:$C$127,I60,$D$7:$D$127)+SUMIF($E$7:$E$127,I60,$F$7:$F$127) | M60: =L60-G60 | O60: =L60-B60 | P60: =J60-K60 | Q60: =D60-F60
A61: 其他資產 | B61: =SUM(B62,B65,B68) | G61: =SUM(G62,G65,G68) | H61: 什項設備 | I61: 255 | J61: =OFFSET(A534,0,$K$1-1) | K61: =-SUMIF($C$7:$C$127,I61,$D$7:$D$127)+SUMIF($E$7:$E$127,I61,$F$7:$F$127) | L61: =VLOOKUP(A61,$A$140:$AX$249,$K$1,FALSE) | M61: =L61-G61 | O61: =L61-B61 | P61: =J61-K61 | Q61: =D61-F61
A62: 遞延資產 | B62: =VLOOKUP(A62,$A$309:$AX$418,$K$1,FALSE) | E62: 112 | F62: =J26-F59 | G62: =B62+SUM(D62:D64)-SUM(F62:F64) | H62: 購建中固定資產 | I62: 256 | J62: =OFFSET(A535,0,$K$1-1) | K62: =-SUMIF($C$7:$C$127,I62,$D$7:$D$127)+SUMIF($E$7:$E$127,I62,$F$7:$F$127) | L62: =VLOOKUP(A62,$A$140:$AX$249,$K$1,FALSE) | M62: =L62-G62 | O62: =L62-B62 | P62: =J62-K62 | Q62: =D62-F62
A63: 0 | D63: =J126 | F63: =J127*-1 | H63: 租賃權益改良 | I63: 257 | J63: =OFFSET(A536,0,$K$1-1) | K63: =-SUMIF($C$7:$C$127,I63,$D$7:$D$127)+SUMIF($E$7:$E$127,I63,$F$7:$F$127) | M63: =L63-G63 | O63: =L63-B63 | P63: =J63-K63 | Q63: =D63-F63
A64: 0 | C64: 259 | D64: =J67*-1 | H64: 增加無形資產及其他資產 | J64: =OFFSET(A537,0,$K$1-1) | K64: =K65+K66 | M64: =L64-G64 | O64: =L64-B64 | P64: =J64-K64 | Q64: =D64-F64
A65: 什項資產 | B65: =VLOOKUP(A65,$A$309:$AX$418,$K$1,FALSE) | C65: 417 | D65: =F111 | E65: 108 | F65: =J22 | G65: =B65+SUM(D65:D67)-SUM(F65:F67) | H65: 增加無形資產 | I65: 258 | J65: =OFFSET(A538,0,$K$1-1) | K65: =-SUMIF($C$7:$C$127,I65,$D$7:$D$127)+SUMIF($E$7:$E$127,I65,$F$7:$F$127) | L65: =VLOOKUP(A65,$A$140:$AX$249,$K$1,FALSE) | M65: =L65-G65 | O65: =L65-B65 | P65: =J65-K65 | Q65: =D65-F65
A66: 0 | H66: 增加其他資產 | J66: =OFFSET(A539,0,$K$1-1) | K66: =K67 | M66: =L66-G66 | O66: =L66-B66 | P66: =J66-K66 | Q66: =D66-F66
A67: 0 | H67: 增加遞延費用 | I67: 259 | J67: =OFFSET(A540,0,$K$1-1) | K67: =-SUMIF($C$7:$C$127,I67,$D$7:$D$127)+SUMIF($E$7:$E$127,I67,$F$7:$F$127) | M67: =L67-G67 | O67: =L67-B67 | P67: =J67-K67 | Q67: =D67-F67
G68: =B68+D68-F68 | H68: ▼投資活動之淨現金流入（流出） | J68: =OFFSET(A541,0,$K$1-1) | K68: =K40 | P68: =J68-K68 | Q68: =D68-F68
A69: 合 計 | B69: =B7+B17+B26+B54+B56+B61 | G69: =G7+G17+G26+G54+G56+G61 | H69: ▼籌資活動之現金流量 | J69: =OFFSET(A542,0,$K$1-1) | K69: =K70+K72+K74+K81+K79+K83 | L69: =VLOOKUP(A69,$A$140:$AX$249,$K$1,FALSE) | M69: =L69-G69 | O69: =L69-B69 | P69: =J69-K69 | Q69: =D69-F69
A70: 負債 | B70: =B71+B78+B83 | G70: =G71+G78+G83 | H70: 增加短期債務、流動金融負債及其他負債 | J70: =OFFSET(A543,0,$K$1-1) | K70: =K71 | L70: =VLOOKUP(A70,$A$253:$AX$305,$K$1,FALSE) | M70: =L70-G70 | O70: =L70-B70 | P70: =J70-K70 | Q70: =D70-F70
A71: 流動負債 | B71: =SUM(B72:B77) | G71: =SUM(G72:G77) | H71: 增加其他負債 | I71: 311 | J71: =OFFSET(A544,0,$K$1-1) | K71: =-SUMIF($C$7:$C$127,I71,$D$7:$D$127)+SUMIF($E$7:$E$127,I71,$F$7:$F$127) | L71: =VLOOKUP(A71,$A$253:$AX$305,$K$1,FALSE) | M71: =L71-G71 | O71: =L71-B71 | P71: =J71-K71 | Q71: =D71-F71
A72: 短期債務 | B72: =VLOOKUP(A72,$A$423:$AX$475,$K$1,FALSE) | C72: 322 | D72: =J82*-1 | E72: 418 | F72: =D81 | G72: =B72+SUM(F72:F73)-SUM(D72:D73) | H72: 增加長期負債 | J72: =OFFSET(A545,0,$K$1-1) | K72: =K73 | L72: =VLOOKUP(A72,$A$253:$AX$305,$K$1,FALSE) | M72: =L72-G72 | O72: =L72-B72 | P72: =J72-K72 | Q72: =D72-F72
A73: 0 | C73: 316 | H73: 增加長期債務 | I73: 312 | J73: =OFFSET(A546,0,$K$1-1) | K73: =-SUMIF($C$7:$C$127,I73,$D$7:$D$127)+SUMIF($E$7:$E$127,I73,$F$7:$F$127) | M73: =L73-G73 | O73: =L73-B73 | P73: =J73-K73 | Q73: =D73-F73
A74: 應付款項 | B74: =VLOOKUP(A74,$A$423:$AX$475,$K$1,FALSE) | E74: 161 | G74: =B74+SUM(F74:F75)-SUM(D74:D75) | H74: 增加基金、公積及填補短絀 | J74: =OFFSET(A547,0,$K$1-1) | K74: =SUM(K75) | L74: =VLOOKUP(A74,$A$253:$AX$305,$K$1,FALSE) | M74: =L74-G74 | O74: =L74-B74 | P74: =J74-K74 | Q74: =D74-F74
A75: 0 | H75: 增加基金 | J75: =OFFSET(A548,0,$K$1-1) | K75: =SUM(K76:K78) | M75: =L75-G75 | O75: =L75-B75 | P75: =J75-K75 | Q75: =D75-F75
A76: 預收款項 | B76: =VLOOKUP(A76,$A$423:$AX$475,$K$1,FALSE) | E76: 161 | F76: =J34 | G76: =B76+SUM(F76:F77)-SUM(D76:D77) | H76: 國庫撥款增置固定資產 | I76: 313 | J76: =OFFSET(A549,0,$K$1-1) | K76: =-SUMIF($C$7:$C$127,I76,$D$7:$D$127)+SUMIF($E$7:$E$127,I76,$F$7:$F$127) | L76: =VLOOKUP(A76,$A$253:$AX$305,$K$1,FALSE) | M76: =L76-G76 | O76: =L76-B76 | P76: =J76-K76 | Q76: =D76-F76
A77: 0 | H77: 國庫增撥無形資產 | I77: 314 | J77: =OFFSET(A550,0,$K$1-1) | K77: =-SUMIF($C$7:$C$127,I77,$D$7:$D$127)+SUMIF($E$7:$E$127,I77,$F$7:$F$127) | M77: =L77-G77 | O77: =L77-B77 | P77: =J77-K77 | Q77: =D77-F77
A78: 長期負債 | B78: =SUM(B81) | G78: =SUM(G81) | H78: 國庫增撥遞延資產 | I78: 315 | J78: =OFFSET(A551,0,$K$1-1) | K78: =-SUMIF($C$7:$C$127,I78,$D$7:$D$127)+SUMIF($E$7:$E$127,I78,$F$7:$F$127) | L78: =VLOOKUP(A78,$A$253:$AX$305,$K$1,FALSE) | M78: =L78-G78 | O78: =L78-B78 | P78: =J78-K78 | Q78: =D78-F78
H79: 減少短期債務、流動金融負債及其他負債 | J79: =OFFSET(A552,0,$K$1-1)
H80: 減少短期債務 | I80: 316 | J80: =OFFSET(A553,0,$K$1-1) | K80: =-SUMIF($C$7:$C$127,I80,$D$7:$D$127)+SUMIF($E$7:$E$127,I80,$F$7:$F$127)
A81: 長期債務 | B81: =VLOOKUP(A81,$A$423:$AX$475,$K$1,FALSE) | C81: 418 | D81: =J116 | E81: 312 | F81: =J73 | G81: =B81+SUM(F81:F82)-SUM(D81:D82) | H81: 減少長期負債 | J81: =OFFSET(A554,0,$K$1-1) | K81: =K82 | L81: =VLOOKUP(A81,$A$253:$AX$305,$K$1,FALSE) | M81: =L81-G81 | O81: =L81-B81 | P81: =J81-K81 | Q81: =D81-F81
A82: 0 | C82: 322 | H82: 減少長期債務 | I82: 322 | J82: =OFFSET(A555,0,$K$1-1) | K82: =-SUMIF($C$7:$C$127,I82,$D$7:$D$127)+SUMIF($E$7:$E$127,I82,$F$7:$F$127) | M82: =L82-G82 | O82: =L82-B82 | P82: =J82-K82 | Q82: =D72-F82
A83: 其他負債 | B83: =SUM(B84,B90) | G83: =SUM(G84,G90) | H83: 支付利息 | J83: =OFFSET(A556,0,$K$1-1) | K83: =J83 | L83: =VLOOKUP(A83,$A$253:$AX$305,$K$1,FALSE) | M83: =L83-G83 | O83: =L83-B83 | P83: =J83-K83 | Q83: =D83-F83
A84: 什項負債 | B84: =VLOOKUP(A84,$A$423:$AX$475,$K$1,FALSE) | C84: 321 | G84: =B84+SUM(F84:F89)-SUM(D84:D89) | H84: ▼籌資活動之淨現金流入（流出） | J84: =OFFSET(A557,0,$K$1-1) | K84: =K69 | L84: =VLOOKUP(A84,$A$253:$AX$305,$K$1,FALSE) | M84: =L84-G84 | O84: =L84-B84 | P84: =J84-K84 | Q84: =D84-F84
A85: 0 | C85: 402 | D85: =J91*-1 | E85: 122 | F85: =J28 | H85: ▼現金及約當現金之淨增（淨減） | I85: B | J85: =OFFSET(A558,0,$K$1-1) | K85: =J85 | M85: =L85-G85 | O85: =L85-B85 | P85: =J85-K85 | Q85: =D85-F85
A86: 0 | E86: 401 | F86: =J90 | H86: ▼期初現金及約當現金 | J86: =OFFSET(A559,0,$K$1-1) | K86: =B8 | M86: =L86-G86 | O86: =L86-B86 | P86: =J86-K86 | Q86: =D86-F86
A87: 0 | H87: ▼期末現金及約當現金 | J87: =OFFSET(A560,0,$K$1-1) | K87: =G8 | M87: =L87-G87 | O87: =L87-B87 | P87: =J87-K87 | Q87: =D87-F87
A88: 0 | H88: ▼不影響現金流量之投資與籌資活動 | J88: =OFFSET(A561,0,$K$1-1) | M88: =L88-G88 | O88: =L88-B88 | P88: =J88-K88 | Q88: =D88-F88
A89: 0 | H89: 退休離職準備金與應付退休及離職金同額增加(+)或減少(-)之金額 | J89: =OFFSET(A562,0,$K$1-1) | K89: =K90+K91 | M89: =L89-G89 | O89: =L89-B89 | P89: =J89-K89 | Q89: =D89-F89
A90: 遞延負債 | B90: =VLOOKUP(A90,$A$423:$AX$475,$K$1,FALSE) | C90: 124 | D90: =J31*-1 | E90: 311 | F90: =J71 | G90: =B90+SUM(F90:F96)-SUM(D90:D96) | H90: 退休離職準備金與應付退休及離職金同額增加之金額(+) | I90: 401 | J90: =OFFSET(A563,0,$K$1-1) | K90: =(SUMIF($C$7:$C$127,I90,$D$7:$D$127)+SUMIF($E$7:$E$127,I90,$F$7:$F$127))/2 | L90: =VLOOKUP(A90,$A$253:$AX$305,$K$1,FALSE) | M90: =L90-G90 | O90: =L90-B90 | P90: =J90-K90 | Q90: =D90-F90
A91: 0 | C91: 123 | D91: =-J30 | E91: 403 | F91: =J93 | H91: 退休離職準備金與應付退休及離職金同額減少之金額(-) | I91: 402 | J91: =OFFSET(A564,0,$K$1-1) | K91: =(SUMIF($C$7:$C$127,I91,$D$7:$D$127)+SUMIF($E$7:$E$127,I91,$F$7:$F$127))/2*-1 | M91: =L91-G91 | O91: =L91-B91 | P91: =J91-K91 | Q91: =D91-F91
A92: 0 | E92: 407 | F92: =J101 | H92: 其他準備金與遞延收入同額增加之金額 | J92: =OFFSET(A565,0,$K$1-1) | K92: =K93 | M92: =L92-G92 | O92: =L92-B92 | P92: =J92-K92 | Q92: =D92-F92
A93: 0 | E93: 408 | F93: =J102 | H93: 其他準備金與遞延收入同額增加之金額 | I93: 403 | J93: =OFFSET(A566,0,$K$1-1) | K93: =(SUMIF($C$7:$C$127,I93,$D$7:$D$127)+SUMIF($E$7:$E$127,I93,$F$7:$F$127))/2 | M93: =L93-G93 | O93: =L93-B93 | P93: =J93-K93 | Q93: =D93-F93
E94: 410 | H94: 以前年度購建中固定資產科目，調整轉入不動產、廠房及設備科目之 | J94: =OFFSET(A567,0,$K$1-1) | K94: =K95 | P94: =J94-K94
H95: 調整轉入不動產、廠房及設備科目明細 | J95: =OFFSET(A568,0,$K$1-1) | K95: =K96+K97+K98 | O95: =L95-B96 | P95: =J95-K95 | Q95: =D96-F96
A96: 0 | H96: 土地改良物 | I96: 404 | J96: =OFFSET(A569,0,$K$1-1) | K96: =(SUMIF($C$7:$C$127,I96,$D$7:$D$127)+SUMIF($E$7:$E$127,I96,$F$7:$F$127))/2 | O96: =L97-B97 | P96: =J96-K96 | Q96: =D97-F97
A97: 淨值 | B97: =B98+B110+B116+B125 | G97: =G98+G110+G116+G125 | H97: 房屋及建築 | I97: 405 | J97: =OFFSET(A570,0,$K$1-1) | K97: =(SUMIF($C$7:$C$127,I97,$D$7:$D$127)+SUMIF($E$7:$E$127,I97,$F$7:$F$127))/2 | L97: =VLOOKUP(A97,$A$253:$AX$305,$K$1,FALSE) | M97: =L97-G97 | O97: =L98-B98 | P97: =J97-K97 | Q97: =D98-F98
A98: 基金 | B98: =SUM(B99:B101) | G98: =SUM(G99:G101) | H98: 什項設備 | I98: 406 | J98: =OFFSET(A571,0,$K$1-1) | K98: =(SUMIF($C$7:$C$127,I98,$D$7:$D$127)+SUMIF($E$7:$E$127,I98,$F$7:$F$127))/2 | L98: =VLOOKUP(A98,$A$253:$AX$305,$K$1,FALSE) | M98: =L98-G98 | O98: =L99-B99 | P98: =J98-K98 | Q98: =D99-F99
A99: 基金 | B99: =VLOOKUP(A99,$A$423:$AX$475,$K$1,FALSE) | E99: 313 | F99: =J76 | G99: =B99+SUM(F99:F109)-SUM(D99:D109) | H99: 不動產、廠房及設備與遞延收入同額增加(+)或減少(-)之金額 | J99: =OFFSET(A572,0,$K$1-1) | K99: =K100 | L99: =VLOOKUP(A99,$A$253:$AX$305,$K$1,FALSE) | M99: =L99-G99 | O99: =L100-B100 | P99: =J99-K99 | Q99: =D100-F100
A100: 0 | E100: 314 | F100: =J77 | H100: 不動產、廠房及設備與遞延收入同額增加明細(+) | J100: =OFFSET(A573,0,$K$1-1) | K100: =K101+K102 | M100: =L100-G100 | O100: =L101-B101 | P100: =J100-K100 | Q100: =D101-F101
...

Sheet 政大
A1: =OFFSET(A139,0,K1-1) | K1: =L1+2 | L1: 2
A2: 預計平衡表與現金流量表勾稽底稿
A3: 中華民國115年度
A4: 科目 | B4: 114.12.31 | C4: 調整項目 | G4: 115.12.31 | H4: 現金流量表勾稽項目
B5: 預計數 | D5: 借方 | F5: 貸方 | G5: 預計數
A6: 資產 | H6: ▼業務活動之現金流量 | L6: 114年12月 | M6: 差異數要再加(減) | O6: 比較增減 | Q6: 調整項目
A7: 流動資產 | B7: =SUM(B8:B16) | G7: =SUM(G8:G16) | H7: 本期賸餘（短絀） | I7: A | J7: =OFFSET(A480,0,$K$1-1) | K7: =-SUMIF($C$7:$C$127,I7,$D$7:$D$127)+SUMIF($E$7:$E$127,I7,$F$7:$F$127) | L7: =VLOOKUP(A7,$A$140:$AX$249,$K$1,FALSE) | M7: =L7-G7 | O7: =L7-B7 | P7: =J7-K7 | Q7: =D7-F7
A8: 現金 | B8: =VLOOKUP(A8,$A$309:$AX$418,$K$1,FALSE) | C8: B | D8: =IF(G8-B8>0,G8-B8,"0") | E8: B | F8: =IF(G8-B8<0,B8-G8,"0") | G8: =J87 | H8: 利息股利之調整 | J8: =OFFSET(A481,0,$K$1-1) | K8: =SUM(K9:K11) | L8: =VLOOKUP(A8,$A$140:$AX$249,$K$1,FALSE) | M8: =L8-G8 | O8: =L8-B8 | P8: =J8-K8 | Q8: =D8-F8
A9: 流動金融資產 | B9: =VLOOKUP(A9,$A$309:$AX$418,$K$1,FALSE) | C9: 231 | D9: =J50*-1 | E9: 211 | F9: =J42 | G9: =B9+D9-F9+D10-F10 | H9: 利息收入 | J9: =OFFSET(A482,0,$K$1-1) | K9: =J9 | L9: =VLOOKUP(A9,$A$140:$AX$249,$K$1,FALSE) | M9: =L9-G9 | O9: =L9-B9 | P9: =J9-K9 | Q9: =D9-F9
C10: 125 | H10: 股利收入 | J10: =OFFSET(A483,0,$K$1-1) | K10: =J10 | M10: =L10-G10 | O10: =L10-B10 | P10: =J10-K10 | Q10: =D10-F10
A11: 應收款項 | B11: =VLOOKUP(A11,$A$309:$AX$418,$K$1,FALSE) | C11: 151 | E11: 151 | G11: =B11+D11-F11 | H11: 利息費用 | J11: =OFFSET(A484,0,$K$1-1) | K11: =J11 | L11: =VLOOKUP(A11,$A$140:$AX$249,$K$1,FALSE) | M11: =L11-G11 | O11: =L11-B11 | P11: =J11-K11 | Q11: =D11-F11
A12: 0 | H12: 未計利息股利之本期賸餘（短絀） | J12: =OFFSET(A485,0,$K$1-1) | K12: =K7+K8 | M12: =L12-G12 | O12: =L12-B12 | P12: =J12-K12 | Q12: =D12-F12
A13: 存貨 | B13: =VLOOKUP(A13,$A$309:$AX$418,$K$1,FALSE) | C13: 151 | E13: 151 | G13: =B13+D13-F13 | H13: 調整項目 | J13: =OFFSET(A486,0,$K$1-1) | K13: =SUM(K14,K24,K27,K34,K33) | L13: =VLOOKUP(A13,$A$140:$AX$249,$K$1,FALSE) | M13: =L13-G13 | O13: =L13-B13 | P13: =J13-K13 | Q13: =D13-F13
A14: 生產性生物資產－流動 | B14: =VLOOKUP(A14,$A$309:$AX$418,$K$1,FALSE) | C14: 151 | E14: 151 | G14: =B14+D14-F14 | H14: 折舊、減損及折耗 | J14: =OFFSET(A487,0,$K$1-1) | K14: =SUM(K15:K23) | L14: =VLOOKUP(A14,$A$140:$AX$249,$K$1,FALSE) | M14: =L14-G14 | O14: =L14-B14 | P14: =J14-K14 | Q14: =D14-F14
A15: 預付款項 | B15: =VLOOKUP(A15,$A$309:$AX$418,$K$1,FALSE) | C15: 151 | E15: 151 | G15: =B15+D15-F15 | H15: 土地改良物 | I15: 101 | J15: =OFFSET(A488,0,$K$1-1) | K15: =-SUMIF($C$7:$C$127,I15,$D$7:$D$127)+SUMIF($E$7:$E$127,I15,$F$7:$F$127) | L15: =VLOOKUP(A15,$A$140:$AX$249,$K$1,FALSE) | M15: =L15-G15 | O15: =L15-B15 | P15: =J15-K15 | Q15: =D15-F15
A16: 短期貸墊款 | B16: =VLOOKUP(A16,$A$309:$AX$418,$K$1,FALSE) | C16: 151 | E16: 212 | F16: =J43 | G16: =B16+D16-F16 | H16: 房屋及建築 | I16: 102 | J16: =OFFSET(A489,0,$K$1-1) | K16: =-SUMIF($C$7:$C$127,I16,$D$7:$D$127)+SUMIF($E$7:$E$127,I16,$F$7:$F$127) | L16: =VLOOKUP(A16,$A$140:$AX$249,$K$1,FALSE) | M16: =L16-G16 | O16: =L16-B16 | P16: =J16-K16 | Q16: =D16-F16
A17: 投資、長期應收款、貸墊款及準備金 | B17: =SUM(B18:B21) | G17: =SUM(G18:G21) | H17: 機械及設備 | I17: 103 | J17: =OFFSET(A490,0,$K$1-1) | K17: =-SUMIF($C$7:$C$127,I17,$D$7:$D$127)+SUMIF($E$7:$E$127,I17,$F$7:$F$127) | L17: =VLOOKUP(A17,$A$140:$AX$249,$K$1,FALSE) | M17: =L17-G17 | O17: =L17-B17 | P17: =J17-K17 | Q17: =D17-F17
A18: 採權益法之投資 | B18: =VLOOKUP(A18,$A$309:$AX$418,$K$1,FALSE) | G18: =D18+F18+B18 | H18: 交通及運輸設備 | I18: 104 | J18: =OFFSET(A491,0,$K$1-1) | K18: =-SUMIF($C$7:$C$127,I18,$D$7:$D$127)+SUMIF($E$7:$E$127,I18,$F$7:$F$127) | L18: =VLOOKUP(A18,$A$140:$AX$249,$K$1,FALSE) | M18: =L18-G18 | O18: =L18-B18 | P18: =J18-K18 | Q18: =D18-F18
A19: 非流動金融資產 | B19: =VLOOKUP(A19,$A$309:$AX$418,$K$1,FALSE) | C19: 241 | D19: =J52*-1 | E19: 221 | F19: =J45 | G19: =B19+D19-F19 | H19: 什項設備 | I19: 105 | J19: =OFFSET(A492,0,$K$1-1) | K19: =-SUMIF($C$7:$C$127,I19,$D$7:$D$127)+SUMIF($E$7:$E$127,I19,$F$7:$F$127) | L19: =VLOOKUP(A19,$A$140:$AX$249,$K$1,FALSE) | M19: =L19-G19 | O19: =L19-B19 | P19: =J19-K19 | Q19: =D19-F19
A20: 長期應收款 | B20: =VLOOKUP(A20,$A$309:$AX$418,$K$1,FALSE) | G20: =B20+D20-F20 | H20: 租賃資產 | I20: 106 | J20: =OFFSET(A493,0,$K$1-1) | K20: =-SUMIF($C$7:$C$127,I20,$D$7:$D$127)+SUMIF($E$7:$E$127,I20,$F$7:$F$127) | L20: =VLOOKUP(A20,$A$140:$AX$249,$K$1,FALSE) | M20: =L20-G20 | O20: =L20-B20 | P20: =J20-K20 | Q20: =D20-F20
A21: 準備金 | B21: =VLOOKUP(A21,$A$309:$AX$418,$K$1,FALSE) | C21: 242 | D21: =J53*-1 | E21: 222 | F21: =J46 | G21: =B21+SUM(D21:D25)-SUM(F21:F25) | H21: 租賃權益改良 | I21: 107 | J21: =OFFSET(A494,0,$K$1-1) | K21: =-SUMIF($C$7:$C$127,I21,$D$7:$D$127)+SUMIF($E$7:$E$127,I21,$F$7:$F$127) | L21: =VLOOKUP(A21,$A$140:$AX$249,$K$1,FALSE) | M21: =L21-G21 | O21: =L21-B21 | P21: =J21-K21 | Q21: =D21-F21
A22: 0 | C22: 401 | D22: =J90 | E22: 402 | F22: =-J91 | H22: 代管資產 | I22: 108 | J22: =OFFSET(A495,0,$K$1-1) | K22: =-SUMIF($C$7:$C$127,I22,$D$7:$D$127)+SUMIF($E$7:$E$127,I22,$F$7:$F$127) | M22: =L22-G22 | O22: =L22-B22 | P22: =J22-K22 | Q22: =D22-F22
A23: 0 | C23: 403 | D23: =J93 | H23: 生產性生物資產－非流動 | I23: 109 | J23: =OFFSET(A496,0,$K$1-1) | K23: =-SUMIF($C$7:$C$127,I23,$D$7:$D$127)+SUMIF($E$7:$E$127,I23,$F$7:$F$127) | M23: =L23-G23 | O23: =L23-B23 | P23: =J23-K23 | Q23: =D23-F23
A24: 0 | H24: 攤銷 | J24: =OFFSET(A497,0,$K$1-1) | K24: =SUM(K25:K26) | M24: =L24-G24 | O24: =L24-B24 | P24: =J24-K24 | Q24: =D24-F24
C25: 125 | D25: =J32*-1 | H25: 攤銷電腦軟體 | I25: 111 | J25: =OFFSET(A498,0,$K$1-1) | K25: =-SUMIF($C$7:$C$127,I25,$D$7:$D$127)+SUMIF($E$7:$E$127,I25,$F$7:$F$127) | M25: =L25-G25 | O25: =L25-B25 | P25: =J25-K25 | Q25: =D25-F25
A26: 不動產、廠房及設備 | B26: =SUM(B27:B52) | G26: =SUM(G27:G52) | H26: 其他攤銷費用 | I26: 112 | J26: =OFFSET(A499,0,$K$1-1) | K26: =-SUMIF($C$7:$C$127,I26,$D$7:$D$127)+SUMIF($E$7:$E$127,I26,$F$7:$F$127) | L26: =VLOOKUP(A26,$A$140:$AX$249,$K$1,FALSE) | M26: =L26-G26 | O26: =L26-B26 | P26: =J26-K26 | Q26: =D26-F26
A27: 土地 | B27: =VLOOKUP(A27,$A$309:$AX$418,$K$1,FALSE) | C27: 121 | G27: =B27+SUM(D27)-SUM(F27) | H27: 其他 | J27: =OFFSET(A500,0,$K$1-1) | K27: =K28+K29+K32 | L27: =VLOOKUP(A27,$A$140:$AX$249,$K$1,FALSE) | M27: =L27-G27 | O27: =L27-B27 | P27: =J27-K27 | Q27: =D27-F27
A28: 0 | H28: 應付退休及離職金 | I28: 122 | J28: =OFFSET(A501,0,$K$1-1) | K28: =-SUMIF($C$7:$C$127,I28,$D$7:$D$127)+SUMIF($E$7:$E$127,I28,$F$7:$F$127) | M28: =L28-G28 | O28: =L28-B28 | P28: =J28-K28 | Q28: =D28-F28
A29: 土地改良物 | B29: =VLOOKUP(A29,$A$309:$AX$418,$K$1,FALSE) | C29: 251 | D29: =J57*-1 | E29: 101 | F29: =J15 | G29: =B29+SUM(D29:D32)-SUM(F29:F32) | H29: 遞延收入 | J29: =OFFSET(A502,0,$K$1-1) | K29: =SUM(K30:K31) | L29: =VLOOKUP(A29,$A$140:$AX$249,$K$1,FALSE) | M29: =L29-G29 | O29: =L29-B29 | P29: =J29-K29 | Q29: =D29-F29
A30: 0 | C30: 404 | D30: =J96 | H30: 遞延收入-其他補助收入 | I30: 123 | J30: =OFFSET(A503,0,$K$1-1) | K30: =-SUMIF($C$7:$C$127,I30,$D$7:$D$127)+SUMIF($E$7:$E$127,I30,$F$7:$F$127) | M30: =L30-G30 | O30: =L30-B30 | P30: =J30-K30 | Q30: =D30-F30
A31: 0 | H31: 遞延收入-受贈收入 | I31: 124 | J31: =OFFSET(A504,0,$K$1-1) | K31: =-SUMIF($C$7:$C$127,I31,$D$7:$D$127)+SUMIF($E$7:$E$127,I31,$F$7:$F$127) | M31: =L31-G31 | O31: =L31-B31 | P31: =J31-K31 | Q31: =D31-F31
A32: 0 | H32: 其他 | I32: 125 | J32: =OFFSET(A505,0,$K$1-1) | M32: =L32-G32 | O32: =L32-B32 | P32: =J32-K32 | Q32: =D32-F32
A33: 房屋及建築 | B33: =VLOOKUP(A33,$A$309:$AX$418,$K$1,FALSE) | C33: 252 | D33: =J58*-1 | E33: 102 | F33: =J16 | G33: =B33+SUM(D33:D36)-SUM(F33:F36) | H33: 流動資產淨減（淨增） | I33: 151 | J33: =OFFSET(A506,0,$K$1-1) | K33: =-SUMIF($C$7:$C$127,I33,$D$7:$D$127)+SUMIF($E$7:$E$127,I33,$F$7:$F$127) | L33: =VLOOKUP(A33,$A$140:$AX$249,$K$1,FALSE) | M33: =L33-G33 | O33: =L33-B33 | P33: =J33-K33 | Q33: =D33-F33
A34: 0 | C34: 405 | D34: =J97 | H34: 流動負債淨增（淨減） | I34: 161 | J34: =OFFSET(A507,0,$K$1-1) | K34: =-SUMIF($C$7:$C$127,I34,$D$7:$D$127)+SUMIF($E$7:$E$127,I34,$F$7:$F$127) | M34: =L34-G34 | O34: =L34-B34 | P34: =J34-K34 | Q34: =D34-F34
A35: 0 | H35: 未計利息股利之現金流入（流出） | J35: =OFFSET(A508,0,$K$1-1) | K35: =K12+K13 | M35: =L35-G35 | O35: =L35-B35 | P35: =J35-K35 | Q35: =D35-F35
A36: 0 | H36: 收取利息 | J36: =OFFSET(A509,0,$K$1-1) | K36: =J36 | M36: =L36-G36 | O36: =L36-B36 | P36: =J36-K36 | Q36: =D36-F36
A37: 機械及設備 | B37: =VLOOKUP(A37,$A$309:$AX$418,$K$1,FALSE) | C37: 253 | D37: =J59*-1 | E37: 103 | F37: =J17 | G37: =B37+SUM(D37:D41)-SUM(F37:F41) | H37: 收取股利 | J37: =OFFSET(A510,0,$K$1-1) | K37: =J37 | L37: =VLOOKUP(A37,$A$140:$AX$249,$K$1,FALSE) | M37: =L37-G37 | O37: =L37-B37 | P37: =J37-K37 | Q37: =D37-F37
A38: 0 | C38: 407 | D38: =J101 | H38: 支付利息 | J38: =OFFSET(A511,0,$K$1-1) | K38: =J38 | M38: =L38-G38 | O38: =L38-B38 | P38: =J38-K38 | Q38: =D38-F38
A39: 0 | C39: 409 | D39: =J105 | E39: 412 | F39: =-J109 | H39: ▼業務活動之淨現金流入（流出） | J39: =OFFSET(A512,0,$K$1-1) | K39: =K36+K37+K38+K35 | M39: =L39-G39 | O39: =L39-B39 | P39: =J39-K39 | Q39: =D39-F39
A40: 0 | H40: ▼投資活動之現金流量 | J40: =OFFSET(A513,0,$K$1-1) | K40: =SUM(K41,K44,K47,K48,K49,K51,K54,K64) | M40: =L40-G40 | O40: =L40-B40 | P40: =J40-K40 | Q40: =D40-F40
H41: 減少流動金融資產及短期貸墊款 | J41: =OFFSET(A514,0,$K$1-1) | K41: =K42+K43 | M41: =L41-G41 | O41: =L41-B41 | P41: =J41-K41 | Q41: =D41-F41
A42: 交通及運輸設備 | B42: =VLOOKUP(A42,$A$309:$AX$418,$K$1,FALSE) | C42: 254 | D42: =J60*-1 | E42: 104 | F42: =J18 | G42: =B42+SUM(D42:D44)-SUM(F42:F44) | H42: 減少流動金融資產 | I42: 211 | J42: =OFFSET(A515,0,$K$1-1) | K42: =-SUMIF($C$7:$C$127,I42,$D$7:$D$127)+SUMIF($E$7:$E$135,I42,$F$7:$F$127) | L42: =VLOOKUP(A42,$A$140:$AX$249,$K$1,FALSE) | M42: =L42-G42 | O42: =L42-B42 | P42: =J42-K42 | Q42: =D42-F42
C43: 410 | D43: =J106 | E43: 413 | F43: =J110*-1 | H43: 減少短期墊款 | I43: 212 | J43: =OFFSET(A516,0,$K$1-1) | K43: =-SUMIF($C$7:$C$127,I43,$D$7:$D$127)+SUMIF($E$7:$E$135,I43,$F$7:$F$127) | M43: =L43-G43 | O43: =L43-B43 | P43: =J43-K43 | Q43: =D43-F43
H44: 減少投資、長期應收款、貸墊款及準備金 | J44: =OFFSET(A517,0,$K$1-1) | K44: =SUM(K45:K46) | M44: =L44-G44 | O44: =L44-B44 | P44: =J44-K44 | Q44: =D44-F44
A45: 什項設備 | B45: =VLOOKUP(A45,$A$309:$AX$418,$K$1,FALSE) | C45: 255 | D45: =J61*-1 | E45: 105 | F45: =J19 | G45: =B45+SUM(D45:D48)-SUM(F45:F48) | H45: 減少投資 | I45: 221 | J45: =OFFSET(A518,0,$K$1-1) | K45: =-SUMIF($C$7:$C$127,I45,$D$7:$D$127)+SUMIF($E$7:$E$135,I45,$F$7:$F$127) | L45: =VLOOKUP(A45,$A$140:$AX$249,$K$1,FALSE) | M45: =L45-G45 | O45: =L45-B45 | P45: =J45-K45 | Q45: =D45-F45
A46: 0 | C46: 408 | D46: =J102 | H46: 減少準備金 | I46: 222 | J46: =OFFSET(A519,0,$K$1-1) | K46: =-SUMIF($C$7:$C$127,I46,$D$7:$D$127)+SUMIF($E$7:$E$135,I46,$F$7:$F$127) | M46: =L46-G46 | O46: =L46-B46 | P46: =J46-K46 | Q46: =D46-F46
A47: 0 | C47: 411 | D47: =J107 | E47: 414 | F47: =-J111 | H47: 收取利息 | J47: =OFFSET(A520,0,$K$1-1) | K47: =J47 | M47: =L47-G47 | O47: =L47-B47 | P47: =J47-K47 | Q47: =D47-F47
A48: 0 | C48: 406 | D48: =J98 | H48: 收取股利 | J48: =OFFSET(A521,0,$K$1-1) | K48: =J48 | M48: =L48-G48 | O48: =L48-B48 | P48: =J48-K48 | Q48: =D48-F48
A49: 租賃資產 | B49: =VLOOKUP(A49,$A$309:$AX$413,$K$1,FALSE) | E49: 106 | F49: =J20 | G49: =B49+D49-F49 | H49: 增加流動金融資產及短期貸墊款 | J49: =OFFSET(A522,0,$K$1-1) | K49: =K50 | L49: =VLOOKUP(A49,$A$140:$AX$249,$K$1,FALSE) | M49: =L49-G49 | O49: =L49-B49 | P49: =J49-K49 | Q49: =D49-F49
A50: 租賃權益改良 | B50: =VLOOKUP(A50,$A$309:$AX$418,$K$1,FALSE) | C50: 257 | D50: =J63*-1 | E50: 107 | F50: =J21 | G50: =B50+D50-F50 | H50: 增加流動金融資產 | I50: 231 | J50: =OFFSET(A523,0,$K$1-1) | K50: =-SUMIF($C$7:$C$127,I50,$D$7:$D$127)+SUMIF($E$7:$E$135,I50,$F$7:$F$127) | L50: =VLOOKUP(A50,$A$140:$AX$249,$K$1,FALSE) | M50: =L50-G50 | O50: =L50-B49 | P50: =J50-K50 | Q50: =D49-F49
A51: 購建中固定資產 | B51: =VLOOKUP(A51,$A$309:$AX$418,$K$1,FALSE) | C51: 256 | D51: =J62*-1 | E51: 404 | F51: =J96 | G51: =B51+SUM(D51:D53)-SUM(F51:F53) | H51: 增加投資、長期應收款、貸墊款及準備金 | J51: =OFFSET(A524,0,$K$1-1) | K51: =SUM(K52:K53) | L51: =VLOOKUP(A51,$A$140:$AX$249,$K$1,FALSE) | M51: =L51-G51 | O51: =L51-B50 | P51: =J51-K51 | Q51: =D50-F50
E52: 405 | F52: =J97 | H52: 增加投資 | I52: 241 | J52: =OFFSET(A525,0,$K$1-1) | K52: =-SUMIF($C$7:$C$127,I52,$D$7:$D$127)+SUMIF($E$7:$E$135,I52,$F$7:$F$127) | M52: =L52-G52 | O52: =L52-B51 | P52: =J52-K52 | Q52: =D51-F51
E53: 406 | F53: =J98 | H53: 增加準備金 | I53: 242 | J53: =OFFSET(A526,0,$K$1-1) | K53: =-SUMIF($C$7:$C$127,I53,$D$7:$D$127)+SUMIF($E$7:$E$135,I53,$F$7:$F$127) | M53: =L53-G52 | O53: =L53-B52 | P53: =J53-K53 | Q53: =D52-F52
A54: 生物資產－非流動 | B54: =SUM(B55) | G54: =SUM(G55) | H54: 增加不動產、廠房及設備、礦產資源 | J54: =OFFSET(A527,0,$K$1-1) | K54: =K55 | L54: =VLOOKUP(A54,$A$140:$AX$249,$K$1,FALSE) | M54: =L54-G54 | O54: =L54-B54 | P54: =J54-K54 | Q54: =D54-F54
A55: 生產性生物資產－非流動 | B55: =VLOOKUP(A55,$A$309:$AX$418,$K$1,FALSE) | E55: 109 | F55: =J23 | G55: =B55+SUM(D55:D55)-SUM(F55:F55) | H55: 增加不動產、廠房及設備 | J55: =OFFSET(A528,0,$K$1-1) | K55: =K56 | L55: =VLOOKUP(A55,$A$140:$AX$249,$K$1,FALSE) | M55: =L55-G55 | O55: =L55-B55 | P55: =J55-K55 | Q55: =D55-F55
A56: 無形資產 | B56: =SUM(B57) | G56: =SUM(G57) | H56: 固定資產之增置 | J56: =OFFSET(A529,0,$K$1-1) | K56: =SUM(K57:K63) | L56: =VLOOKUP(A56,$A$140:$AX$249,$K$1,FALSE) | M56: =L56-G56 | O56: =L56-B56 | P56: =J56-K56 | Q56: =D56-F56
A57: 無形資產 | B57: =VLOOKUP(A57,$A$309:$AX$418,$K$1,FALSE) | E57: 111 | F57: =J25 | G57: =B57+SUM(D57:D59)-SUM(F57:F59) | H57: 土地改良物 | I57: 251 | J57: =OFFSET(A530,0,$K$1-1) | K57: =-SUMIF($C$7:$C$127,I57,$D$7:$D$127)+SUMIF($E$7:$E$127,I57,$F$7:$F$127) | L57: =VLOOKUP(A57,$A$140:$AX$249,$K$1,FALSE) | M57: =L57-G57 | O57: =L57-B57 | P57: =J57-K57 | Q57: =D57-F57
A58: 0 | C58: 415 | D58: =J113 | E58: 416 | F58: =J114*-1 | H58: 房屋及建築 | I58: 252 | J58: =OFFSET(A531,0,$K$1-1) | K58: =-SUMIF($C$7:$C$127,I58,$D$7:$D$127)+SUMIF($E$7:$E$127,I58,$F$7:$F$127) | M58: =L58-G58 | O58: =L58-B58 | P58: =J58-K58 | Q58: =D58-F58
A59: 0 | C59: 258 | D59: =J65*-1 | E59: 112 | H59: 機械及設備 | I59: 253 | J59: =OFFSET(A532,0,$K$1-1) | K59: =-SUMIF($C$7:$C$127,I59,$D$7:$D$127)+SUMIF($E$7:$E$127,I59,$F$7:$F$127) | M59: =L59-G59 | O59: =L59-B59 | P59: =J59-K59 | Q59: =D59-F59
A60: 0 | H60: 交通及運輸設備 | I60: 254 | J60: =OFFSET(A533,0,$K$1-1) | K60: =-SUMIF($C$7:$C$127,I60,$D$7:$D$127)+SUMIF($E$7:$E$127,I60,$F$7:$F$127) | M60: =L60-G60 | O60: =L60-B60 | P60: =J60-K60 | Q60: =D60-F60
A61: 其他資產 | B61: =SUM(B62,B65,B68) | G61: =SUM(G62,G65,G68) | H61: 什項設備 | I61: 255 | J61: =OFFSET(A534,0,$K$1-1) | K61: =-SUMIF($C$7:$C$127,I61,$D$7:$D$127)+SUMIF($E$7:$E$127,I61,$F$7:$F$127) | L61: =VLOOKUP(A61,$A$140:$AX$249,$K$1,FALSE) | M61: =L61-G61 | O61: =L61-B61 | P61: =J61-K61 | Q61: =D61-F61
A62: 遞延資產 | B62: =VLOOKUP(A62,$A$309:$AX$418,$K$1,FALSE) | E62: 112 | F62: =J26-F59 | G62: =B62+SUM(D62:D64)-SUM(F62:F64) | H62: 購建中固定資產 | I62: 256 | J62: =OFFSET(A535,0,$K$1-1) | K62: =-SUMIF($C$7:$C$127,I62,$D$7:$D$127)+SUMIF($E$7:$E$127,I62,$F$7:$F$127) | L62: =VLOOKUP(A62,$A$140:$AX$249,$K$1,FALSE) | M62: =L62-G62 | O62: =L62-B62 | P62: =J62-K62 | Q62: =D62-F62
A63: 0 | D63: =J126 | F63: =J127*-1 | H63: 租賃權益改良 | I63: 257 | J63: =OFFSET(A536,0,$K$1-1) | K63: =-SUMIF($C$7:$C$127,I63,$D$7:$D$127)+SUMIF($E$7:$E$127,I63,$F$7:$F$127) | M63: =L63-G63 | O63: =L63-B63 | P63: =J63-K63 | Q63: =D63-F63
A64: 0 | C64: 259 | D64: =J67*-1 | H64: 增加無形資產及其他資產 | J64: =OFFSET(A537,0,$K$1-1) | K64: =K65+K66 | M64: =L64-G64 | O64: =L64-B64 | P64: =J64-K64 | Q64: =D64-F64
A65: 什項資產 | B65: =VLOOKUP(A65,$A$309:$AX$418,$K$1,FALSE) | C65: 417 | D65: =F111 | E65: 108 | F65: =J22 | G65: =B65+SUM(D65:D67)-SUM(F65:F67) | H65: 增加無形資產 | I65: 258 | J65: =OFFSET(A538,0,$K$1-1) | K65: =-SUMIF($C$7:$C$127,I65,$D$7:$D$127)+SUMIF($E$7:$E$127,I65,$F$7:$F$127) | L65: =VLOOKUP(A65,$A$140:$AX$249,$K$1,FALSE) | M65: =L65-G65 | O65: =L65-B65 | P65: =J65-K65 | Q65: =D65-F65
A66: 0 | H66: 增加其他資產 | J66: =OFFSET(A539,0,$K$1-1) | K66: =K67 | M66: =L66-G66 | O66: =L66-B66 | P66: =J66-K66 | Q66: =D66-F66
A67: 0 | H67: 增加遞延費用 | I67: 259 | J67: =OFFSET(A540,0,$K$1-1) | K67: =-SUMIF($C$7:$C$127,I67,$D$7:$D$127)+SUMIF($E$7:$E$127,I67,$F$7:$F$127) | M67: =L67-G67 | O67: =L67-B67 | P67: =J67-K67 | Q67: =D67-F67
G68: =B68+D68-F68 | H68: ▼投資活動之淨現金流入（流出） | J68: =OFFSET(A541,0,$K$1-1) | K68: =K40 | P68: =J68-K68 | Q68: =D68-F68
A69: 合 計 | B69: =B7+B17+B26+B54+B56+B61 | G69: =G7+G17+G26+G54+G56+G61 | H69: ▼籌資活動之現金流量 | J69: =OFFSET(A542,0,$K$1-1) | K69: =K70+K72+K74+K81+K79+K83 | L69: =VLOOKUP(A69,$A$140:$AX$249,$K$1,FALSE) | M69: =L69-G69 | O69: =L69-B69 | P69: =J69-K69 | Q69: =D69-F69
A70: 負債 | B70: =B71+B78+B83 | G70: =G71+G78+G83 | H70: 增加短期債務、流動金融負債及其他負債 | J70: =OFFSET(A543,0,$K$1-1) | K70: =K71 | L70: =VLOOKUP(A70,$A$253:$AX$305,$K$1,FALSE) | M70: =L70-G70 | O70: =L70-B70 | P70: =J70-K70 | Q70: =D70-F70
A71: 流動負債 | B71: =SUM(B72:B77) | G71: =SUM(G72:G77) | H71: 增加其他負債 | I71: 311 | J71: =OFFSET(A544,0,$K$1-1) | K71: =-SUMIF($C$7:$C$127,I71,$D$7:$D$127)+SUMIF($E$7:$E$127,I71,$F$7:$F$127) | L71: =VLOOKUP(A71,$A$253:$AX$305,$K$1,FALSE) | M71: =L71-G71 | O71: =L71-B71 | P71: =J71-K71 | Q71: =D71-F71
A72: 短期債務 | B72: =VLOOKUP(A72,$A$423:$AX$475,$K$1,FALSE) | C72: 322 | D72: =J82*-1 | E72: 418 | F72: =D81 | G72: =B72+SUM(F72:F73)-SUM(D72:D73) | H72: 增加長期負債 | J72: =OFFSET(A545,0,$K$1-1) | K72: =K73 | L72: =VLOOKUP(A72,$A$253:$AX$305,$K$1,FALSE) | M72: =L72-G72 | O72: =L72-B72 | P72: =J72-K72 | Q72: =D72-F72
A73: 0 | C73: 316 | H73: 增加長期債務 | I73: 312 | J73: =OFFSET(A546,0,$K$1-1) | K73: =-SUMIF($C$7:$C$127,I73,$D$7:$D$127)+SUMIF($E$7:$E$127,I73,$F$7:$F$127) | M73: =L73-G73 | O73: =L73-B73 | P73: =J73-K73 | Q73: =D73-F73
A74: 應付款項 | B74: =VLOOKUP(A74,$A$423:$AX$475,$K$1,FALSE) | E74: 161 | G74: =B74+SUM(F74:F75)-SUM(D74:D75) | H74: 增加基金、公積及填補短絀 | J74: =OFFSET(A547,0,$K$1-1) | K74: =SUM(K75) | L74: =VLOOKUP(A74,$A$253:$AX$305,$K$1,FALSE) | M74: =L74-G74 | O74: =L74-B74 | P74: =J74-K74 | Q74: =D74-F74
A75: 0 | H75: 增加基金 | J75: =OFFSET(A548,0,$K$1-1) | K75: =SUM(K76:K78) | M75: =L75-G75 | O75: =L75-B75 | P75: =J75-K75 | Q75: =D75-F75
A76: 預收款項 | B76: =VLOOKUP(A76,$A$423:$AX$475,$K$1,FALSE) | E76: 161 | F76: =J34 | G76: =B76+SUM(F76:F77)-SUM(D76:D77) | H76: 國庫撥款增置固定資產 | I76: 313 | J76: =OFFSET(A549,0,$K$1-1) | K76: =-SUMIF($C$7:$C$127,I76,$D$7:$D$127)+SUMIF($E$7:$E$127,I76,$F$7:$F$127) | L76: =VLOOKUP(A76,$A$253:$AX$305,$K$1,FALSE) | M76: =L76-G76 | O76: =L76-B76 | P76: =J76-K76 | Q76: =D76-F76
A77: 0 | H77: 國庫增撥無形資產 | I77: 314 | J77: =OFFSET(A550,0,$K$1-1) | K77: =-SUMIF($C$7:$C$127,I77,$D$7:$D$127)+SUMIF($E$7:$E$127,I77,$F$7:$F$127) | M77: =L77-G77 | O77: =L77-B77 | P77: =J77-K77 | Q77: =D77-F77
A78: 長期負債 | B78: =SUM(B81) | G78: =SUM(G81) | H78: 國庫增撥遞延資產 | I78: 315 | J78: =OFFSET(A551,0,$K$1-1) | K78: =-SUMIF($C$7:$C$127,I78,$D$7:$D$127)+SUMIF($E$7:$E$127,I78,$F$7:$F$127) | L78: =VLOOKUP(A78,$A$253:$AX$305,$K$1,FALSE) | M78: =L78-G78 | O78: =L78-B78 | P78: =J78-K78 | Q78: =D78-F78
H79: 減少短期債務、流動金融負債及其他負債 | J79: =OFFSET(A552,0,$K$1-1)
H80: 減少短期債務 | I80: 316 | J80: =OFFSET(A553,0,$K$1-1) | K80: =-SUMIF($C$7:$C$127,I80,$D$7:$D$127)+SUMIF($E$7:$E$127,I80,$F$7:$F$127)
A81: 長期債務 | B81: =VLOOKUP(A81,$A$423:$AX$475,$K$1,FALSE) | C81: 418 | D81: =J116 | E81: 312 | F81: =J73 | G81: =B81+SUM(F81:F82)-SUM(D81:D82) | H81: 減少長期負債 | J81: =OFFSET(A554,0,$K$1-1) | K81: =K82 | L81: =VLOOKUP(A81,$A$253:$AX$305,$K$1,FALSE) | M81: =L81-G81 | O81: =L81-B81 | P81: =J81-K81 | Q81: =D81-F81
A82: 0 | C82: 322 | H82: 減少長期債務 | I82: 322 | J82: =OFFSET(A555,0,$K$1-1) | K82: =-SUMIF($C$7:$C$127,I82,$D$7:$D$127)+SUMIF($E$7:$E$127,I82,$F$7:$F$127) | M82: =L82-G82 | O82: =L82-B82 | P82: =J82-K82 | Q82: =D72-F82
A83: 其他負債 | B83: =SUM(B84,B90) | G83: =SUM(G84,G90) | H83: 支付利息 | J83: =OFFSET(A556,0,$K$1-1) | K83: =J83 | L83: =VLOOKUP(A83,$A$253:$AX$305,$K$1,FALSE) | M83: =L83-G83 | O83: =L83-B83 | P83: =J83-K83 | Q83: =D83-F83
A84: 什項負債 | B84: =VLOOKUP(A84,$A$423:$AX$475,$K$1,FALSE) | C84: 321 | G84: =B84+SUM(F84:F89)-SUM(D84:D89) | H84: ▼籌資活動之淨現金流入（流出） | J84: =OFFSET(A557,0,$K$1-1) | K84: =K69 | L84: =VLOOKUP(A84,$A$253:$AX$305,$K$1,FALSE) | M84: =L84-G84 | O84: =L84-B84 | P84: =J84-K84 | Q84: =D84-F84
A85: 0 | C85: 402 | D85: =J91*-1 | E85: 122 | F85: =J28 | H85: ▼現金及約當現金之淨增（淨減） | I85: B | J85: =OFFSET(A558,0,$K$1-1) | K85: =J85 | M85: =L85-G85 | O85: =L85-B85 | P85: =J85-K85 | Q85: =D85-F85
A86: 0 | E86: 401 | F86: =J90 | H86: ▼期初現金及約當現金 | J86: =OFFSET(A559,0,$K$1-1) | K86: =B8 | M86: =L86-G86 | O86: =L86-B86 | P86: =J86-K86 | Q86: =D86-F86
A87: 0 | H87: ▼期末現金及約當現金 | J87: =OFFSET(A560,0,$K$1-1) | K87: =G8 | M87: =L87-G87 | O87: =L87-B87 | P87: =J87-K87 | Q87: =D87-F87
A88: 0 | H88: ▼不影響現金流量之投資與籌資活動 | J88: =OFFSET(A561,0,$K$1-1) | M88: =L88-G88 | O88: =L88-B88 | P88: =J88-K88 | Q88: =D88-F88
A89: 0 | H89: 退休離職準備金與應付退休及離職金同額增加(+)或減少(-)之金額 | J89: =OFFSET(A562,0,$K$1-1) | K89: =K90+K91 | M89: =L89-G89 | O89: =L89-B89 | P89: =J89-K89 | Q89: =D89-F89
A90: 遞延負債 | B90: =VLOOKUP(A90,$A$423:$AX$475,$K$1,FALSE) | C90: 124 | D90: =J31*-1 | E90: 311 | F90: =J71 | G90: =B90+SUM(F90:F96)-SUM(D90:D96) | H90: 退休離職準備金與應付退休及離職金同額增加之金額(+) | I90: 401 | J90: =OFFSET(A563,0,$K$1-1) | K90: =(SUMIF($C$7:$C$127,I90,$D$7:$D$127)+SUMIF($E$7:$E$127,I90,$F$7:$F$127))/2 | L90: =VLOOKUP(A90,$A$253:$AX$305,$K$1,FALSE) | M90: =L90-G90 | O90: =L90-B90 | P90: =J90-K90 | Q90: =D90-F90
A91: 0 | C91: 123 | D91: =-J30 | E91: 403 | F91: =J93 | H91: 退休離職準備金與應付退休及離職金同額減少之金額(-) | I91: 402 | J91: =OFFSET(A564,0,$K$1-1) | K91: =(SUMIF($C$7:$C$127,I91,$D$7:$D$127)+SUMIF($E$7:$E$127,I91,$F$7:$F$127))/2*-1 | M91: =L91-G91 | O91: =L91-B91 | P91: =J91-K91 | Q91: =D91-F91
A92: 0 | E92: 407 | F92: =J101 | H92: 其他準備金與遞延收入同額增加之金額 | J92: =OFFSET(A565,0,$K$1-1) | K92: =K93 | M92: =L92-G92 | O92: =L92-B92 | P92: =J92-K92 | Q92: =D92-F92
A93: 0 | E93: 408 | F93: =J102 | H93: 其他準備金與遞延收入同額增加之金額 | I93: 403 | J93: =OFFSET(A566,0,$K$1-1) | K93: =(SUMIF($C$7:$C$127,I93,$D$7:$D$127)+SUMIF($E$7:$E$127,I93,$F$7:$F$127))/2 | M93: =L93-G93 | O93: =L93-B93 | P93: =J93-K93 | Q93: =D93-F93
E94: 410 | H94: 以前年度購建中固定資產科目，調整轉入不動產、廠房及設備科目之 | J94: =OFFSET(A567,0,$K$1-1) | K94: =K95 | P94: =J94-K94
H95: 調整轉入不動產、廠房及設備科目明細 | J95: =OFFSET(A568,0,$K$1-1) | K95: =K96+K97+K98 | O95: =L95-B96 | P95: =J95-K95 | Q95: =D96-F96
A96: 0 | H96: 土地改良物 | I96: 404 | J96: =OFFSET(A569,0,$K$1-1) | K96: =(SUMIF($C$7:$C$127,I96,$D$7:$D$127)+SUMIF($E$7:$E$127,I96,$F$7:$F$127))/2 | O96: =L97-B97 | P96: =J96-K96 | Q96: =D97-F97
A97: 淨值 | B97: =B98+B110+B116+B125 | G97: =G98+G110+G116+G125 | H97: 房屋及建築 | I97: 405 | J97: =OFFSET(A570,0,$K$1-1) | K97: =(SUMIF($C$7:$C$127,I97,$D$7:$D$127)+SUMIF($E$7:$E$127,I97,$F$7:$F$127))/2 | L97: =VLOOKUP(A97,$A$253:$AX$305,$K$1,FALSE) | M97: =L97-G97 | O97: =L98-B98 | P97: =J97-K97 | Q97: =D98-F98
A98: 基金 | B98: =SUM(B99:B101) | G98: =SUM(G99:G101) | H98: 什項設備 | I98: 406 | J98: =OFFSET(A571,0,$K$1-1) | K98: =(SUMIF($C$7:$C$127,I98,$D$7:$D$127)+SUMIF($E$7:$E$127,I98,$F$7:$F$127))/2 | L98: =VLOOKUP(A98,$A$253:$AX$305,$K$1,FALSE) | M98: =L98-G98 | O98: =L99-B99 | P98: =J98-K98 | Q98: =D99-F99
A99: 基金 | B99: =VLOOKUP(A99,$A$423:$AX$475,$K$1,FALSE) | E99: 313 | F99: =J76 | G99: =B99+SUM(F99:F109)-SUM(D99:D109) | H99: 不動產、廠房及設備與遞延收入同額增加(+)或減少(-)之金額 | J99: =OFFSET(A572,0,$K$1-1) | K99: =K100 | L99: =VLOOKUP(A99,$A$253:$AX$305,$K$1,FALSE) | M99: =L99-G99 | O99: =L100-B100 | P99: =J99-K99 | Q99: =D100-F100
A100: 0 | E100: 314 | F100: =J77 | H100: 不動產、廠房及設備與遞延收入同額增加明細(+) | J100: =OFFSET(A573,0,$K$1-1) | K100: =K101+K102 | M100: =L100-G100 | O100: =L101-B101 | P100: =J100-K100 | Q100: =D101-F101
...

Sheet 清大
A1: =OFFSET(A139,0,K1-1) | K1: =L1+2 | L1: 3
A2: 預計平衡表與現金流量表勾稽底稿
A3: 中華民國115年度
A4: 科目 | B4: 114.12.31 | C4: 調整項目 | G4: 115.12.31 | H4: 現金流量表勾稽項目
B5: 預計數 | D5: 借方 | F5: 貸方 | G5: 預計數
A6: 資產 | H6: ▼業務活動之現金流量 | L6: 114年12月 | M6: 差異數要再加(減) | O6: 比較增減 | Q6: 調整項目
A7: 流動資產 | B7: =SUM(B8:B16) | G7: =SUM(G8:G16) | H7: 本期賸餘（短絀） | I7: A | J7: =OFFSET(A480,0,$K$1-1) | K7: =-SUMIF($C$7:$C$127,I7,$D$7:$D$127)+SUMIF($E$7:$E$127,I7,$F$7:$F$127) | L7: =VLOOKUP(A7,$A$140:$AX$249,$K$1,FALSE) | M7: =L7-G7 | O7: =L7-B7 | P7: =J7-K7 | Q7: =D7-F7
A8: 現金 | B8: =VLOOKUP(A8,$A$309:$AX$418,$K$1,FALSE) | C8: B | D8: =IF(G8-B8>0,G8-B8,"0") | E8: B | F8: =IF(G8-B8<0,B8-G8,"0") | G8: =J87 | H8: 利息股利之調整 | J8: =OFFSET(A481,0,$K$1-1) | K8: =SUM(K9:K11) | L8: =VLOOKUP(A8,$A$140:$AX$249,$K$1,FALSE) | M8: =L8-G8 | O8: =L8-B8 | P8: =J8-K8 | Q8: =D8-F8
A9: 流動金融資產 | B9: =VLOOKUP(A9,$A$309:$AX$418,$K$1,FALSE) | C9: 231 | D9: =J50*-1 | E9: 211 | F9: =J42 | G9: =B9+D9-F9+D10-F10 | H9: 利息收入 | J9: =OFFSET(A482,0,$K$1-1) | K9: =J9 | L9: =VLOOKUP(A9,$A$140:$AX$249,$K$1,FALSE) | M9: =L9-G9 | O9: =L9-B9 | P9: =J9-K9 | Q9: =D9-F9
C10: 125 | H10: 股利收入 | J10: =OFFSET(A483,0,$K$1-1) | K10: =J10 | M10: =L10-G10 | O10: =L10-B10 | P10: =J10-K10 | Q10: =D10-F10
A11: 應收款項 | B11: =VLOOKUP(A11,$A$309:$AX$418,$K$1,FALSE) | C11: 151 | E11: 151 | G11: =B11+D11-F11 | H11: 利息費用 | J11: =OFFSET(A484,0,$K$1-1) | K11: =J11 | L11: =VLOOKUP(A11,$A$140:$AX$249,$K$1,FALSE) | M11: =L11-G11 | O11: =L11-B11 | P11: =J11-K11 | Q11: =D11-F11
A12: 0 | H12: 未計利息股利之本期賸餘（短絀） | J12: =OFFSET(A485,0,$K$1-1) | K12: =K7+K8 | M12: =L12-G12 | O12: =L12-B12 | P12: =J12-K12 | Q12: =D12-F12
A13: 存貨 | B13: =VLOOKUP(A13,$A$309:$AX$418,$K$1,FALSE) | C13: 151 | E13: 151 | G13: =B13+D13-F13 | H13: 調整項目 | J13: =OFFSET(A486,0,$K$1-1) | K13: =SUM(K14,K24,K27,K34,K33) | L13: =VLOOKUP(A13,$A$140:$AX$249,$K$1,FALSE) | M13: =L13-G13 | O13: =L13-B13 | P13: =J13-K13 | Q13: =D13-F13
A14: 生產性生物資產－流動 | B14: =VLOOKUP(A14,$A$309:$AX$418,$K$1,FALSE) | C14: 151 | E14: 151 | G14: =B14+D14-F14 | H14: 折舊、減損及折耗 | J14: =OFFSET(A487,0,$K$1-1) | K14: =SUM(K15:K23) | L14: =VLOOKUP(A14,$A$140:$AX$249,$K$1,FALSE) | M14: =L14-G14 | O14: =L14-B14 | P14: =J14-K14 | Q14: =D14-F14
A15: 預付款項 | B15: =VLOOKUP(A15,$A$309:$AX$418,$K$1,FALSE) | C15: 151 | E15: 151 | G15: =B15+D15-F15 | H15: 土地改良物 | I15: 101 | J15: =OFFSET(A488,0,$K$1-1) | K15: =-SUMIF($C$7:$C$127,I15,$D$7:$D$127)+SUMIF($E$7:$E$127,I15,$F$7:$F$127) | L15: =VLOOKUP(A15,$A$140:$AX$249,$K$1,FALSE) | M15: =L15-G15 | O15: =L15-B15 | P15: =J15-K15 | Q15: =D15-F15
A16: 短期貸墊款 | B16: =VLOOKUP(A16,$A$309:$AX$418,$K$1,FALSE) | C16: 151 | E16: 212 | F16: =J43 | G16: =B16+D16-F16 | H16: 房屋及建築 | I16: 102 | J16: =OFFSET(A489,0,$K$1-1) | K16: =-SUMIF($C$7:$C$127,I16,$D$7:$D$127)+SUMIF($E$7:$E$127,I16,$F$7:$F$127) | L16: =VLOOKUP(A16,$A$140:$AX$249,$K$1,FALSE) | M16: =L16-G16 | O16: =L16-B16 | P16: =J16-K16 | Q16: =D16-F16
A17: 投資、長期應收款、貸墊款及準備金 | B17: =SUM(B18:B21) | G17: =SUM(G18:G21) | H17: 機械及設備 | I17: 103 | J17: =OFFSET(A490,0,$K$1-1) | K17: =-SUMIF($C$7:$C$127,I17,$D$7:$D$127)+SUMIF($E$7:$E$127,I17,$F$7:$F$127) | L17: =VLOOKUP(A17,$A$140:$AX$249,$K$1,FALSE) | M17: =L17-G17 | O17: =L17-B17 | P17: =J17-K17 | Q17: =D17-F17
A18: 採權益法之投資 | B18: =VLOOKUP(A18,$A$309:$AX$418,$K$1,FALSE) | G18: =D18+F18+B18 | H18: 交通及運輸設備 | I18: 104 | J18: =OFFSET(A491,0,$K$1-1) | K18: =-SUMIF($C$7:$C$127,I18,$D$7:$D$127)+SUMIF($E$7:$E$127,I18,$F$7:$F$127) | L18: =VLOOKUP(A18,$A$140:$AX$249,$K$1,FALSE) | M18: =L18-G18 | O18: =L18-B18 | P18: =J18-K18 | Q18: =D18-F18
A19: 非流動金融資產 | B19: =VLOOKUP(A19,$A$309:$AX$418,$K$1,FALSE) | C19: 241 | D19: =J52*-1 | E19: 221 | F19: =J45 | G19: =B19+D19-F19 | H19: 什項設備 | I19: 105 | J19: =OFFSET(A492,0,$K$1-1) | K19: =-SUMIF($C$7:$C$127,I19,$D$7:$D$127)+SUMIF($E$7:$E$127,I19,$F$7:$F$127) | L19: =VLOOKUP(A19,$A$140:$AX$249,$K$1,FALSE) | M19: =L19-G19 | O19: =L19-B19 | P19: =J19-K19 | Q19: =D19-F19
A20: 長期應收款 | B20: =VLOOKUP(A20,$A$309:$AX$418,$K$1,FALSE) | G20: =B20+D20-F20 | H20: 租賃資產 | I20: 106 | J20: =OFFSET(A493,0,$K$1-1) | K20: =-SUMIF($C$7:$C$127,I20,$D$7:$D$127)+SUMIF($E$7:$E$127,I20,$F$7:$F$127) | L20: =VLOOKUP(A20,$A$140:$AX$249,$K$1,FALSE) | M20: =L20-G20 | O20: =L20-B20 | P20: =J20-K20 | Q20: =D20-F20
A21: 準備金 | B21: =VLOOKUP(A21,$A$309:$AX$418,$K$1,FALSE) | C21: 242 | D21: =J53*-1 | E21: 222 | F21: =J46 | G21: =B21+SUM(D21:D25)-SUM(F21:F25) | H21: 租賃權益改良 | I21: 107 | J21: =OFFSET(A494,0,$K$1-1) | K21: =-SUMIF($C$7:$C$127,I21,$D$7:$D$127)+SUMIF($E$7:$E$127,I21,$F$7:$F$127) | L21: =VLOOKUP(A21,$A$140:$AX$249,$K$1,FALSE) | M21: =L21-G21 | O21: =L21-B21 | P21: =J21-K21 | Q21: =D21-F21
A22: 0 | C22: 401 | D22: =J90 | E22: 402 | F22: =-J91 | H22: 代管資產 | I22: 108 | J22: =OFFSET(A495,0,$K$1-1) | K22: =-SUMIF($C$7:$C$127,I22,$D$7:$D$127)+SUMIF($E$7:$E$127,I22,$F$7:$F$127) | M22: =L22-G22 | O22: =L22-B22 | P22: =J22-K22 | Q22: =D22-F22
A23: 0 | C23: 403 | D23: =J93 | H23: 生產性生物資產－非流動 | I23: 109 | J23: =OFFSET(A496,0,$K$1-1) | K23: =-SUMIF($C$7:$C$127,I23,$D$7:$D$127)+SUMIF($E$7:$E$127,I23,$F$7:$F$127) | M23: =L23-G23 | O23: =L23-B23 | P23: =J23-K23 | Q23: =D23-F23
A24: 0 | H24: 攤銷 | J24: =OFFSET(A497,0,$K$1-1) | K24: =SUM(K25:K26) | M24: =L24-G24 | O24: =L24-B24 | P24: =J24-K24 | Q24: =D24-F24
C25: 125 | D25: =J32*-1 | H25: 攤銷電腦軟體 | I25: 111 | J25: =OFFSET(A498,0,$K$1-1) | K25: =-SUMIF($C$7:$C$127,I25,$D$7:$D$127)+SUMIF($E$7:$E$127,I25,$F$7:$F$127) | M25: =L25-G25 | O25: =L25-B25 | P25: =J25-K25 | Q25: =D25-F25
A26: 不動產、廠房及設備 | B26: =SUM(B27:B52) | G26: =SUM(G27:G52) | H26: 其他攤銷費用 | I26: 112 | J26: =OFFSET(A499,0,$K$1-1) | K26: =-SUMIF($C$7:$C$127,I26,$D$7:$D$127)+SUMIF($E$7:$E$127,I26,$F$7:$F$127) | L26: =VLOOKUP(A26,$A$140:$AX$249,$K$1,FALSE) | M26: =L26-G26 | O26: =L26-B26 | P26: =J26-K26 | Q26: =D26-F26
A27: 土地 | B27: =VLOOKUP(A27,$A$309:$AX$418,$K$1,FALSE) | C27: 121 | G27: =B27+SUM(D27)-SUM(F27) | H27: 其他 | J27: =OFFSET(A500,0,$K$1-1) | K27: =K28+K29+K32 | L27: =VLOOKUP(A27,$A$140:$AX$249,$K$1,FALSE) | M27: =L27-G27 | O27: =L27-B27 | P27: =J27-K27 | Q27: =D27-F27
A28: 0 | H28: 應付退休及離職金 | I28: 122 | J28: =OFFSET(A501,0,$K$1-1) | K28: =-SUMIF($C$7:$C$127,I28,$D$7:$D$127)+SUMIF($E$7:$E$127,I28,$F$7:$F$127) | M28: =L28-G28 | O28: =L28-B28 | P28: =J28-K28 | Q28: =D28-F28
A29: 土地改良物 | B29: =VLOOKUP(A29,$A$309:$AX$418,$K$1,FALSE) | C29: 251 | D29: =J57*-1 | E29: 101 | F29: =J15 | G29: =B29+SUM(D29:D32)-SUM(F29:F32) | H29: 遞延收入 | J29: =OFFSET(A502,0,$K$1-1) | K29: =SUM(K30:K31) | L29: =VLOOKUP(A29,$A$140:$AX$249,$K$1,FALSE) | M29: =L29-G29 | O29: =L29-B29 | P29: =J29-K29 | Q29: =D29-F29
A30: 0 | C30: 404 | D30: =J96 | H30: 遞延收入-其他補助收入 | I30: 123 | J30: =OFFSET(A503,0,$K$1-1) | K30: =-SUMIF($C$7:$C$127,I30,$D$7:$D$127)+SUMIF($E$7:$E$127,I30,$F$7:$F$127) | M30: =L30-G30 | O30: =L30-B30 | P30: =J30-K30 | Q30: =D30-F30
A31: 0 | H31: 遞延收入-受贈收入 | I31: 124 | J31: =OFFSET(A504,0,$K$1-1) | K31: =-SUMIF($C$7:$C$127,I31,$D$7:$D$127)+SUMIF($E$7:$E$127,I31,$F$7:$F$127) | M31: =L31-G31 | O31: =L31-B31 | P31: =J31-K31 | Q31: =D31-F31
A32: 0 | H32: 其他 | I32: 125 | J32: =OFFSET(A505,0,$K$1-1) | M32: =L32-G32 | O32: =L32-B32 | P32: =J32-K32 | Q32: =D32-F32
A33: 房屋及建築 | B33: =VLOOKUP(A33,$A$309:$AX$418,$K$1,FALSE) | C33: 252 | D33: =J58*-1 | E33: 102 | F33: =J16 | G33: =B33+SUM(D33:D36)-SUM(F33:F36) | H33: 流動資產淨減（淨增） | I33: 151 | J33: =OFFSET(A506,0,$K$1-1) | K33: =-SUMIF($C$7:$C$127,I33,$D$7:$D$127)+SUMIF($E$7:$E$127,I33,$F$7:$F$127) | L33: =VLOOKUP(A33,$A$140:$AX$249,$K$1,FALSE) | M33: =L33-G33 | O33: =L33-B33 | P33: =J33-K33 | Q33: =D33-F33
A34: 0 | C34: 405 | D34: =J97 | H34: 流動負債淨增（淨減） | I34: 161 | J34: =OFFSET(A507,0,$K$1-1) | K34: =-SUMIF($C$7:$C$127,I34,$D$7:$D$127)+SUMIF($E$7:$E$127,I34,$F$7:$F$127) | M34: =L34-G34 | O34: =L34-B34 | P34: =J34-K34 | Q34: =D34-F34
A35: 0 | H35: 未計利息股利之現金流入（流出） | J35: =OFFSET(A508,0,$K$1-1) | K35: =K12+K13 | M35: =L35-G35 | O35: =L35-B35 | P35: =J35-K35 | Q35: =D35-F35
A36: 0 | H36: 收取利息 | J36: =OFFSET(A509,0,$K$1-1) | K36: =J36 | M36: =L36-G36 | O36: =L36-B36 | P36: =J36-K36 | Q36: =D36-F36
A37: 機械及設備 | B37: =VLOOKUP(A37,$A$309:$AX$418,$K$1,FALSE) | C37: 253 | D37: =J59*-1 | E37: 103 | F37: =J17 | G37: =B37+SUM(D37:D41)-SUM(F37:F41) | H37: 收取股利 | J37: =OFFSET(A510,0,$K$1-1) | K37: =J37 | L37: =VLOOKUP(A37,$A$140:$AX$249,$K$1,FALSE) | M37: =L37-G37 | O37: =L37-B37 | P37: =J37-K37 | Q37: =D37-F37
A38: 0 | C38: 407 | D38: =J101 | H38: 支付利息 | J38: =OFFSET(A511,0,$K$1-1) | K38: =J38 | M38: =L38-G38 | O38: =L38-B38 | P38: =J38-K38 | Q38: =D38-F38
A39: 0 | C39: 409 | D39: =J105 | E39: 412 | F39: =-J109 | H39: ▼業務活動之淨現金流入（流出） | J39: =OFFSET(A512,0,$K$1-1) | K39: =K36+K37+K38+K35 | M39: =L39-G39 | O39: =L39-B39 | P39: =J39-K39 | Q39: =D39-F39
A40: 0 | H40: ▼投資活動之現金流量 | J40: =OFFSET(A513,0,$K$1-1) | K40: =SUM(K41,K44,K47,K48,K49,K51,K54,K64) | M40: =L40-G40 | O40: =L40-B40 | P40: =J40-K40 | Q40: =D40-F40
H41: 減少流動金融資產及短期貸墊款 | J41: =OFFSET(A514,0,$K$1-1) | K41: =K42+K43 | M41: =L41-G41 | O41: =L41-B41 | P41: =J41-K41 | Q41: =D41-F41
A42: 交通及運輸設備 | B42: =VLOOKUP(A42,$A$309:$AX$418,$K$1,FALSE) | C42: 254 | D42: =J60*-1 | E42: 104 | F42: =J18 | G42: =B42+SUM(D42:D44)-SUM(F42:F44) | H42: 減少流動金融資產 | I42: 211 | J42: =OFFSET(A515,0,$K$1-1) | K42: =-SUMIF($C$7:$C$127,I42,$D$7:$D$127)+SUMIF($E$7:$E$135,I42,$F$7:$F$127) | L42: =VLOOKUP(A42,$A$140:$AX$249,$K$1,FALSE) | M42: =L42-G42 | O42: =L42-B42 | P42: =J42-K42 | Q42: =D42-F42
C43: 410 | D43: =J106 | E43: 413 | F43: =J110*-1 | H43: 減少短期墊款 | I43: 212 | J43: =OFFSET(A516,0,$K$1-1) | K43: =-SUMIF($C$7:$C$127,I43,$D$7:$D$127)+SUMIF($E$7:$E$135,I43,$F$7:$F$127) | M43: =L43-G43 | O43: =L43-B43 | P43: =J43-K43 | Q43: =D43-F43
H44: 減少投資、長期應收款、貸墊款及準備金 | J44: =OFFSET(A517,0,$K$1-1) | K44: =SUM(K45:K46) | M44: =L44-G44 | O44: =L44-B44 | P44: =J44-K44 | Q44: =D44-F44
A45: 什項設備 | B45: =VLOOKUP(A45,$A$309:$AX$418,$K$1,FALSE) | C45: 255 | D45: =J61*-1 | E45: 105 | F45: =J19 | G45: =B45+SUM(D45:D48)-SUM(F45:F48) | H45: 減少投資 | I45: 221 | J45: =OFFSET(A518,0,$K$1-1) | K45: =-SUMIF($C$7:$C$127,I45,$D$7:$D$127)+SUMIF($E$7:$E$135,I45,$F$7:$F$127) | L45: =VLOOKUP(A45,$A$140:$AX$249,$K$1,FALSE) | M45: =L45-G45 | O45: =L45-B45 | P45: =J45-K45 | Q45: =D45-F45
A46: 0 | C46: 408 | D46: =J102 | H46: 減少準備金 | I46: 222 | J46: =OFFSET(A519,0,$K$1-1) | K46: =-SUMIF($C$7:$C$127,I46,$D$7:$D$127)+SUMIF($E$7:$E$135,I46,$F$7:$F$127) | M46: =L46-G46 | O46: =L46-B46 | P46: =J46-K46 | Q46: =D46-F46
A47: 0 | C47: 411 | D47: =J107 | E47: 414 | F47: =-J111 | H47: 收取利息 | J47: =OFFSET(A520,0,$K$1-1) | K47: =J47 | M47: =L47-G47 | O47: =L47-B47 | P47: =J47-K47 | Q47: =D47-F47
A48: 0 | C48: 406 | D48: =J98 | H48: 收取股利 | J48: =OFFSET(A521,0,$K$1-1) | K48: =J48 | M48: =L48-G48 | O48: =L48-B48 | P48: =J48-K48 | Q48: =D48-F48
A49: 租賃資產 | B49: =VLOOKUP(A49,$A$309:$AX$413,$K$1,FALSE) | E49: 106 | F49: =J20 | G49: =B49+D49-F49 | H49: 增加流動金融資產及短期貸墊款 | J49: =OFFSET(A522,0,$K$1-1) | K49: =K50 | L49: =VLOOKUP(A49,$A$140:$AX$249,$K$1,FALSE) | M49: =L49-G49 | O49: =L49-B49 | P49: =J49-K49 | Q49: =D49-F49
A50: 租賃權益改良 | B50: =VLOOKUP(A50,$A$309:$AX$418,$K$1,FALSE) | C50: 257 | D50: =J63*-1 | E50: 107 | F50: =J21 | G50: =B50+D50-F50 | H50: 增加流動金融資產 | I50: 231 | J50: =OFFSET(A523,0,$K$1-1) | K50: =-SUMIF($C$7:$C$127,I50,$D$7:$D$127)+SUMIF($E$7:$E$135,I50,$F$7:$F$127) | L50: =VLOOKUP(A50,$A$140:$AX$249,$K$1,FALSE) | M50: =L50-G50 | O50: =L50-B49 | P50: =J50-K50 | Q50: =D49-F49
A51: 購建中固定資產 | B51: =VLOOKUP(A51,$A$309:$AX$418,$K$1,FALSE) | C51: 256 | D51: =J62*-1 | E51: 404 | F51: =J96 | G51: =B51+SUM(D51:D53)-SUM(F51:F53) | H51: 增加投資、長期應收款、貸墊款及準備金 | J51: =OFFSET(A524,0,$K$1-1) | K51: =SUM(K52:K53) | L51: =VLOOKUP(A51,$A$140:$AX$249,$K$1,FALSE) | M51: =L51-G51 | O51: =L51-B50 | P51: =J51-K51 | Q51: =D50-F50
E52: 405 | F52: =J97 | H52: 增加投資 | I52: 241 | J52: =OFFSET(A525,0,$K$1-1) | K52: =-SUMIF($C$7:$C$127,I52,$D$7:$D$127)+SUMIF($E$7:$E$135,I52,$F$7:$F$127) | M52: =L52-G52 | O52: =L52-B51 | P52: =J52-K52 | Q52: =D51-F51
E53: 406 | F53: =J98 | H53: 增加準備金 | I53: 242 | J53: =OFFSET(A526,0,$K$1-1) | K53: =-SUMIF($C$7:$C$127,I53,$D$7:$D$127)+SUMIF($E$7:$E$135,I53,$F$7:$F$127) | M53: =L53-G52 | O53: =L53-B52 | P53: =J53-K53 | Q53: =D52-F52
A54: 生物資產－非流動 | B54: =SUM(B55) | G54: =SUM(G55) | H54: 增加不動產、廠房及設備、礦產資源 | J54: =OFFSET(A527,0,$K$1-1) | K54: =K55 | L54: =VLOOKUP(A54,$A$140:$AX$249,$K$1,FALSE) | M54: =L54-G54 | O54: =L54-B54 | P54: =J54-K54 | Q54: =D54-F54
A55: 生產性生物資產－非流動 | B55: =VLOOKUP(A55,$A$309:$AX$418,$K$1,FALSE) | E55: 109 | F55: =J23 | G55: =B55+SUM(D55:D55)-SUM(F55:F55) | H55: 增加不動產、廠房及設備 | J55: =OFFSET(A528,0,$K$1-1) | K55: =K56 | L55: =VLOOKUP(A55,$A$140:$AX$249,$K$1,FALSE) | M55: =L55-G55 | O55: =L55-B55 | P55: =J55-K55 | Q55: =D55-F55
A56: 無形資產 | B56: =SUM(B57) | G56: =SUM(G57) | H56: 固定資產之增置 | J56: =OFFSET(A529,0,$K$1-1) | K56: =SUM(K57:K63) | L56: =VLOOKUP(A56,$A$140:$AX$249,$K$1,FALSE) | M56: =L56-G56 | O56: =L56-B56 | P56: =J56-K56 | Q56: =D56-F56
A57: 無形資產 | B57: =VLOOKUP(A57,$A$309:$AX$418,$K$1,FALSE) | E57: 111 | F57: =J25 | G57: =B57+SUM(D57:D59)-SUM(F57:F59) | H57: 土地改良物 | I57: 251 | J57: =OFFSET(A530,0,$K$1-1) | K57: =-SUMIF($C$7:$C$127,I57,$D$7:$D$127)+SUMIF($E$7:$E$127,I57,$F$7:$F$127) | L57: =VLOOKUP(A57,$A$140:$AX$249,$K$1,FALSE) | M57: =L57-G57 | O57: =L57-B57 | P57: =J57-K57 | Q57: =D57-F57
A58: 0 | C58: 415 | D58: =J113 | E58: 416 | F58: =J114*-1 | H58: 房屋及建築 | I58: 252 | J58: =OFFSET(A531,0,$K$1-1) | K58: =-SUMIF($C$7:$C$127,I58,$D$7:$D$127)+SUMIF($E$7:$E$127,I58,$F$7:$F$127) | M58: =L58-G58 | O58: =L58-B58 | P58: =J58-K58 | Q58: =D58-F58
A59: 0 | C59: 258 | D59: =J65*-1 | E59: 112 | H59: 機械及設備 | I59: 253 | J59: =OFFSET(A532,0,$K$1-1) | K59: =-SUMIF($C$7:$C$127,I59,$D$7:$D$127)+SUMIF($E$7:$E$127,I59,$F$7:$F$127) | M59: =L59-G59 | O59: =L59-B59 | P59: =J59-K59 | Q59: =D59-F59
A60: 0 | H60: 交通及運輸設備 | I60: 254 | J60: =OFFSET(A533,0,$K$1-1) | K60: =-SUMIF($C$7:$C$127,I60,$D$7:$D$127)+SUMIF($E$7:$E$127,I60,$F$7:$F$127) | M60: =L60-G60 | O60: =L60-B60 | P60: =J60-K60 | Q60: =D60-F60
A61: 其他資產 | B61: =SUM(B62,B65,B68) | G61: =SUM(G62,G65,G68) | H61: 什項設備 | I61: 255 | J61: =OFFSET(A534,0,$K$1-1) | K61: =-SUMIF($C$7:$C$127,I61,$D$7:$D$127)+SUMIF($E$7:$E$127,I61,$F$7:$F$127) | L61: =VLOOKUP(A61,$A$140:$AX$249,$K$1,FALSE) | M61: =L61-G61 | O61: =L61-B61 | P61: =J61-K61 | Q61: =D61-F61
A62: 遞延資產 | B62: =VLOOKUP(A62,$A$309:$AX$418,$K$1,FALSE) | E62: 112 | F62: =J26-F59 | G62: =B62+SUM(D62:D64)-SUM(F62:F64) | H62: 購建中固定資產 | I62: 256 | J62: =OFFSET(A535,0,$K$1-1) | K62: =-SUMIF($C$7:$C$127,I62,$D$7:$D$127)+SUMIF($E$7:$E$127,I62,$F$7:$F$127) | L62: =VLOOKUP(A62,$A$140:$AX$249,$K$1,FALSE) | M62: =L62-G62 | O62: =L62-B62 | P62: =J62-K62 | Q62: =D62-F62
A63: 0 | D63: =J126 | F63: =J127*-1 | H63: 租賃權益改良 | I63: 257 | J63: =OFFSET(A536,0,$K$1-1) | K63: =-SUMIF($C$7:$C$127,I63,$D$7:$D$127)+SUMIF($E$7:$E$127,I63,$F$7:$F$127) | M63: =L63-G63 | O63: =L63-B63 | P63: =J63-K63 | Q63: =D63-F63
A64: 0 | C64: 259 | D64: =J67*-1 | H64: 增加無形資產及其他資產 | J64: =OFFSET(A537,0,$K$1-1) | K64: =K65+K66 | M64: =L64-G64 | O64: =L64-B64 | P64: =J64-K64 | Q64: =D64-F64
A65: 什項資產 | B65: =VLOOKUP(A65,$A$309:$AX$418,$K$1,FALSE) | C65: 417 | D65: =F111 | E65: 108 | F65: =J22 | G65: =B65+SUM(D65:D67)-SUM(F65:F67) | H65: 增加無形資產 | I65: 258 | J65: =OFFSET(A538,0,$K$1-1) | K65: =-SUMIF($C$7:$C$127,I65,$D$7:$D$127)+SUMIF($E$7:$E$127,I65,$F$7:$F$127) | L65: =VLOOKUP(A65,$A$140:$AX$249,$K$1,FALSE) | M65: =L65-G65 | O65: =L65-B65 | P65: =J65-K65 | Q65: =D65-F65
A66: 0 | H66: 增加其他資產 | J66: =OFFSET(A539,0,$K$1-1) | K66: =K67 | M66: =L66-G66 | O66: =L66-B66 | P66: =J66-K66 | Q66: =D66-F66
A67: 0 | H67: 增加遞延費用 | I67: 259 | J67: =OFFSET(A540,0,$K$1-1) | K67: =-SUMIF($C$7:$C$127,I67,$D$7:$D$127)+SUMIF($E$7:$E$127,I67,$F$7:$F$127) | M67: =L67-G67 | O67: =L67-B67 | P67: =J67-K67 | Q67: =D67-F67
G68: =B68+D68-F68 | H68: ▼投資活動之淨現金流入（流出） | J68: =OFFSET(A541,0,$K$1-1) | K68: =K40 | P68: =J68-K68 | Q68: =D68-F68
A69: 合 計 | B69: =B7+B17+B26+B54+B56+B61 | G69: =G7+G17+G26+G54+G56+G61 | H69: ▼籌資活動之現金流量 | J69: =OFFSET(A542,0,$K$1-1) | K69: =K70+K72+K74+K81+K79+K83 | L69: =VLOOKUP(A69,$A$140:$AX$249,$K$1,FALSE) | M69: =L69-G69 | O69: =L69-B69 | P69: =J69-K69 | Q69: =D69-F69
A70: 負債 | B70: =B71+B78+B83 | G70: =G71+G78+G83 | H70: 增加短期債務、流動金融負債及其他負債 | J70: =OFFSET(A543,0,$K$1-1) | K70: =K71 | L70: =VLOOKUP(A70,$A$253:$AX$305,$K$1,FALSE) | M70: =L70-G70 | O70: =L70-B70 | P70: =J70-K70 | Q70: =D70-F70
A71: 流動負債 | B71: =SUM(B72:B77) | G71: =SUM(G72:G77) | H71: 增加其他負債 | I71: 311 | J71: =OFFSET(A544,0,$K$1-1) | K71: =-SUMIF($C$7:$C$127,I71,$D$7:$D$127)+SUMIF($E$7:$E$127,I71,$F$7:$F$127) | L71: =VLOOKUP(A71,$A$253:$AX$305,$K$1,FALSE) | M71: =L71-G71 | O71: =L71-B71 | P71: =J71-K71 | Q71: =D71-F71
A72: 短期債務 | B72: =VLOOKUP(A72,$A$423:$AX$475,$K$1,FALSE) | C72: 322 | D72: =J82*-1 | E72: 418 | F72: =D81 | G72: =B72+SUM(F72:F73)-SUM(D72:D73) | H72: 增加長期負債 | J72: =OFFSET(A545,0,$K$1-1) | K72: =K73 | L72: =VLOOKUP(A72,$A$253:$AX$305,$K$1,FALSE) | M72: =L72-G72 | O72: =L72-B72 | P72: =J72-K72 | Q72: =D72-F72
A73: 0 | C73: 316 | H73: 增加長期債務 | I73: 312 | J73: =OFFSET(A546,0,$K$1-1) | K73: =-SUMIF($C$7:$C$127,I73,$D$7:$D$127)+SUMIF($E$7:$E$127,I73,$F$7:$F$127) | M73: =L73-G73 | O73: =L73-B73 | P73: =J73-K73 | Q73: =D73-F73
A74: 應付款項 | B74: =VLOOKUP(A74,$A$423:$AX$475,$K$1,FALSE) | E74: 161 | G74: =B74+SUM(F74:F75)-SUM(D74:D75) | H74: 增加基金、公積及填補短絀 | J74: =OFFSET(A547,0,$K$1-1) | K74: =SUM(K75) | L74: =VLOOKUP(A74,$A$253:$AX$305,$K$1,FALSE) | M74: =L74-G74 | O74: =L74-B74 | P74: =J74-K74 | Q74: =D74-F74
A75: 0 | H75: 增加基金 | J75: =OFFSET(A548,0,$K$1-1) | K75: =SUM(K76:K78) | M75: =L75-G75 | O75: =L75-B75 | P75: =J75-K75 | Q75: =D75-F75
A76: 預收款項 | B76: =VLOOKUP(A76,$A$423:$AX$475,$K$1,FALSE) | E76: 161 | F76: =J34 | G76: =B76+SUM(F76:F77)-SUM(D76:D77) | H76: 國庫撥款增置固定資產 | I76: 313 | J76: =OFFSET(A549,0,$K$1-1) | K76: =-SUMIF($C$7:$C$127,I76,$D$7:$D$127)+SUMIF($E$7:$E$127,I76,$F$7:$F$127) | L76: =VLOOKUP(A76,$A$253:$AX$305,$K$1,FALSE) | M76: =L76-G76 | O76: =L76-B76 | P76: =J76-K76 | Q76: =D76-F76
A77: 0 | H77: 國庫增撥無形資產 | I77: 314 | J77: =OFFSET(A550,0,$K$1-1) | K77: =-SUMIF($C$7:$C$127,I77,$D$7:$D$127)+SUMIF($E$7:$E$127,I77,$F$7:$F$127) | M77: =L77-G77 | O77: =L77-B77 | P77: =J77-K77 | Q77: =D77-F77
A78: 長期負債 | B78: =SUM(B81) | G78: =SUM(G81) | H78: 國庫增撥遞延資產 | I78: 315 | J78: =OFFSET(A551,0,$K$1-1) | K78: =-SUMIF($C$7:$C$127,I78,$D$7:$D$127)+SUMIF($E$7:$E$127,I78,$F$7:$F$127) | L78: =VLOOKUP(A78,$A$253:$AX$305,$K$1,FALSE) | M78: =L78-G78 | O78: =L78-B78 | P78: =J78-K78 | Q78: =D78-F78
H79: 減少短期債務、流動金融負債及其他負債 | J79: =OFFSET(A552,0,$K$1-1)
H80: 減少短期債務 | I80: 316 | J80: =OFFSET(A553,0,$K$1-1) | K80: =-SUMIF($C$7:$C$127,I80,$D$7:$D$127)+SUMIF($E$7:$E$127,I80,$F$7:$F$127)
A81: 長期債務 | B81: =VLOOKUP(A81,$A$423:$AX$475,$K$1,FALSE) | C81: 418 | D81: =J116 | E81: 312 | F81: =J73 | G81: =B81+SUM(F81:F82)-SUM(D81:D82) | H81: 減少長期負債 | J81: =OFFSET(A554,0,$K$1-1) | K81: =K82 | L81: =VLOOKUP(A81,$A$253:$AX$305,$K$1,FALSE) | M81: =L81-G81 | O81: =L81-B81 | P81: =J81-K81 | Q81: =D81-F81
A82: 0 | C82: 322 | H82: 減少長期債務 | I82: 322 | J82: =OFFSET(A555,0,$K$1-1) | K82: =-SUMIF($C$7:$C$127,I82,$D$7:$D$127)+SUMIF($E$7:$E$127,I82,$F$7:$F$127) | M82: =L82-G82 | O82: =L82-B82 | P82: =J82-K82 | Q82: =D72-F82
A83: 其他負債 | B83: =SUM(B84,B90) | G83: =SUM(G84,G90) | H83: 支付利息 | J83: =OFFSET(A556,0,$K$1-1) | K83: =J83 | L83: =VLOOKUP(A83,$A$253:$AX$305,$K$1,FALSE) | M83: =L83-G83 | O83: =L83-B83 | P83: =J83-K83 | Q83: =D83-F83
A84: 什項負債 | B84: =VLOOKUP(A84,$A$423:$AX$475,$K$1,FALSE) | C84: 321 | G84: =B84+SUM(F84:F89)-SUM(D84:D89) | H84: ▼籌資活動之淨現金流入（流出） | J84: =OFFSET(A557,0,$K$1-1) | K84: =K69 | L84: =VLOOKUP(A84,$A$253:$AX$305,$K$1,FALSE) | M84: =L84-G84 | O84: =L84-B84 | P84: =J84-K84 | Q84: =D84-F84
A85: 0 | C85: 402 | D85: =J91*-1 | E85: 122 | F85: =J28 | H85: ▼現金及約當現金之淨增（淨減） | I85: B | J85: =OFFSET(A558,0,$K$1-1) | K85: =J85 | M85: =L85-G85 | O85: =L85-B85 | P85: =J85-K85 | Q85: =D85-F85
A86: 0 | E86: 401 | F86: =J90 | H86: ▼期初現金及約當現金 | J86: =OFFSET(A559,0,$K$1-1) | K86: =B8 | M86: =L86-G86 | O86: =L86-B86 | P86: =J86-K86 | Q86: =D86-F86
A87: 0 | H87: ▼期末現金及約當現金 | J87: =OFFSET(A560,0,$K$1-1) | K87: =G8 | M87: =L87-G87 | O87: =L87-B87 | P87: =J87-K87 | Q87: =D87-F87
A88: 0 | H88: ▼不影響現金流量之投資與籌資活動 | J88: =OFFSET(A561,0,$K$1-1) | M88: =L88-G88 | O88: =L88-B88 | P88: =J88-K88 | Q88: =D88-F88
A89: 0 | H89: 退休離職準備金與應付退休及離職金同額增加(+)或減少(-)之金額 | J89: =OFFSET(A562,0,$K$1-1) | K89: =K90+K91 | M89: =L89-G89 | O89: =L89-B89 | P89: =J89-K89 | Q89: =D89-F89
A90: 遞延負債 | B90: =VLOOKUP(A90,$A$423:$AX$475,$K$1,FALSE) | C90: 124 | D90: =J31*-1 | E90: 311 | F90: =J71 | G90: =B90+SUM(F90:F96)-SUM(D90:D96) | H90: 退休離職準備金與應付退休及離職金同額增加之金額(+) | I90: 401 | J90: =OFFSET(A563,0,$K$1-1) | K90: =(SUMIF($C$7:$C$127,I90,$D$7:$D$127)+SUMIF($E$7:$E$127,I90,$F$7:$F$127))/2 | L90: =VLOOKUP(A90,$A$253:$AX$305,$K$1,FALSE) | M90: =L90-G90 | O90: =L90-B90 | P90: =J90-K90 | Q90: =D90-F90
A91: 0 | C91: 123 | D91: =-J30 | E91: 403 | F91: =J93 | H91: 退休離職準備金與應付退休及離職金同額減少之金額(-) | I91: 402 | J91: =OFFSET(A564,0,$K$1-1) | K91: =(SUMIF($C$7:$C$127,I91,$D$7:$D$127)+SUMIF($E$7:$E$127,I91,$F$7:$F$127))/2*-1 | M91: =L91-G91 | O91: =L91-B91 | P91: =J91-K91 | Q91: =D91-F91
A92: 0 | E92: 407 | F92: =J101 | H92: 其他準備金與遞延收入同額增加之金額 | J92: =OFFSET(A565,0,$K$1-1) | K92: =K93 | M92: =L92-G92 | O92: =L92-B92 | P92: =J92-K92 | Q92: =D92-F92
A93: 0 | E93: 408 | F93: =J102 | H93: 其他準備金與遞延收入同額增加之金額 | I93: 403 | J93: =OFFSET(A566,0,$K$1-1) | K93: =(SUMIF($C$7:$C$127,I93,$D$7:$D$127)+SUMIF($E$7:$E$127,I93,$F$7:$F$127))/2 | M93: =L93-G93 | O93: =L93-B93 | P93: =J93-K93 | Q93: =D93-F93
E94: 410 | H94: 以前年度購建中固定資產科目，調整轉入不動產、廠房及設備科目之 | J94: =OFFSET(A567,0,$K$1-1) | K94: =K95 | P94: =J94-K94
H95: 調整轉入不動產、廠房及設備科目明細 | J95: =OFFSET(A568,0,$K$1-1) | K95: =K96+K97+K98 | O95: =L95-B96 | P95: =J95-K95 | Q95: =D96-F96
A96: 0 | H96: 土地改良物 | I96: 404 | J96: =OFFSET(A569,0,$K$1-1) | K96: =(SUMIF($C$7:$C$127,I96,$D$7:$D$127)+SUMIF($E$7:$E$127,I96,$F$7:$F$127))/2 | O96: =L97-B97 | P96: =J96-K96 | Q96: =D97-F97
A97: 淨值 | B97: =B98+B110+B116+B125 | G97: =G98+G110+G116+G125 | H97: 房屋及建築 | I97: 405 | J97: =OFFSET(A570,0,$K$1-1) | K97: =(SUMIF($C$7:$C$127,I97,$D$7:$D$127)+SUMIF($E$7:$E$127,I97,$F$7:$F$127))/2 | L97: =VLOOKUP(A97,$A$253:$AX$305,$K$1,FALSE) | M97: =L97-G97 | O97: =L98-B98 | P97: =J97-K97 | Q97: =D98-F98
A98: 基金 | B98: =SUM(B99:B101) | G98: =SUM(G99:G101) | H98: 什項設備 | I98: 406 | J98: =OFFSET(A571,0,$K$1-1) | K98: =(SUMIF($C$7:$C$127,I98,$D$7:$D$127)+SUMIF($E$7:$E$127,I98,$F$7:$F$127))/2 | L98: =VLOOKUP(A98,$A$253:$AX$305,$K$1,FALSE) | M98: =L98-G98 | O98: =L99-B99 | P98: =J98-K98 | Q98: =D99-F99
A99: 基金 | B99: =VLOOKUP(A99,$A$423:$AX$475,$K$1,FALSE) | E99: 313 | F99: =J76 | G99: =B99+SUM(F99:F109)-SUM(D99:D109) | H99: 不動產、廠房及設備與遞延收入同額增加(+)或減少(-)之金額 | J99: =OFFSET(A572,0,$K$1-1) | K99: =K100 | L99: =VLOOKUP(A99,$A$253:$AX$305,$K$1,FALSE) | M99: =L99-G99 | O99: =L100-B100 | P99: =J99-K99 | Q99: =D100-F100
A100: 0 | E100: 314 | F100: =J77 | H100: 不動產、廠房及設備與遞延收入同額增加明細(+) | J100: =OFFSET(A573,0,$K$1-1) | K100: =K101+K102 | M100: =L100-G100 | O100: =L101-B101 | P100: =J100-K100 | Q100: =D101-F101
...

Sheet 中興
A1: =OFFSET(A139,0,K1-1) | K1: =L1+2 | L1: 4
A2: 預計平衡表與現金流量表勾稽底稿
A3: 中華民國115年度
A4: 科目 | B4: 114.12.31 | C4: 調整項目 | G4: 115.12.31 | H4: 現金流量表勾稽項目
B5: 預計數 | D5: 借方 | F5: 貸方 | G5: 預計數
A6: 資產 | H6: ▼業務活動之現金流量 | L6: 114年12月 | M6: 差異數要再加(減) | O6: 比較增減 | Q6: 調整項目
A7: 流動資產 | B7: =SUM(B8:B16) | G7: =SUM(G8:G16) | H7: 本期賸餘（短絀） | I7: A | J7: =OFFSET(A480,0,$K$1-1) | K7: =-SUMIF($C$7:$C$127,I7,$D$7:$D$127)+SUMIF($E$7:$E$127,I7,$F$7:$F$127) | L7: =VLOOKUP(A7,$A$140:$AX$249,$K$1,FALSE) | M7: =L7-G7 | O7: =L7-B7 | P7: =J7-K7 | Q7: =D7-F7
A8: 現金 | B8: =VLOOKUP(A8,$A$309:$AX$418,$K$1,FALSE) | C8: B | D8: =IF(G8-B8>0,G8-B8,"0") | E8: B | F8: =IF(G8-B8<0,B8-G8,"0") | G8: =J87 | H8: 利息股利之調整 | J8: =OFFSET(A481,0,$K$1-1) | K8: =SUM(K9:K11) | L8: =VLOOKUP(A8,$A$140:$AX$249,$K$1,FALSE) | M8: =L8-G8 | O8: =L8-B8 | P8: =J8-K8 | Q8: =D8-F8
A9: 流動金融資產 | B9: =VLOOKUP(A9,$A$309:$AX$418,$K$1,FALSE) | C9: 231 | D9: =J50*-1 | E9: 211 | F9: =J42 | G9: =B9+D9-F9+D10-F10 | H9: 利息收入 | J9: =OFFSET(A482,0,$K$1-1) | K9: =J9 | L9: =VLOOKUP(A9,$A$140:$AX$249,$K$1,FALSE) | M9: =L9-G9 | O9: =L9-B9 | P9: =J9-K9 | Q9: =D9-F9
C10: 125 | H10: 股利收入 | J10: =OFFSET(A483,0,$K$1-1) | K10: =J10 | M10: =L10-G10 | O10: =L10-B10 | P10: =J10-K10 | Q10: =D10-F10
A11: 應收款項 | B11: =VLOOKUP(A11,$A$309:$AX$418,$K$1,FALSE) | C11: 151 | E11: 151 | G11: =B11+D11-F11 | H11: 利息費用 | J11: =OFFSET(A484,0,$K$1-1) | K11: =J11 | L11: =VLOOKUP(A11,$A$140:$AX$249,$K$1,FALSE) | M11: =L11-G11 | O11: =L11-B11 | P11: =J11-K11 | Q11: =D11-F11
A12: 0 | H12: 未計利息股利之本期賸餘（短絀） | J12: =OFFSET(A485,0,$K$1-1) | K12: =K7+K8 | M12: =L12-G12 | O12: =L12-B12 | P12: =J12-K12 | Q12: =D12-F12
A13: 存貨 | B13: =VLOOKUP(A13,$A$309:$AX$418,$K$1,FALSE) | C13: 151 | E13: 151 | G13: =B13+D13-F13 | H13: 調整項目 | J13: =OFFSET(A486,0,$K$1-1) | K13: =SUM(K14,K24,K27,K34,K33) | L13: =VLOOKUP(A13,$A$140:$AX$249,$K$1,FALSE) | M13: =L13-G13 | O13: =L13-B13 | P13: =J13-K13 | Q13: =D13-F13
A14: 生產性生物資產－流動 | B14: =VLOOKUP(A14,$A$309:$AX$418,$K$1,FALSE) | C14: 151 | E14: 151 | G14: =B14+D14-F14 | H14: 折舊、減損及折耗 | J14: =OFFSET(A487,0,$K$1-1) | K14: =SUM(K15:K23) | L14: =VLOOKUP(A14,$A$140:$AX$249,$K$1,FALSE) | M14: =L14-G14 | O14: =L14-B14 | P14: =J14-K14 | Q14: =D14-F14
A15: 預付款項 | B15: =VLOOKUP(A15,$A$309:$AX$418,$K$1,FALSE) | C15: 151 | E15: 151 | G15: =B15+D15-F15 | H15: 土地改良物 | I15: 101 | J15: =OFFSET(A488,0,$K$1-1) | K15: =-SUMIF($C$7:$C$127,I15,$D$7:$D$127)+SUMIF($E$7:$E$127,I15,$F$7:$F$127) | L15: =VLOOKUP(A15,$A$140:$AX$249,$K$1,FALSE) | M15: =L15-G15 | O15: =L15-B15 | P15: =J15-K15 | Q15: =D15-F15
A16: 短期貸墊款 | B16: =VLOOKUP(A16,$A$309:$AX$418,$K$1,FALSE) | C16: 151 | E16: 212 | F16: =J43 | G16: =B16+D16-F16 | H16: 房屋及建築 | I16: 102 | J16: =OFFSET(A489,0,$K$1-1) | K16: =-SUMIF($C$7:$C$127,I16,$D$7:$D$127)+SUMIF($E$7:$E$127,I16,$F$7:$F$127) | L16: =VLOOKUP(A16,$A$140:$AX$249,$K$1,FALSE) | M16: =L16-G16 | O16: =L16-B16 | P16: =J16-K16 | Q16: =D16-F16
A17: 投資、長期應收款、貸墊款及準備金 | B17: =SUM(B18:B21) | G17: =SUM(G18:G21) | H17: 機械及設備 | I17: 103 | J17: =OFFSET(A490,0,$K$1-1) | K17: =-SUMIF($C$7:$C$127,I17,$D$7:$D$127)+SUMIF($E$7:$E$127,I17,$F$7:$F$127) | L17: =VLOOKUP(A17,$A$140:$AX$249,$K$1,FALSE) | M17: =L17-G17 | O17: =L17-B17 | P17: =J17-K17 | Q17: =D17-F17
A18: 採權益法之投資 | B18: =VLOOKUP(A18,$A$309:$AX$418,$K$1,FALSE) | G18: =D18+F18+B18 | H18: 交通及運輸設備 | I18: 104 | J18: =OFFSET(A491,0,$K$1-1) | K18: =-SUMIF($C$7:$C$127,I18,$D$7:$D$127)+SUMIF($E$7:$E$127,I18,$F$7:$F$127) | L18: =VLOOKUP(A18,$A$140:$AX$249,$K$1,FALSE) | M18: =L18-G18 | O18: =L18-B18 | P18: =J18-K18 | Q18: =D18-F18
A19: 非流動金融資產 | B19: =VLOOKUP(A19,$A$309:$AX$418,$K$1,FALSE) | C19: 241 | D19: =J52*-1 | E19: 221 | F19: =J45 | G19: =B19+D19-F19 | H19: 什項設備 | I19: 105 | J19: =OFFSET(A492,0,$K$1-1) | K19: =-SUMIF($C$7:$C$127,I19,$D$7:$D$127)+SUMIF($E$7:$E$127,I19,$F$7:$F$127) | L19: =VLOOKUP(A19,$A$140:$AX$249,$K$1,FALSE) | M19: =L19-G19 | O19: =L19-B19 | P19: =J19-K19 | Q19: =D19-F19
A20: 長期應收款 | B20: =VLOOKUP(A20,$A$309:$AX$418,$K$1,FALSE) | G20: =B20+D20-F20 | H20: 租賃資產 | I20: 106 | J20: =OFFSET(A493,0,$K$1-1) | K20: =-SUMIF($C$7:$C$127,I20,$D$7:$D$127)+SUMIF($E$7:$E$127,I20,$F$7:$F$127) | L20: =VLOOKUP(A20,$A$140:$AX$249,$K$1,FALSE) | M20: =L20-G20 | O20: =L20-B20 | P20: =J20-K20 | Q20: =D20-F20
A21: 準備金 | B21: =VLOOKUP(A21,$A$309:$AX$418,$K$1,FALSE) | C21: 242 | D21: =J53*-1 | E21: 222 | F21: =J46 | G21: =B21+SUM(D21:D25)-SUM(F21:F25) | H21: 租賃權益改良 | I21: 107 | J21: =OFFSET(A494,0,$K$1-1) | K21: =-SUMIF($C$7:$C$127,I21,$D$7:$D$127)+SUMIF($E$7:$E$127,I21,$F$7:$F$127) | L21: =VLOOKUP(A21,$A$140:$AX$249,$K$1,FALSE) | M21: =L21-G21 | O21: =L21-B21 | P21: =J21-K21 | Q21: =D21-F21
A22: 0 | C22: 401 | D22: =J90 | E22: 402 | F22: =-J91 | H22: 代管資產 | I22: 108 | J22: =OFFSET(A495,0,$K$1-1) | K22: =-SUMIF($C$7:$C$127,I22,$D$7:$D$127)+SUMIF($E$7:$E$127,I22,$F$7:$F$127) | M22: =L22-G22 | O22: =L22-B22 | P22: =J22-K22 | Q22: =D22-F22
A23: 0 | C23: 403 | D23: =J93 | H23: 生產性生物資產－非流動 | I23: 109 | J23: =OFFSET(A496,0,$K$1-1) | K23: =-SUMIF($C$7:$C$127,I23,$D$7:$D$127)+SUMIF($E$7:$E$127,I23,$F$7:$F$127) | M23: =L23-G23 | O23: =L23-B23 | P23: =J23-K23 | Q23: =D23-F23
A24: 0 | H24: 攤銷 | J24: =OFFSET(A497,0,$K$1-1) | K24: =SUM(K25:K26) | M24: =L24-G24 | O24: =L24-B24 | P24: =J24-K24 | Q24: =D24-F24
C25: 125 | D25: =J32*-1 | H25: 攤銷電腦軟體 | I25: 111 | J25: =OFFSET(A498,0,$K$1-1) | K25: =-SUMIF($C$7:$C$127,I25,$D$7:$D$127)+SUMIF($E$7:$E$127,I25,$F$7:$F$127) | M25: =L25-G25 | O25: =L25-B25 | P25: =J25-K25 | Q25: =D25-F25
A26: 不動產、廠房及設備 | B26: =SUM(B27:B52) | G26: =SUM(G27:G52) | H26: 其他攤銷費用 | I26: 112 | J26: =OFFSET(A499,0,$K$1-1) | K26: =-SUMIF($C$7:$C$127,I26,$D$7:$D$127)+SUMIF($E$7:$E$127,I26,$F$7:$F$127) | L26: =VLOOKUP(A26,$A$140:$AX$249,$K$1,FALSE) | M26: =L26-G26 | O26: =L26-B26 | P26: =J26-K26 | Q26: =D26-F26
A27: 土地 | B27: =VLOOKUP(A27,$A$309:$AX$418,$K$1,FALSE) | C27: 121 | G27: =B27+SUM(D27)-SUM(F27) | H27: 其他 | J27: =OFFSET(A500,0,$K$1-1) | K27: =K28+K29+K32 | L27: =VLOOKUP(A27,$A$140:$AX$249,$K$1,FALSE) | M27: =L27-G27 | O27: =L27-B27 | P27: =J27-K27 | Q27: =D27-F27
A28: 0 | H28: 應付退休及離職金 | I28: 122 | J28: =OFFSET(A501,0,$K$1-1) | K28: =-SUMIF($C$7:$C$127,I28,$D$7:$D$127)+SUMIF($E$7:$E$127,I28,$F$7:$F$127) | M28: =L28-G28 | O28: =L28-B28 | P28: =J28-K28 | Q28: =D28-F28
A29: 土地改良物 | B29: =VLOOKUP(A29,$A$309:$AX$418,$K$1,FALSE) | C29: 251 | D29: =J57*-1 | E29: 101 | F29: =J15 | G29: =B29+SUM(D29:D32)-SUM(F29:F32) | H29: 遞延收入 | J29: =OFFSET(A502,0,$K$1-1) | K29: =SUM(K30:K31) | L29: =VLOOKUP(A29,$A$140:$AX$249,$K$1,FALSE) | M29: =L29-G29 | O29: =L29-B29 | P29: =J29-K29 | Q29: =D29-F29
A30: 0 | C30: 404 | D30: =J96 | H30: 遞延收入-其他補助收入 | I30: 123 | J30: =OFFSET(A503,0,$K$1-1) | K30: =-SUMIF($C$7:$C$127,I30,$D$7:$D$127)+SUMIF($E$7:$E$127,I30,$F$7:$F$127) | M30: =L30-G30 | O30: =L30-B30 | P30: =J30-K30 | Q30: =D30-F30
A31: 0 | H31: 遞延收入-受贈收入 | I31: 124 | J31: =OFFSET(A504,0,$K$1-1) | K31: =-SUMIF($C$7:$C$127,I31,$D$7:$D$127)+SUMIF($E$7:$E$127,I31,$F$7:$F$127) | M31: =L31-G31 | O31: =L31-B31 | P31: =J31-K31 | Q31: =D31-F31
A32: 0 | H32: 其他 | I32: 125 | J32: =OFFSET(A505,0,$K$1-1) | M32: =L32-G32 | O32: =L32-B32 | P32: =J32-K32 | Q32: =D32-F32
A33: 房屋及建築 | B33: =VLOOKUP(A33,$A$309:$AX$418,$K$1,FALSE) | C33: 252 | D33: =J58*-1 | E33: 102 | F33: =J16 | G33: =B33+SUM(D33:D36)-SUM(F33:F36) | H33: 流動資產淨減（淨增） | I33: 151 | J33: =OFFSET(A506,0,$K$1-1) | K33: =-SUMIF($C$7:$C$127,I33,$D$7:$D$127)+SUMIF($E$7:$E$127,I33,$F$7:$F$127) | L33: =VLOOKUP(A33,$A$140:$AX$249,$K$1,FALSE) | M33: =L33-G33 | O33: =L33-B33 | P33: =J33-K33 | Q33: =D33-F33
A34: 0 | C34: 405 | D34: =J97 | H34: 流動負債淨增（淨減） | I34: 161 | J34: =OFFSET(A507,0,$K$1-1) | K34: =-SUMIF($C$7:$C$127,I34,$D$7:$D$127)+SUMIF($E$7:$E$127,I34,$F$7:$F$127) | M34: =L34-G34 | O34: =L34-B34 | P34: =J34-K34 | Q34: =D34-F34
A35: 0 | H35: 未計利息股利之現金流入（流出） | J35: =OFFSET(A508,0,$K$1-1) | K35: =K12+K13 | M35: =L35-G35 | O35: =L35-B35 | P35: =J35-K35 | Q35: =D35-F35
A36: 0 | H36: 收取利息 | J36: =OFFSET(A509,0,$K$1-1) | K36: =J36 | M36: =L36-G36 | O36: =L36-B36 | P36: =J36-K36 | Q36: =D36-F36
A37: 機械及設備 | B37: =VLOOKUP(A37,$A$309:$AX$418,$K$1,FALSE) | C37: 253 | D37: =J59*-1 | E37: 103 | F37: =J17 | G37: =B37+SUM(D37:D41)-SUM(F37:F41) | H37: 收取股利 | J37: =OFFSET(A510,0,$K$1-1) | K37: =J37 | L37: =VLOOKUP(A37,$A$140:$AX$249,$K$1,FALSE) | M37: =L37-G37 | O37: =L37-B37 | P37: =J37-K37 | Q37: =D37-F37
A38: 0 | C38: 407 | D38: =J101 | H38: 支付利息 | J38: =OFFSET(A511,0,$K$1-1) | K38: =J38 | M38: =L38-G38 | O38: =L38-B38 | P38: =J38-K38 | Q38: =D38-F38
A39: 0 | C39: 409 | D39: =J105 | E39: 412 | F39: =-J109 | H39: ▼業務活動之淨現金流入（流出） | J39: =OFFSET(A512,0,$K$1-1) | K39: =K36+K37+K38+K35 | M39: =L39-G39 | O39: =L39-B39 | P39: =J39-K39 | Q39: =D39-F39
A40: 0 | H40: ▼投資活動之現金流量 | J40: =OFFSET(A513,0,$K$1-1) | K40: =SUM(K41,K44,K47,K48,K49,K51,K54,K64) | M40: =L40-G40 | O40: =L40-B40 | P40: =J40-K40 | Q40: =D40-F40
H41: 減少流動金融資產及短期貸墊款 | J41: =OFFSET(A514,0,$K$1-1) | K41: =K42+K43 | M41: =L41-G41 | O41: =L41-B41 | P41: =J41-K41 | Q41: =D41-F41
A42: 交通及運輸設備 | B42: =VLOOKUP(A42,$A$309:$AX$418,$K$1,FALSE) | C42: 254 | D42: =J60*-1 | E42: 104 | F42: =J18 | G42: =B42+SUM(D42:D44)-SUM(F42:F44) | H42: 減少流動金融資產 | I42: 211 | J42: =OFFSET(A515,0,$K$1-1) | K42: =-SUMIF($C$7:$C$127,I42,$D$7:$D$127)+SUMIF($E$7:$E$135,I42,$F$7:$F$127) | L42: =VLOOKUP(A42,$A$140:$AX$249,$K$1,FALSE) | M42: =L42-G42 | O42: =L42-B42 | P42: =J42-K42 | Q42: =D42-F42
C43: 410 | D43: =J106 | E43: 413 | F43: =J110*-1 | H43: 減少短期墊款 | I43: 212 | J43: =OFFSET(A516,0,$K$1-1) | K43: =-SUMIF($C$7:$C$127,I43,$D$7:$D$127)+SUMIF($E$7:$E$135,I43,$F$7:$F$127) | M43: =L43-G43 | O43: =L43-B43 | P43: =J43-K43 | Q43: =D43-F43
H44: 減少投資、長期應收款、貸墊款及準備金 | J44: =OFFSET(A517,0,$K$1-1) | K44: =SUM(K45:K46) | M44: =L44-G44 | O44: =L44-B44 | P44: =J44-K44 | Q44: =D44-F44
A45: 什項設備 | B45: =VLOOKUP(A45,$A$309:$AX$418,$K$1,FALSE) | C45: 255 | D45: =J61*-1 | E45: 105 | F45: =J19 | G45: =B45+SUM(D45:D48)-SUM(F45:F48) | H45: 減少投資 | I45: 221 | J45: =OFFSET(A518,0,$K$1-1) | K45: =-SUMIF($C$7:$C$127,I45,$D$7:$D$127)+SUMIF($E$7:$E$135,I45,$F$7:$F$127) | L45: =VLOOKUP(A45,$A$140:$AX$249,$K$1,FALSE) | M45: =L45-G45 | O45: =L45-B45 | P45: =J45-K45 | Q45: =D45-F45
A46: 0 | C46: 408 | D46: =J102 | H46: 減少準備金 | I46: 222 | J46: =OFFSET(A519,0,$K$1-1) | K46: =-SUMIF($C$7:$C$127,I46,$D$7:$D$127)+SUMIF($E$7:$E$135,I46,$F$7:$F$127) | M46: =L46-G46 | O46: =L46-B46 | P46: =J46-K46 | Q46: =D46-F46
A47: 0 | C47: 411 | D47: =J107 | E47: 414 | F47: =-J111 | H47: 收取利息 | J47: =OFFSET(A520,0,$K$1-1) | K47: =J47 | M47: =L47-G47 | O47: =L47-B47 | P47: =J47-K47 | Q47: =D47-F47
A48: 0 | C48: 406 | D48: =J98 | H48: 收取股利 | J48: =OFFSET(A521,0,$K$1-1) | K48: =J48 | M48: =L48-G48 | O48: =L48-B48 | P48: =J48-K48 | Q48: =D48-F48
A49: 租賃資產 | B49: =VLOOKUP(A49,$A$309:$AX$413,$K$1,FALSE) | E49: 106 | F49: =J20 | G49: =B49+D49-F49 | H49: 增加流動金融資產及短期貸墊款 | J49: =OFFSET(A522,0,$K$1-1) | K49: =K50 | L49: =VLOOKUP(A49,$A$140:$AX$249,$K$1,FALSE) | M49: =L49-G49 | O49: =L49-B49 | P49: =J49-K49 | Q49: =D49-F49
A50: 租賃權益改良 | B50: =VLOOKUP(A50,$A$309:$AX$418,$K$1,FALSE) | C50: 257 | D50: =J63*-1 | E50: 107 | F50: =J21 | G50: =B50+D50-F50 | H50: 增加流動金融資產 | I50: 231 | J50: =OFFSET(A523,0,$K$1-1) | K50: =-SUMIF($C$7:$C$127,I50,$D$7:$D$127)+SUMIF($E$7:$E$135,I50,$F$7:$F$127) | L50: =VLOOKUP(A50,$A$140:$AX$249,$K$1,FALSE) | M50: =L50-G50 | O50: =L50-B49 | P50: =J50-K50 | Q50: =D49-F49
A51: 購建中固定資產 | B51: =VLOOKUP(A51,$A$309:$AX$418,$K$1,FALSE) | C51: 256 | D51: =J62*-1 | E51: 404 | F51: =J96 | G51: =B51+SUM(D51:D53)-SUM(F51:F53) | H51: 增加投資、長期應收款、貸墊款及準備金 | J51: =OFFSET(A524,0,$K$1-1) | K51: =SUM(K52:K53) | L51: =VLOOKUP(A51,$A$140:$AX$249,$K$1,FALSE) | M51: =L51-G51 | O51: =L51-B50 | P51: =J51-K51 | Q51: =D50-F50
E52: 405 | F52: =J97 | H52: 增加投資 | I52: 241 | J52: =OFFSET(A525,0,$K$1-1) | K52: =-SUMIF($C$7:$C$127,I52,$D$7:$D$127)+SUMIF($E$7:$E$135,I52,$F$7:$F$127) | M52: =L52-G52 | O52: =L52-B51 | P52: =J52-K52 | Q52: =D51-F51
E53: 406 | F53: =J98 | H53: 增加準備金 | I53: 242 | J53: =OFFSET(A526,0,$K$1-1) | K53: =-SUMIF($C$7:$C$127,I53,$D$7:$D$127)+SUMIF($E$7:$E$135,I53,$F$7:$F$127) | M53: =L53-G52 | O53: =L53-B52 | P53: =J53-K53 | Q53: =D52-F52
A54: 生物資產－非流動 | B54: =SUM(B55) | G54: =SUM(G55) | H54: 增加不動產、廠房及設備、礦產資源 | J54: =OFFSET(A527,0,$K$1-1) | K54: =K55 | L54: =VLOOKUP(A54,$A$140:$AX$249,$K$1,FALSE) | M54: =L54-G54 | O54: =L54-B54 | P54: =J54-K54 | Q54: =D54-F54
A55: 生產性生物資產－非流動 | B55: =VLOOKUP(A55,$A$309:$AX$418,$K$1,FALSE) | E55: 109 | F55: =J23 | G55: =B55+SUM(D55:D55)-SUM(F55:F55) | H55: 增加不動產、廠房及設備 | J55: =OFFSET(A528,0,$K$1-1) | K55: =K56 | L55: =VLOOKUP(A55,$A$140:$AX$249,$K$1,FALSE) | M55: =L55-G55 | O55: =L55-B55 | P55: =J55-K55 | Q55: =D55-F55
A56: 無形資產 | B56: =SUM(B57) | G56: =SUM(G57) | H56: 固定資產之增置 | J56: =OFFSET(A529,0,$K$1-1) | K56: =SUM(K57:K63) | L56: =VLOOKUP(A56,$A$140:$AX$249,$K$1,FALSE) | M56: =L56-G56 | O56: =L56-B56 | P56: =J56-K56 | Q56: =D56-F56
A57: 無形資產 | B57: =VLOOKUP(A57,$A$309:$AX$418,$K$1,FALSE) | E57: 111 | F57: =J25 | G57: =B57+SUM(D57:D59)-SUM(F57:F59) | H57: 土地改良物 | I57: 251 | J57: =OFFSET(A530,0,$K$1-1) | K57: =-SUMIF($C$7:$C$127,I57,$D$7:$D$127)+SUMIF($E$7:$E$127,I57,$F$7:$F$127) | L57: =VLOOKUP(A57,$A$140:$AX$249,$K$1,FALSE) | M57: =L57-G57 | O57: =L57-B57 | P57: =J57-K57 | Q57: =D57-F57
A58: 0 | C58: 415 | D58: =J113 | E58: 416 | F58: =J114*-1 | H58: 房屋及建築 | I58: 252 | J58: =OFFSET(A531,0,$K$1-1) | K58: =-SUMIF($C$7:$C$127,I58,$D$7:$D$127)+SUMIF($E$7:$E$127,I58,$F$7:$F$127) | M58: =L58-G58 | O58: =L58-B58 | P58: =J58-K58 | Q58: =D58-F58
A59: 0 | C59: 258 | D59: =J65*-1 | E59: 112 | H59: 機械及設備 | I59: 253 | J59: =OFFSET(A532,0,$K$1-1) | K59: =-SUMIF($C$7:$C$127,I59,$D$7:$D$127)+SUMIF($E$7:$E$127,I59,$F$7:$F$127) | M59: =L59-G59 | O59: =L59-B59 | P59: =J59-K59 | Q59: =D59-F59
A60: 0 | H60: 交通及運輸設備 | I60: 254 | J60: =OFFSET(A533,0,$K$1-1) | K60: =-SUMIF($C$7:$C$127,I60,$D$7:$D$127)+SUMIF($E$7:$E$127,I60,$F$7:$F$127) | M60: =L60-G60 | O60: =L60-B60 | P60: =J60-K60 | Q60: =D60-F60
A61: 其他資產 | B61: =SUM(B62,B65,B68) | G61: =SUM(G62,G65,G68) | H61: 什項設備 | I61: 255 | J61: =OFFSET(A534,0,$K$1-1) | K61: =-SUMIF($C$7:$C$127,I61,$D$7:$D$127)+SUMIF($E$7:$E$127,I61,$F$7:$F$127) | L61: =VLOOKUP(A61,$A$140:$AX$249,$K$1,FALSE) | M61: =L61-G61 | O61: =L61-B61 | P61: =J61-K61 | Q61: =D61-F61
A62: 遞延資產 | B62: =VLOOKUP(A62,$A$309:$AX$418,$K$1,FALSE) | E62: 112 | F62: =J26-F59 | G62: =B62+SUM(D62:D64)-SUM(F62:F64) | H62: 購建中固定資產 | I62: 256 | J62: =OFFSET(A535,0,$K$1-1) | K62: =-SUMIF($C$7:$C$127,I62,$D$7:$D$127)+SUMIF($E$7:$E$127,I62,$F$7:$F$127) | L62: =VLOOKUP(A62,$A$140:$AX$249,$K$1,FALSE) | M62: =L62-G62 | O62: =L62-B62 | P62: =J62-K62 | Q62: =D62-F62
A63: 0 | D63: =J126 | F63: =J127*-1 | H63: 租賃權益改良 | I63: 257 | J63: =OFFSET(A536,0,$K$1-1) | K63: =-SUMIF($C$7:$C$127,I63,$D$7:$D$127)+SUMIF($E$7:$E$127,I63,$F$7:$F$127) | M63: =L63-G63 | O63: =L63-B63 | P63: =J63-K63 | Q63: =D63-F63
A64: 0 | C64: 259 | D64: =J67*-1 | H64: 增加無形資產及其他資產 | J64: =OFFSET(A537,0,$K$1-1) | K64: =K65+K66 | M64: =L64-G64 | O64: =L64-B64 | P64: =J64-K64 | Q64: =D64-F64
A65: 什項資產 | B65: =VLOOKUP(A65,$A$309:$AX$418,$K$1,FALSE) | C65: 417 | D65: =F111 | E65: 108 | F65: =J22 | G65: =B65+SUM(D65:D67)-SUM(F65:F67) | H65: 增加無形資產 | I65: 258 | J65: =OFFSET(A538,0,$K$1-1) | K65: =-SUMIF($C$7:$C$127,I65,$D$7:$D$127)+SUMIF($E$7:$E$127,I65,$F$7:$F$127) | L65: =VLOOKUP(A65,$A$140:$AX$249,$K$1,FALSE) | M65: =L65-G65 | O65: =L65-B65 | P65: =J65-K65 | Q65: =D65-F65
A66: 0 | H66: 增加其他資產 | J66: =OFFSET(A539,0,$K$1-1) | K66: =K67 | M66: =L66-G66 | O66: =L66-B66 | P66: =J66-K66 | Q66: =D66-F66
A67: 0 | H67: 增加遞延費用 | I67: 259 | J67: =OFFSET(A540,0,$K$1-1) | K67: =-SUMIF($C$7:$C$127,I67,$D$7:$D$127)+SUMIF($E$7:$E$127,I67,$F$7:$F$127) | M67: =L67-G67 | O67: =L67-B67 | P67: =J67-K67 | Q67: =D67-F67
G68: =B68+D68-F68 | H68: ▼投資活動之淨現金流入（流出） | J68: =OFFSET(A541,0,$K$1-1) | K68: =K40 | P68: =J68-K68 | Q68: =D68-F68
A69: 合 計 | B69: =B7+B17+B26+B54+B56+B61 | G69: =G7+G17+G26+G54+G56+G61 | H69: ▼籌資活動之現金流量 | J69: =OFFSET(A542,0,$K$1-1) | K69: =K70+K72+K74+K81+K79+K83 | L69: =VLOOKUP(A69,$A$140:$AX$249,$K$1,FALSE) | M69: =L69-G69 | O69: =L69-B69 | P69: =J69-K69 | Q69: =D69-F69
A70: 負債 | B70: =B71+B78+B83 | G70: =G71+G78+G83 | H70: 增加短期債務、流動金融負債及其他負債 | J70: =OFFSET(A543,0,$K$1-1) | K70: =K71 | L70: =VLOOKUP(A70,$A$253:$AX$305,$K$1,FALSE) | M70: =L70-G70 | O70: =L70-B70 | P70: =J70-K70 | Q70: =D70-F70
A71: 流動負債 | B71: =SUM(B72:B77) | G71: =SUM(G72:G77) | H71: 增加其他負債 | I71: 311 | J71: =OFFSET(A544,0,$K$1-1) | K71: =-SUMIF($C$7:$C$127,I71,$D$7:$D$127)+SUMIF($E$7:$E$127,I71,$F$7:$F$127) | L71: =VLOOKUP(A71,$A$253:$AX$305,$K$1,FALSE) | M71: =L71-G71 | O71: =L71-B71 | P71: =J71-K71 | Q71: =D71-F71
A72: 短期債務 | B72: =VLOOKUP(A72,$A$423:$AX$475,$K$1,FALSE) | C72: 322 | D72: =J82*-1 | E72: 418 | F72: =D81 | G72: =B72+SUM(F72:F73)-SUM(D72:D73) | H72: 增加長期負債 | J72: =OFFSET(A545,0,$K$1-1) | K72: =K73 | L72: =VLOOKUP(A72,$A$253:$AX$305,$K$1,FALSE) | M72: =L72-G72 | O72: =L72-B72 | P72: =J72-K72 | Q72: =D72-F72
A73: 0 | C73: 316 | H73: 增加長期債務 | I73: 312 | J73: =OFFSET(A546,0,$K$1-1) | K73: =-SUMIF($C$7:$C$127,I73,$D$7:$D$127)+SUMIF($E$7:$E$127,I73,$F$7:$F$127) | M73: =L73-G73 | O73: =L73-B73 | P73: =J73-K73 | Q73: =D73-F73
A74: 應付款項 | B74: =VLOOKUP(A74,$A$423:$AX$475,$K$1,FALSE) | E74: 161 | G74: =B74+SUM(F74:F75)-SUM(D74:D75) | H74: 增加基金、公積及填補短絀 | J74: =OFFSET(A547,0,$K$1-1) | K74: =SUM(K75) | L74: =VLOOKUP(A74,$A$253:$AX$305,$K$1,FALSE) | M74: =L74-G74 | O74: =L74-B74 | P74: =J74-K74 | Q74: =D74-F74
A75: 0 | H75: 增加基金 | J75: =OFFSET(A548,0,$K$1-1) | K75: =SUM(K76:K78) | M75: =L75-G75 | O75: =L75-B75 | P75: =J75-K75 | Q75: =D75-F75
A76: 預收款項 | B76: =VLOOKUP(A76,$A$423:$AX$475,$K$1,FALSE) | E76: 161 | F76: =J34 | G76: =B76+SUM(F76:F77)-SUM(D76:D77) | H76: 國庫撥款增置固定資產 | I76: 313 | J76: =OFFSET(A549,0,$K$1-1) | K76: =-SUMIF($C$7:$C$127,I76,$D$7:$D$127)+SUMIF($E$7:$E$127,I76,$F$7:$F$127) | L76: =VLOOKUP(A76,$A$253:$AX$305,$K$1,FALSE) | M76: =L76-G76 | O76: =L76-B76 | P76: =J76-K76 | Q76: =D76-F76
A77: 0 | H77: 國庫增撥無形資產 | I77: 314 | J77: =OFFSET(A550,0,$K$1-1) | K77: =-SUMIF($C$7:$C$127,I77,$D$7:$D$127)+SUMIF($E$7:$E$127,I77,$F$7:$F$127) | M77: =L77-G77 | O77: =L77-B77 | P77: =J77-K77 | Q77: =D77-F77
A78: 長期負債 | B78: =SUM(B81) | G78: =SUM(G81) | H78: 國庫增撥遞延資產 | I78: 315 | J78: =OFFSET(A551,0,$K$1-1) | K78: =-SUMIF($C$7:$C$127,I78,$D$7:$D$127)+SUMIF($E$7:$E$127,I78,$F$7:$F$127) | L78: =VLOOKUP(A78,$A$253:$AX$305,$K$1,FALSE) | M78: =L78-G78 | O78: =L78-B78 | P78: =J78-K78 | Q78: =D78-F78
H79: 減少短期債務、流動金融負債及其他負債 | J79: =OFFSET(A552,0,$K$1-1)
H80: 減少短期債務 | I80: 316 | J80: =OFFSET(A553,0,$K$1-1) | K80: =-SUMIF($C$7:$C$127,I80,$D$7:$D$127)+SUMIF($E$7:$E$127,I80,$F$7:$F$127)
A81: 長期債務 | B81: =VLOOKUP(A81,$A$423:$AX$475,$K$1,FALSE) | C81: 418 | D81: =J116 | E81: 312 | F81: =J73 | G81: =B81+SUM(F81:F82)-SUM(D81:D82) | H81: 減少長期負債 | J81: =OFFSET(A554,0,$K$1-1) | K81: =K82 | L81: =VLOOKUP(A81,$A$253:$AX$305,$K$1,FALSE) | M81: =L81-G81 | O81: =L81-B81 | P81: =J81-K81 | Q81: =D81-F81
A82: 0 | C82: 322 | H82: 減少長期債務 | I82: 322 | J82: =OFFSET(A555,0,$K$1-1) | K82: =-SUMIF($C$7:$C$127,I82,$D$7:$D$127)+SUMIF($E$7:$E$127,I82,$F$7:$F$127) | M82: =L82-G82 | O82: =L82-B82 | P82: =J82-K82 | Q82: =D72-F82
A83: 其他負債 | B83: =SUM(B84,B90) | G83: =SUM(G84,G90) | H83: 支付利息 | J83: =OFFSET(A556,0,$K$1-1) | K83: =J83 | L83: =VLOOKUP(A83,$A$253:$AX$305,$K$1,FALSE) | M83: =L83-G83 | O83: =L83-B83 | P83: =J83-K83 | Q83: =D83-F83
A84: 什項負債 | B84: =VLOOKUP(A84,$A$423:$AX$475,$K$1,FALSE) | C84: 321 | G84: =B84+SUM(F84:F89)-SUM(D84:D89) | H84: ▼籌資活動之淨現金流入（流出） | J84: =OFFSET(A557,0,$K$1-1) | K84: =K69 | L84: =VLOOKUP(A84,$A$253:$AX$305,$K$1,FALSE) | M84: =L84-G84 | O84: =L84-B84 | P84: =J84-K84 | Q84: =D84-F84
A85: 0 | C85: 402 | D85: =J91*-1 | E85: 122 | F85: =J28 | H85: ▼現金及約當現金之淨增（淨減） | I85: B | J85: =OFFSET(A558,0,$K$1-1) | K85: =J85 | M85: =L85-G85 | O85: =L85-B85 | P85: =J85-K85 | Q85: =D85-F85
A86: 0 | E86: 401 | F86: =J90 | H86: ▼期初現金及約當現金 | J86: =OFFSET(A559,0,$K$1-1) | K86: =B8 | M86: =L86-G86 | O86: =L86-B86 | P86: =J86-K86 | Q86: =D86-F86
A87: 0 | H87: ▼期末現金及約當現金 | J87: =OFFSET(A560,0,$K$1-1) | K87: =G8 | M87: =L87-G87 | O87: =L87-B87 | P87: =J87-K87 | Q87: =D87-F87
A88: 0 | H88: ▼不影響現金流量之投資與籌資活動 | J88: =OFFSET(A561,0,$K$1-1) | M88: =L88-G88 | O88: =L88-B88 | P88: =J88-K88 | Q88: =D88-F88
A89: 0 | H89: 退休離職準備金與應付退休及離職金同額增加(+)或減少(-)之金額 | J89: =OFFSET(A562,0,$K$1-1) | K89: =K90+K91 | M89: =L89-G89 | O89: =L89-B89 | P89: =J89-K89 | Q89: =D89-F89
A90: 遞延負債 | B90: =VLOOKUP(A90,$A$423:$AX$475,$K$1,FALSE) | C90: 124 | D90: =J31*-1 | E90: 311 | F90: =J71 | G90: =B90+SUM(F90:F96)-SUM(D90:D96) | H90: 退休離職準備金與應付退休及離職金同額增加之金額(+) | I90: 401 | J90: =OFFSET(A563,0,$K$1-1) | K90: =(SUMIF($C$7:$C$127,I90,$D$7:$D$127)+SUMIF($E$7:$E$127,I90,$F$7:$F$127))/2 | L90: =VLOOKUP(A90,$A$253:$AX$305,$K$1,FALSE) | M90: =L90-G90 | O90: =L90-B90 | P90: =J90-K90 | Q90: =D90-F90
A91: 0 | C91: 123 | D91: =-J30 | E91: 403 | F91: =J93 | H91: 退休離職準備金與應付退休及離職金同額減少之金額(-) | I91: 402 | J91: =OFFSET(A564,0,$K$1-1) | K91: =(SUMIF($C$7:$C$127,I91,$D$7:$D$127)+SUMIF($E$7:$E$127,I91,$F$7:$F$127))/2*-1 | M91: =L91-G91 | O91: =L91-B91 | P91: =J91-K91 | Q91: =D91-F91
A92: 0 | E92: 407 | F92: =J101 | H92: 其他準備金與遞延收入同額增加之金額 | J92: =OFFSET(A565,0,$K$1-1) | K92: =K93 | M92: =L92-G92 | O92: =L92-B92 | P92: =J92-K92 | Q92: =D92-F92
A93: 0 | E93: 408 | F93: =J102 | H93: 其他準備金與遞延收入同額增加之金額 | I93: 403 | J93: =OFFSET(A566,0,$K$1-1) | K93: =(SUMIF($C$7:$C$127,I93,$D$7:$D$127)+SUMIF($E$7:$E$127,I93,$F$7:$F$127))/2 | M93: =L93-G93 | O93: =L93-B93 | P93: =J93-K93 | Q93: =D93-F93
E94: 410 | H94: 以前年度購建中固定資產科目，調整轉入不動產、廠房及設備科目之 | J94: =OFFSET(A567,0,$K$1-1) | K94: =K95 | P94: =J94-K94
H95: 調整轉入不動產、廠房及設備科目明細 | J95: =OFFSET(A568,0,$K$1-1) | K95: =K96+K97+K98 | O95: =L95-B96 | P95: =J95-K95 | Q95: =D96-F96
A96: 0 | H96: 土地改良物 | I96: 404 | J96: =OFFSET(A569,0,$K$1-1) | K96: =(SUMIF($C$7:$C$127,I96,$D$7:$D$127)+SUMIF($E$7:$E$127,I96,$F$7:$F$127))/2 | O96: =L97-B97 | P96: =J96-K96 | Q96: =D97-F97
A97: 淨值 | B97: =B98+B110+B116+B125 | G97: =G98+G110+G116+G125 | H97: 房屋及建築 | I97: 405 | J97: =OFFSET(A570,0,$K$1-1) | K97: =(SUMIF($C$7:$C$127,I97,$D$7:$D$127)+SUMIF($E$7:$E$127,I97,$F$7:$F$127))/2 | L97: =VLOOKUP(A97,$A$253:$AX$305,$K$1,FALSE) | M97: =L97-G97 | O97: =L98-B98 | P97: =J97-K97 | Q97: =D98-F98
A98: 基金 | B98: =SUM(B99:B101) | G98: =SUM(G99:G101) | H98: 什項設備 | I98: 406 | J98: =OFFSET(A571,0,$K$1-1) | K98: =(SUMIF($C$7:$C$127,I98,$D$7:$D$127)+SUMIF($E$7:$E$127,I98,$F$7:$F$127))/2 | L98: =VLOOKUP(A98,$A$253:$AX$305,$K$1,FALSE) | M98: =L98-G98 | O98: =L99-B99 | P98: =J98-K98 | Q98: =D99-F99
A99: 基金 | B99: =VLOOKUP(A99,$A$423:$AX$475,$K$1,FALSE) | E99: 313 | F99: =J76 | G99: =B99+SUM(F99:F109)-SUM(D99:D109) | H99: 不動產、廠房及設備與遞延收入同額增加(+)或減少(-)之金額 | J99: =OFFSET(A572,0,$K$1-1) | K99: =K100 | L99: =VLOOKUP(A99,$A$253:$AX$305,$K$1,FALSE) | M99: =L99-G99 | O99: =L100-B100 | P99: =J99-K99 | Q99: =D100-F100
A100: 0 | E100: 314 | F100: =J77 | H100: 不動產、廠房及設備與遞延收入同額增加明細(+) | J100: =OFFSET(A573,0,$K$1-1) | K100: =K101+K102 | M100: =L100-G100 | O100: =L101-B101 | P100: =J100-K100 | Q100: =D101-F101
...

Sheet 成大
A1: =OFFSET(A139,0,K1-1) | K1: =L1+2 | L1: 5
A2: 預計平衡表與現金流量表勾稽底稿
A3: 中華民國115年度
A4: 科目 | B4: 114.12.31 | C4: 調整項目 | G4: 115.12.31 | H4: 現金流量表勾稽項目
B5: 預計數 | D5: 借方 | F5: 貸方 | G5: 預計數
A6: 資產 | H6: ▼業務活動之現金流量 | L6: 114年12月 | M6: 差異數要再加(減) | O6: 比較增減 | Q6: 調整項目
A7: 流動資產 | B7: =SUM(B8:B16) | G7: =SUM(G8:G16) | H7: 本期賸餘（短絀） | I7: A | J7: =OFFSET(A480,0,$K$1-1) | K7: =-SUMIF($C$7:$C$127,I7,$D$7:$D$127)+SUMIF($E$7:$E$127,I7,$F$7:$F$127) | L7: =VLOOKUP(A7,$A$140:$AX$249,$K$1,FALSE) | M7: =L7-G7 | O7: =L7-B7 | P7: =J7-K7 | Q7: =D7-F7
A8: 現金 | B8: =VLOOKUP(A8,$A$309:$AX$418,$K$1,FALSE) | C8: B | D8: =IF(G8-B8>0,G8-B8,"0") | E8: B | F8: =IF(G8-B8<0,B8-G8,"0") | G8: =J87 | H8: 利息股利之調整 | J8: =OFFSET(A481,0,$K$1-1) | K8: =SUM(K9:K11) | L8: =VLOOKUP(A8,$A$140:$AX$249,$K$1,FALSE) | M8: =L8-G8 | O8: =L8-B8 | P8: =J8-K8 | Q8: =D8-F8
A9: 流動金融資產 | B9: =VLOOKUP(A9,$A$309:$AX$418,$K$1,FALSE) | C9: 231 | D9: =J50*-1 | E9: 211 | F9: =J42 | G9: =B9+D9-F9+D10-F10 | H9: 利息收入 | J9: =OFFSET(A482,0,$K$1-1) | K9: =J9 | L9: =VLOOKUP(A9,$A$140:$AX$249,$K$1,FALSE) | M9: =L9-G9 | O9: =L9-B9 | P9: =J9-K9 | Q9: =D9-F9
C10: 125 | H10: 股利收入 | J10: =OFFSET(A483,0,$K$1-1) | K10: =J10 | M10: =L10-G10 | O10: =L10-B10 | P10: =J10-K10 | Q10: =D10-F10
A11: 應收款項 | B11: =VLOOKUP(A11,$A$309:$AX$418,$K$1,FALSE) | C11: 151 | E11: 151 | G11: =B11+D11-F11 | H11: 利息費用 | J11: =OFFSET(A484,0,$K$1-1) | K11: =J11 | L11: =VLOOKUP(A11,$A$140:$AX$249,$K$1,FALSE) | M11: =L11-G11 | O11: =L11-B11 | P11: =J11-K11 | Q11: =D11-F11
A12: 0 | H12: 未計利息股利之本期賸餘（短絀） | J12: =OFFSET(A485,0,$K$1-1) | K12: =K7+K8 | M12: =L12-G12 | O12: =L12-B12 | P12: =J12-K12 | Q12: =D12-F12
A13: 存貨 | B13: =VLOOKUP(A13,$A$309:$AX$418,$K$1,FALSE) | C13: 151 | E13: 151 | G13: =B13+D13-F13 | H13: 調整項目 | J13: =OFFSET(A486,0,$K$1-1) | K13: =SUM(K14,K24,K27,K34,K33) | L13: =VLOOKUP(A13,$A$140:$AX$249,$K$1,FALSE) | M13: =L13-G13 | O13: =L13-B13 | P13: =J13-K13 | Q13: =D13-F13
A14: 生產性生物資產－流動 | B14: =VLOOKUP(A14,$A$309:$AX$418,$K$1,FALSE) | C14: 151 | E14: 151 | G14: =B14+D14-F14 | H14: 折舊、減損及折耗 | J14: =OFFSET(A487,0,$K$1-1) | K14: =SUM(K15:K23) | L14: =VLOOKUP(A14,$A$140:$AX$249,$K$1,FALSE) | M14: =L14-G14 | O14: =L14-B14 | P14: =J14-K14 | Q14: =D14-F14
A15: 預付款項 | B15: =VLOOKUP(A15,$A$309:$AX$418,$K$1,FALSE) | C15: 151 | E15: 151 | G15: =B15+D15-F15 | H15: 土地改良物 | I15: 101 | J15: =OFFSET(A488,0,$K$1-1) | K15: =-SUMIF($C$7:$C$127,I15,$D$7:$D$127)+SUMIF($E$7:$E$127,I15,$F$7:$F$127) | L15: =VLOOKUP(A15,$A$140:$AX$249,$K$1,FALSE) | M15: =L15-G15 | O15: =L15-B15 | P15: =J15-K15 | Q15: =D15-F15
A16: 短期貸墊款 | B16: =VLOOKUP(A16,$A$309:$AX$418,$K$1,FALSE) | C16: 151 | E16: 212 | F16: =J43 | G16: =B16+D16-F16 | H16: 房屋及建築 | I16: 102 | J16: =OFFSET(A489,0,$K$1-1) | K16: =-SUMIF($C$7:$C$127,I16,$D$7:$D$127)+SUMIF($E$7:$E$127,I16,$F$7:$F$127) | L16: =VLOOKUP(A16,$A$140:$AX$249,$K$1,FALSE) | M16: =L16-G16 | O16: =L16-B16 | P16: =J16-K16 | Q16: =D16-F16
A17: 投資、長期應收款、貸墊款及準備金 | B17: =SUM(B18:B21) | G17: =SUM(G18:G21) | H17: 機械及設備 | I17: 103 | J17: =OFFSET(A490,0,$K$1-1) | K17: =-SUMIF($C$7:$C$127,I17,$D$7:$D$127)+SUMIF($E$7:$E$127,I17,$F$7:$F$127) | L17: =VLOOKUP(A17,$A$140:$AX$249,$K$1,FALSE) | M17: =L17-G17 | O17: =L17-B17 | P17: =J17-K17 | Q17: =D17-F17
A18: 採權益法之投資 | B18: =VLOOKUP(A18,$A$309:$AX$418,$K$1,FALSE) | G18: =D18+F18+B18 | H18: 交通及運輸設備 | I18: 104 | J18: =OFFSET(A491,0,$K$1-1) | K18: =-SUMIF($C$7:$C$127,I18,$D$7:$D$127)+SUMIF($E$7:$E$127,I18,$F$7:$F$127) | L18: =VLOOKUP(A18,$A$140:$AX$249,$K$1,FALSE) | M18: =L18-G18 | O18: =L18-B18 | P18: =J18-K18 | Q18: =D18-F18
A19: 非流動金融資產 | B19: =VLOOKUP(A19,$A$309:$AX$418,$K$1,FALSE) | C19: 241 | D19: =J52*-1 | E19: 221 | F19: =J45 | G19: =B19+D19-F19 | H19: 什項設備 | I19: 105 | J19: =OFFSET(A492,0,$K$1-1) | K19: =-SUMIF($C$7:$C$127,I19,$D$7:$D$127)+SUMIF($E$7:$E$127,I19,$F$7:$F$127) | L19: =VLOOKUP(A19,$A$140:$AX$249,$K$1,FALSE) | M19: =L19-G19 | O19: =L19-B19 | P19: =J19-K19 | Q19: =D19-F19
A20: 長期應收款 | B20: =VLOOKUP(A20,$A$309:$AX$418,$K$1,FALSE) | G20: =B20+D20-F20 | H20: 租賃資產 | I20: 106 | J20: =OFFSET(A493,0,$K$1-1) | K20: =-SUMIF($C$7:$C$127,I20,$D$7:$D$127)+SUMIF($E$7:$E$127,I20,$F$7:$F$127) | L20: =VLOOKUP(A20,$A$140:$AX$249,$K$1,FALSE) | M20: =L20-G20 | O20: =L20-B20 | P20: =J20-K20 | Q20: =D20-F20
A21: 準備金 | B21: =VLOOKUP(A21,$A$309:$AX$418,$K$1,FALSE) | C21: 242 | D21: =J53*-1 | E21: 222 | F21: =J46 | G21: =B21+SUM(D21:D25)-SUM(F21:F25) | H21: 租賃權益改良 | I21: 107 | J21: =OFFSET(A494,0,$K$1-1) | K21: =-SUMIF($C$7:$C$127,I21,$D$7:$D$127)+SUMIF($E$7:$E$127,I21,$F$7:$F$127) | L21: =VLOOKUP(A21,$A$140:$AX$249,$K$1,FALSE) | M21: =L21-G21 | O21: =L21-B21 | P21: =J21-K21 | Q21: =D21-F21
A22: 0 | C22: 401 | D22: =J90 | E22: 402 | F22: =-J91 | H22: 代管資產 | I22: 108 | J22: =OFFSET(A495,0,$K$1-1) | K22: =-SUMIF($C$7:$C$127,I22,$D$7:$D$127)+SUMIF($E$7:$E$127,I22,$F$7:$F$127) | M22: =L22-G22 | O22: =L22-B22 | P22: =J22-K22 | Q22: =D22-F22
A23: 0 | C23: 403 | D23: =J93 | H23: 生產性生物資產－非流動 | I23: 109 | J23: =OFFSET(A496,0,$K$1-1) | K23: =-SUMIF($C$7:$C$127,I23,$D$7:$D$127)+SUMIF($E$7:$E$127,I23,$F$7:$F$127) | M23: =L23-G23 | O23: =L23-B23 | P23: =J23-K23 | Q23: =D23-F23
A24: 0 | H24: 攤銷 | J24: =OFFSET(A497,0,$K$1-1) | K24: =SUM(K25:K26) | M24: =L24-G24 | O24: =L24-B24 | P24: =J24-K24 | Q24: =D24-F24
C25: 125 | D25: =J32*-1 | H25: 攤銷電腦軟體 | I25: 111 | J25: =OFFSET(A498,0,$K$1-1) | K25: =-SUMIF($C$7:$C$127,I25,$D$7:$D$127)+SUMIF($E$7:$E$127,I25,$F$7:$F$127) | M25: =L25-G25 | O25: =L25-B25 | P25: =J25-K25 | Q25: =D25-F25
A26: 不動產、廠房及設備 | B26: =SUM(B27:B52) | G26: =SUM(G27:G52) | H26: 其他攤銷費用 | I26: 112 | J26: =OFFSET(A499,0,$K$1-1) | K26: =-SUMIF($C$7:$C$127,I26,$D$7:$D$127)+SUMIF($E$7:$E$127,I26,$F$7:$F$127) | L26: =VLOOKUP(A26,$A$140:$AX$249,$K$1,FALSE) | M26: =L26-G26 | O26: =L26-B26 | P26: =J26-K26 | Q26: =D26-F26
A27: 土地 | B27: =VLOOKUP(A27,$A$309:$AX$418,$K$1,FALSE) | C27: 121 | G27: =B27+SUM(D27)-SUM(F27) | H27: 其他 | J27: =OFFSET(A500,0,$K$1-1) | K27: =K28+K29+K32 | L27: =VLOOKUP(A27,$A$140:$AX$249,$K$1,FALSE) | M27: =L27-G27 | O27: =L27-B27 | P27: =J27-K27 | Q27: =D27-F27
A28: 0 | H28: 應付退休及離職金 | I28: 122 | J28: =OFFSET(A501,0,$K$1-1) | K28: =-SUMIF($C$7:$C$127,I28,$D$7:$D$127)+SUMIF($E$7:$E$127,I28,$F$7:$F$127) | M28: =L28-G28 | O28: =L28-B28 | P28: =J28-K28 | Q28: =D28-F28
A29: 土地改良物 | B29: =VLOOKUP(A29,$A$309:$AX$418,$K$1,FALSE) | C29: 251 | D29: =J57*-1 | E29: 101 | F29: =J15 | G29: =B29+SUM(D29:D32)-SUM(F29:F32) | H29: 遞延收入 | J29: =OFFSET(A502,0,$K$1-1) | K29: =SUM(K30:K31) | L29: =VLOOKUP(A29,$A$140:$AX$249,$K$1,FALSE) | M29: =L29-G29 | O29: =L29-B29 | P29: =J29-K29 | Q29: =D29-F29
A30: 0 | C30: 404 | D30: =J96 | H30: 遞延收入-其他補助收入 | I30: 123 | J30: =OFFSET(A503,0,$K$1-1) | K30: =-SUMIF($C$7:$C$127,I30,$D$7:$D$127)+SUMIF($E$7:$E$127,I30,$F$7:$F$127) | M30: =L30-G30 | O30: =L30-B30 | P30: =J30-K30 | Q30: =D30-F30
A31: 0 | H31: 遞延收入-受贈收入 | I31: 124 | J31: =OFFSET(A504,0,$K$1-1) | K31: =-SUMIF($C$7:$C$127,I31,$D$7:$D$127)+SUMIF($E$7:$E$127,I31,$F$7:$F$127) | M31: =L31-G31 | O31: =L31-B31 | P31: =J31-K31 | Q31: =D31-F31
A32: 0 | H32: 其他 | I32: 125 | J32: =OFFSET(A505,0,$K$1-1) | M32: =L32-G32 | O32: =L32-B32 | P32: =J32-K32 | Q32: =D32-F32
A33: 房屋及建築 | B33: =VLOOKUP(A33,$A$309:$AX$418,$K$1,FALSE) | C33: 252 | D33: =J58*-1 | E33: 102 | F33: =J16 | G33: =B33+SUM(D33:D36)-SUM(F33:F36) | H33: 流動資產淨減（淨增） | I33: 151 | J33: =OFFSET(A506,0,$K$1-1) | K33: =-SUMIF($C$7:$C$127,I33,$D$7:$D$127)+SUMIF($E$7:$E$127,I33,$F$7:$F$127) | L33: =VLOOKUP(A33,$A$140:$AX$249,$K$1,FALSE) | M33: =L33-G33 | O33: =L33-B33 | P33: =J33-K33 | Q33: =D33-F33
A34: 0 | C34: 405 | D34: =J97 | H34: 流動負債淨增（淨減） | I34: 161 | J34: =OFFSET(A507,0,$K$1-1) | K34: =-SUMIF($C$7:$C$127,I34,$D$7:$D$127)+SUMIF($E$7:$E$127,I34,$F$7:$F$127) | M34: =L34-G34 | O34: =L34-B34 | P34: =J34-K34 | Q34: =D34-F34
A35: 0 | H35: 未計利息股利之現金流入（流出） | J35: =OFFSET(A508,0,$K$1-1) | K35: =K12+K13 | M35: =L35-G35 | O35: =L35-B35 | P35: =J35-K35 | Q35: =D35-F35
A36: 0 | H36: 收取利息 | J36: =OFFSET(A509,0,$K$1-1) | K36: =J36 | M36: =L36-G36 | O36: =L36-B36 | P36: =J36-K36 | Q36: =D36-F36
A37: 機械及設備 | B37: =VLOOKUP(A37,$A$309:$AX$418,$K$1,FALSE) | C37: 253 | D37: =J59*-1 | E37: 103 | F37: =J17 | G37: =B37+SUM(D37:D41)-SUM(F37:F41) | H37: 收取股利 | J37: =OFFSET(A510,0,$K$1-1) | K37: =J37 | L37: =VLOOKUP(A37,$A$140:$AX$249,$K$1,FALSE) | M37: =L37-G37 | O37: =L37-B37 | P37: =J37-K37 | Q37: =D37-F37
A38: 0 | C38: 407 | D38: =J101 | H38: 支付利息 | J38: =OFFSET(A511,0,$K$1-1) | K38: =J38 | M38: =L38-G38 | O38: =L38-B38 | P38: =J38-K38 | Q38: =D38-F38
A39: 0 | C39: 409 | D39: =J105 | E39: 412 | F39: =-J109 | H39: ▼業務活動之淨現金流入（流出） | J39: =OFFSET(A512,0,$K$1-1) | K39: =K36+K37+K38+K35 | M39: =L39-G39 | O39: =L39-B39 | P39: =J39-K39 | Q39: =D39-F39
A40: 0 | H40: ▼投資活動之現金流量 | J40: =OFFSET(A513,0,$K$1-1) | K40: =SUM(K41,K44,K47,K48,K49,K51,K54,K64) | M40: =L40-G40 | O40: =L40-B40 | P40: =J40-K40 | Q40: =D40-F40
H41: 減少流動金融資產及短期貸墊款 | J41: =OFFSET(A514,0,$K$1-1) | K41: =K42+K43 | M41: =L41-G41 | O41: =L41-B41 | P41: =J41-K41 | Q41: =D41-F41
A42: 交通及運輸設備 | B42: =VLOOKUP(A42,$A$309:$AX$418,$K$1,FALSE) | C42: 254 | D42: =J60*-1 | E42: 104 | F42: =J18 | G42: =B42+SUM(D42:D44)-SUM(F42:F44) | H42: 減少流動金融資產 | I42: 211 | J42: =OFFSET(A515,0,$K$1-1) | K42: =-SUMIF($C$7:$C$127,I42,$D$7:$D$127)+SUMIF($E$7:$E$135,I42,$F$7:$F$127) | L42: =VLOOKUP(A42,$A$140:$AX$249,$K$1,FALSE) | M42: =L42-G42 | O42: =L42-B42 | P42: =J42-K42 | Q42: =D42-F42
C43: 410 | D43: =J106 | E43: 413 | F43: =J110*-1 | H43: 減少短期墊款 | I43: 212 | J43: =OFFSET(A516,0,$K$1-1) | K43: =-SUMIF($C$7:$C$127,I43,$D$7:$D$127)+SUMIF($E$7:$E$135,I43,$F$7:$F$127) | M43: =L43-G43 | O43: =L43-B43 | P43: =J43-K43 | Q43: =D43-F43
H44: 減少投資、長期應收款、貸墊款及準備金 | J44: =OFFSET(A517,0,$K$1-1) | K44: =SUM(K45:K46) | M44: =L44-G44 | O44: =L44-B44 | P44: =J44-K44 | Q44: =D44-F44
A45: 什項設備 | B45: =VLOOKUP(A45,$A$309:$AX$418,$K$1,FALSE) | C45: 255 | D45: =J61*-1 | E45: 105 | F45: =J19 | G45: =B45+SUM(D45:D48)-SUM(F45:F48) | H45: 減少投資 | I45: 221 | J45: =OFFSET(A518,0,$K$1-1) | K45: =-SUMIF($C$7:$C$127,I45,$D$7:$D$127)+SUMIF($E$7:$E$135,I45,$F$7:$F$127) | L45: =VLOOKUP(A45,$A$140:$AX$249,$K$1,FALSE) | M45: =L45-G45 | O45: =L45-B45 | P45: =J45-K45 | Q45: =D45-F45
A46: 0 | C46: 408 | D46: =J102 | H46: 減少準備金 | I46: 222 | J46: =OFFSET(A519,0,$K$1-1) | K46: =-SUMIF($C$7:$C$127,I46,$D$7:$D$127)+SUMIF($E$7:$E$135,I46,$F$7:$F$127) | M46: =L46-G46 | O46: =L46-B46 | P46: =J46-K46 | Q46: =D46-F46
A47: 0 | C47: 411 | D47: =J107 | E47: 414 | F47: =-J111 | H47: 收取利息 | J47: =OFFSET(A520,0,$K$1-1) | K47: =J47 | M47: =L47-G47 | O47: =L47-B47 | P47: =J47-K47 | Q47: =D47-F47
A48: 0 | C48: 406 | D48: =J98 | H48: 收取股利 | J48: =OFFSET(A521,0,$K$1-1) | K48: =J48 | M48: =L48-G48 | O48: =L48-B48 | P48: =J48-K48 | Q48: =D48-F48
A49: 租賃資產 | B49: =VLOOKUP(A49,$A$309:$AX$413,$K$1,FALSE) | E49: 106 | F49: =J20 | G49: =B49+D49-F49 | H49: 增加流動金融資產及短期貸墊款 | J49: =OFFSET(A522,0,$K$1-1) | K49: =K50 | L49: =VLOOKUP(A49,$A$140:$AX$249,$K$1,FALSE) | M49: =L49-G49 | O49: =L49-B49 | P49: =J49-K49 | Q49: =D49-F49
A50: 租賃權益改良 | B50: =VLOOKUP(A50,$A$309:$AX$418,$K$1,FALSE) | C50: 257 | D50: =J63*-1 | E50: 107 | F50: =J21 | G50: =B50+D50-F50 | H50: 增加流動金融資產 | I50: 231 | J50: =OFFSET(A523,0,$K$1-1) | K50: =-SUMIF($C$7:$C$127,I50,$D$7:$D$127)+SUMIF($E$7:$E$135,I50,$F$7:$F$127) | L50: =VLOOKUP(A50,$A$140:$AX$249,$K$1,FALSE) | M50: =L50-G50 | O50: =L50-B49 | P50: =J50-K50 | Q50: =D49-F49
A51: 購建中固定資產 | B51: =VLOOKUP(A51,$A$309:$AX$418,$K$1,FALSE) | C51: 256 | D51: =J62*-1 | E51: 404 | F51: =J96 | G51: =B51+SUM(D51:D53)-SUM(F51:F53) | H51: 增加投資、長期應收款、貸墊款及準備金 | J51: =OFFSET(A524,0,$K$1-1) | K51: =SUM(K52:K53) | L51: =VLOOKUP(A51,$A$140:$AX$249,$K$1,FALSE) | M51: =L51-G51 | O51: =L51-B50 | P51: =J51-K51 | Q51: =D50-F50
E52: 405 | F52: =J97 | H52: 增加投資 | I52: 241 | J52: =OFFSET(A525,0,$K$1-1) | K52: =-SUMIF($C$7:$C$127,I52,$D$7:$D$127)+SUMIF($E$7:$E$135,I52,$F$7:$F$127) | M52: =L52-G52 | O52: =L52-B51 | P52: =J52-K52 | Q52: =D51-F51
E53: 406 | F53: =J98 | H53: 增加準備金 | I53: 242 | J53: =OFFSET(A526,0,$K$1-1) | K53: =-SUMIF($C$7:$C$127,I53,$D$7:$D$127)+SUMIF($E$7:$E$135,I53,$F$7:$F$127) | M53: =L53-G52 | O53: =L53-B52 | P53: =J53-K53 | Q53: =D52-F52
A54: 生物資產－非流動 | B54: =SUM(B55) | G54: =SUM(G55) | H54: 增加不動產、廠房及設備、礦產資源 | J54: =OFFSET(A527,0,$K$1-1) | K54: =K55 | L54: =VLOOKUP(A54,$A$140:$AX$249,$K$1,FALSE) | M54: =L54-G54 | O54: =L54-B54 | P54: =J54-K54 | Q54: =D54-F54
A55: 生產性生物資產－非流動 | B55: =VLOOKUP(A55,$A$309:$AX$418,$K$1,FALSE) | E55: 109 | F55: =J23 | G55: =B55+SUM(D55:D55)-SUM(F55:F55) | H55: 增加不動產、廠房及設備 | J55: =OFFSET(A528,0,$K$1-1) | K55: =K56 | L55: =VLOOKUP(A55,$A$140:$AX$249,$K$1,FALSE) | M55: =L55-G55 | O55: =L55-B55 | P55: =J55-K55 | Q55: =D55-F55
A56: 無形資產 | B56: =SUM(B57) | G56: =SUM(G57) | H56: 固定資產之增置 | J56: =OFFSET(A529,0,$K$1-1) | K56: =SUM(K57:K63) | L56: =VLOOKUP(A56,$A$140:$AX$249,$K$1,FALSE) | M56: =L56-G56 | O56: =L56-B56 | P56: =J56-K56 | Q56: =D56-F56
A57: 無形資產 | B57: =VLOOKUP(A57,$A$309:$AX$418,$K$1,FALSE) | E57: 111 | F57: =J25 | G57: =B57+SUM(D57:D59)-SUM(F57:F59) | H57: 土地改良物 | I57: 251 | J57: =OFFSET(A530,0,$K$1-1) | K57: =-SUMIF($C$7:$C$127,I57,$D$7:$D$127)+SUMIF($E$7:$E$127,I57,$F$7:$F$127) | L57: =VLOOKUP(A57,$A$140:$AX$249,$K$1,FALSE) | M57: =L57-G57 | O57: =L57-B57 | P57: =J57-K57 | Q57: =D57-F57
A58: 0 | C58: 415 | D58: =J113 | E58: 416 | F58: =J114*-1 | H58: 房屋及建築 | I58: 252 | J58: =OFFSET(A531,0,$K$1-1) | K58: =-SUMIF($C$7:$C$127,I58,$D$7:$D$127)+SUMIF($E$7:$E$127,I58,$F$7:$F$127) | M58: =L58-G58 | O58: =L58-B58 | P58: =J58-K58 | Q58: =D58-F58
A59: 0 | C59: 258 | D59: =J65*-1 | E59: 112 | H59: 機械及設備 | I59: 253 | J59: =OFFSET(A532,0,$K$1-1) | K59: =-SUMIF($C$7:$C$127,I59,$D$7:$D$127)+SUMIF($E$7:$E$127,I59,$F$7:$F$127) | M59: =L59-G59 | O59: =L59-B59 | P59: =J59-K59 | Q59: =D59-F59
A60: 0 | H60: 交通及運輸設備 | I60: 254 | J60: =OFFSET(A533,0,$K$1-1) | K60: =-SUMIF($C$7:$C$127,I60,$D$7:$D$127)+SUMIF($E$7:$E$127,I60,$F$7:$F$127) | M60: =L60-G60 | O60: =L60-B60 | P60: =J60-K60 | Q60: =D60-F60
A61: 其他資產 | B61: =SUM(B62,B65,B68) | G61: =SUM(G62,G65,G68) | H61: 什項設備 | I61: 255 | J61: =OFFSET(A534,0,$K$1-1) | K61: =-SUMIF($C$7:$C$127,I61,$D$7:$D$127)+SUMIF($E$7:$E$127,I61,$F$7:$F$127) | L61: =VLOOKUP(A61,$A$140:$AX$249,$K$1,FALSE) | M61: =L61-G61 | O61: =L61-B61 | P61: =J61-K61 | Q61: =D61-F61
A62: 遞延資產 | B62: =VLOOKUP(A62,$A$309:$AX$418,$K$1,FALSE) | E62: 112 | F62: =J26-F59 | G62: =B62+SUM(D62:D64)-SUM(F62:F64) | H62: 購建中固定資產 | I62: 256 | J62: =OFFSET(A535,0,$K$1-1) | K62: =-SUMIF($C$7:$C$127,I62,$D$7:$D$127)+SUMIF($E$7:$E$127,I62,$F$7:$F$127) | L62: =VLOOKUP(A62,$A$140:$AX$249,$K$1,FALSE) | M62: =L62-G62 | O62: =L62-B62 | P62: =J62-K62 | Q62: =D62-F62
A63: 0 | D63: =J126 | F63: =J127*-1 | H63: 租賃權益改良 | I63: 257 | J63: =OFFSET(A536,0,$K$1-1) | K63: =-SUMIF($C$7:$C$127,I63,$D$7:$D$127)+SUMIF($E$7:$E$127,I63,$F$7:$F$127) | M63: =L63-G63 | O63: =L63-B63 | P63: =J63-K63 | Q63: =D63-F63
A64: 0 | C64: 259 | D64: =J67*-1 | H64: 增加無形資產及其他資產 | J64: =OFFSET(A537,0,$K$1-1) | K64: =K65+K66 | M64: =L64-G64 | O64: =L64-B64 | P64: =J64-K64 | Q64: =D64-F64
A65: 什項資產 | B65: =VLOOKUP(A65,$A$309:$AX$418,$K$1,FALSE) | C65: 417 | D65: =F111 | E65: 108 | F65: =J22 | G65: =B65+SUM(D65:D67)-SUM(F65:F67) | H65: 增加無形資產 | I65: 258 | J65: =OFFSET(A538,0,$K$1-1) | K65: =-SUMIF($C$7:$C$127,I65,$D$7:$D$127)+SUMIF($E$7:$E$127,I65,$F$7:$F$127) | L65: =VLOOKUP(A65,$A$140:$AX$249,$K$1,FALSE) | M65: =L65-G65 | O65: =L65-B65 | P65: =J65-K65 | Q65: =D65-F65
A66: 0 | H66: 增加其他資產 | J66: =OFFSET(A539,0,$K$1-1) | K66: =K67 | M66: =L66-G66 | O66: =L66-B66 | P66: =J66-K66 | Q66: =D66-F66
A67: 0 | H67: 增加遞延費用 | I67: 259 | J67: =OFFSET(A540,0,$K$1-1) | K67: =-SUMIF($C$7:$C$127,I67,$D$7:$D$127)+SUMIF($E$7:$E$127,I67,$F$7:$F$127) | M67: =L67-G67 | O67: =L67-B67 | P67: =J67-K67 | Q67: =D67-F67
G68: =B68+D68-F68 | H68: ▼投資活動之淨現金流入（流出） | J68: =OFFSET(A541,0,$K$1-1) | K68: =K40 | P68: =J68-K68 | Q68: =D68-F68
A69: 合 計 | B69: =B7+B17+B26+B54+B56+B61 | G69: =G7+G17+G26+G54+G56+G61 | H69: ▼籌資活動之現金流量 | J69: =OFFSET(A542,0,$K$1-1) | K69: =K70+K72+K74+K81+K79+K83 | L69: =VLOOKUP(A69,$A$140:$AX$249,$K$1,FALSE) | M69: =L69-G69 | O69: =L69-B69 | P69: =J69-K69 | Q69: =D69-F69
A70: 負債 | B70: =B71+B78+B83 | G70: =G71+G78+G83 | H70: 增加短期債務、流動金融負債及其他負債 | J70: =OFFSET(A543,0,$K$1-1) | K70: =K71 | L70: =VLOOKUP(A70,$A$253:$AX$305,$K$1,FALSE) | M70: =L70-G70 | O70: =L70-B70 | P70: =J70-K70 | Q70: =D70-F70
A71: 流動負債 | B71: =SUM(B72:B77) | G71: =SUM(G72:G77) | H71: 增加其他負債 | I71: 311 | J71: =OFFSET(A544,0,$K$1-1) | K71: =-SUMIF($C$7:$C$127,I71,$D$7:$D$127)+SUMIF($E$7:$E$127,I71,$F$7:$F$127) | L71: =VLOOKUP(A71,$A$253:$AX$305,$K$1,FALSE) | M71: =L71-G71 | O71: =L71-B71 | P71: =J71-K71 | Q71: =D71-F71
A72: 短期債務 | B72: =VLOOKUP(A72,$A$423:$AX$475,$K$1,FALSE) | C72: 322 | D72: =J82*-1 | E72: 418 | F72: =D81 | G72: =B72+SUM(F72:F73)-SUM(D72:D73) | H72: 增加長期負債 | J72: =OFFSET(A545,0,$K$1-1) | K72: =K73 | L72: =VLOOKUP(A72,$A$253:$AX$305,$K$1,FALSE) | M72: =L72-G72 | O72: =L72-B72 | P72: =J72-K72 | Q72: =D72-F72
A73: 0 | C73: 316 | H73: 增加長期債務 | I73: 312 | J73: =OFFSET(A546,0,$K$1-1) | K73: =-SUMIF($C$7:$C$127,I73,$D$7:$D$127)+SUMIF($E$7:$E$127,I73,$F$7:$F$127) | M73: =L73-G73 | O73: =L73-B73 | P73: =J73-K73 | Q73: =D73-F73
A74: 應付款項 | B74: =VLOOKUP(A74,$A$423:$AX$475,$K$1,FALSE) | E74: 161 | G74: =B74+SUM(F74:F75)-SUM(D74:D75) | H74: 增加基金、公積及填補短絀 | J74: =OFFSET(A547,0,$K$1-1) | K74: =SUM(K75) | L74: =VLOOKUP(A74,$A$253:$AX$305,$K$1,FALSE) | M74: =L74-G74 | O74: =L74-B74 | P74: =J74-K74 | Q74: =D74-F74
A75: 0 | H75: 增加基金 | J75: =OFFSET(A548,0,$K$1-1) | K75: =SUM(K76:K78) | M75: =L75-G75 | O75: =L75-B75 | P75: =J75-K75 | Q75: =D75-F75
A76: 預收款項 | B76: =VLOOKUP(A76,$A$423:$AX$475,$K$1,FALSE) | E76: 161 | F76: =J34 | G76: =B76+SUM(F76:F77)-SUM(D76:D77) | H76: 國庫撥款增置固定資產 | I76: 313 | J76: =OFFSET(A549,0,$K$1-1) | K76: =-SUMIF($C$7:$C$127,I76,$D$7:$D$127)+SUMIF($E$7:$E$127,I76,$F$7:$F$127) | L76: =VLOOKUP(A76,$A$253:$AX$305,$K$1,FALSE) | M76: =L76-G76 | O76: =L76-B76 | P76: =J76-K76 | Q76: =D76-F76
A77: 0 | H77: 國庫增撥無形資產 | I77: 314 | J77: =OFFSET(A550,0,$K$1-1) | K77: =-SUMIF($C$7:$C$127,I77,$D$7:$D$127)+SUMIF($E$7:$E$127,I77,$F$7:$F$127) | M77: =L77-G77 | O77: =L77-B77 | P77: =J77-K77 | Q77: =D77-F77
A78: 長期負債 | B78: =SUM(B81) | G78: =SUM(G81) | H78: 國庫增撥遞延資產 | I78: 315 | J78: =OFFSET(A551,0,$K$1-1) | K78: =-SUMIF($C$7:$C$127,I78,$D$7:$D$127)+SUMIF($E$7:$E$127,I78,$F$7:$F$127) | L78: =VLOOKUP(A78,$A$253:$AX$305,$K$1,FALSE) | M78: =L78-G78 | O78: =L78-B78 | P78: =J78-K78 | Q78: =D78-F78
H79: 減少短期債務、流動金融負債及其他負債 | J79: =OFFSET(A552,0,$K$1-1)
H80: 減少短期債務 | I80: 316 | J80: =OFFSET(A553,0,$K$1-1) | K80: =-SUMIF($C$7:$C$127,I80,$D$7:$D$127)+SUMIF($E$7:$E$127,I80,$F$7:$F$127)
A81: 長期債務 | B81: =VLOOKUP(A81,$A$423:$AX$475,$K$1,FALSE) | C81: 418 | D81: =J116 | E81: 312 | F81: =J73 | G81: =B81+SUM(F81:F82)-SUM(D81:D82) | H81: 減少長期負債 | J81: =OFFSET(A554,0,$K$1-1) | K81: =K82 | L81: =VLOOKUP(A81,$A$253:$AX$305,$K$1,FALSE) | M81: =L81-G81 | O81: =L81-B81 | P81: =J81-K81 | Q81: =D81-F81
A82: 0 | C82: 322 | H82: 減少長期債務 | I82: 322 | J82: =OFFSET(A555,0,$K$1-1) | K82: =-SUMIF($C$7:$C$127,I82,$D$7:$D$127)+SUMIF($E$7:$E$127,I82,$F$7:$F$127) | M82: =L82-G82 | O82: =L82-B82 | P82: =J82-K82 | Q82: =D72-F82
A83: 其他負債 | B83: =SUM(B84,B90) | G83: =SUM(G84,G90) | H83: 支付利息 | J83: =OFFSET(A556,0,$K$1-1) | K83: =J83 | L83: =VLOOKUP(A83,$A$253:$AX$305,$K$1,FALSE) | M83: =L83-G83 | O83: =L83-B83 | P83: =J83-K83 | Q83: =D83-F83
A84: 什項負債 | B84: =VLOOKUP(A84,$A$423:$AX$475,$K$1,FALSE) | C84: 321 | G84: =B84+SUM(F84:F89)-SUM(D84:D89) | H84: ▼籌資活動之淨現金流入（流出） | J84: =OFFSET(A557,0,$K$1-1) | K84: =K69 | L84: =VLOOKUP(A84,$A$253:$AX$305,$K$1,FALSE) | M84: =L84-G84 | O84: =L84-B84 | P84: =J84-K84 | Q84: =D84-F84
A85: 0 | C85: 402 | D85: =J91*-1 | E85: 122 | F85: =J28 | H85: ▼現金及約當現金之淨增（淨減） | I85: B | J85: =OFFSET(A558,0,$K$1-1) | K85: =J85 | M85: =L85-G85 | O85: =L85-B85 | P85: =J85-K85 | Q85: =D85-F85
A86: 0 | E86: 401 | F86: =J90 | H86: ▼期初現金及約當現金 | J86: =OFFSET(A559,0,$K$1-1) | K86: =B8 | M86: =L86-G86 | O86: =L86-B86 | P86: =J86-K86 | Q86: =D86-F86
A87: 0 | H87: ▼期末現金及約當現金 | J87: =OFFSET(A560,0,$K$1-1) | K87: =G8 | M87: =L87-G87 | O87: =L87-B87 | P87: =J87-K87 | Q87: =D87-F87
A88: 0 | H88: ▼不影響現金流量之投資與籌資活動 | J88: =OFFSET(A561,0,$K$1-1) | M88: =L88-G88 | O88: =L88-B88 | P88: =J88-K88 | Q88: =D88-F88
A89: 0 | H89: 退休離職準備金與應付退休及離職金同額增加(+)或減少(-)之金額 | J89: =OFFSET(A562,0,$K$1-1) | K89: =K90+K91 | M89: =L89-G89 | O89: =L89-B89 | P89: =J89-K89 | Q89: =D89-F89
A90: 遞延負債 | B90: =VLOOKUP(A90,$A$423:$AX$475,$K$1,FALSE) | C90: 124 | D90: =J31*-1 | E90: 311 | F90: =J71 | G90: =B90+SUM(F90:F96)-SUM(D90:D96) | H90: 退休離職準備金與應付退休及離職金同額增加之金額(+) | I90: 401 | J90: =OFFSET(A563,0,$K$1-1) | K90: =(SUMIF($C$7:$C$127,I90,$D$7:$D$127)+SUMIF($E$7:$E$127,I90,$F$7:$F$127))/2 | L90: =VLOOKUP(A90,$A$253:$AX$305,$K$1,FALSE) | M90: =L90-G90 | O90: =L90-B90 | P90: =J90-K90 | Q90: =D90-F90
A91: 0 | C91: 123 | D91: =-J30 | E91: 403 | F91: =J93 | H91: 退休離職準備金與應付退休及離職金同額減少之金額(-) | I91: 402 | J91: =OFFSET(A564,0,$K$1-1) | K91: =(SUMIF($C$7:$C$127,I91,$D$7:$D$127)+SUMIF($E$7:$E$127,I91,$F$7:$F$127))/2*-1 | M91: =L91-G91 | O91: =L91-B91 | P91: =J91-K91 | Q91: =D91-F91
A92: 0 | E92: 407 | F92: =J101 | H92: 其他準備金與遞延收入同額增加之金額 | J92: =OFFSET(A565,0,$K$1-1) | K92: =K93 | M92: =L92-G92 | O92: =L92-B92 | P92: =J92-K92 | Q92: =D92-F92
A93: 0 | E93: 408 | F93: =J102 | H93: 其他準備金與遞延收入同額增加之金額 | I93: 403 | J93: =OFFSET(A566,0,$K$1-1) | K93: =(SUMIF($C$7:$C$127,I93,$D$7:$D$127)+SUMIF($E$7:$E$127,I93,$F$7:$F$127))/2 | M93: =L93-G93 | O93: =L93-B93 | P93: =J93-K93 | Q93: =D93-F93
E94: 410 | H94: 以前年度購建中固定資產科目，調整轉入不動產、廠房及設備科目之 | J94: =OFFSET(A567,0,$K$1-1) | K94: =K95 | P94: =J94-K94
H95: 調整轉入不動產、廠房及設備科目明細 | J95: =OFFSET(A568,0,$K$1-1) | K95: =K96+K97+K98 | O95: =L95-B96 | P95: =J95-K95 | Q95: =D96-F96
A96: 0 | H96: 土地改良物 | I96: 404 | J96: =OFFSET(A569,0,$K$1-1) | K96: =(SUMIF($C$7:$C$127,I96,$D$7:$D$127)+SUMIF($E$7:$E$127,I96,$F$7:$F$127))/2 | O96: =L97-B97 | P96: =J96-K96 | Q96: =D97-F97
A97: 淨值 | B97: =B98+B110+B116+B125 | G97: =G98+G110+G116+G125 | H97: 房屋及建築 | I97: 405 | J97: =OFFSET(A570,0,$K$1-1) | K97: =(SUMIF($C$7:$C$127,I97,$D$7:$D$127)+SUMIF($E$7:$E$127,I97,$F$7:$F$127))/2 | L97: =VLOOKUP(A97,$A$253:$AX$305,$K$1,FALSE) | M97: =L97-G97 | O97: =L98-B98 | P97: =J97-K97 | Q97: =D98-F98
A98: 基金 | B98: =SUM(B99:B101) | G98: =SUM(G99:G101) | H98: 什項設備 | I98: 406 | J98: =OFFSET(A571,0,$K$1-1) | K98: =(SUMIF($C$7:$C$127,I98,$D$7:$D$127)+SUMIF($E$7:$E$127,I98,$F$7:$F$127))/2 | L98: =VLOOKUP(A98,$A$253:$AX$305,$K$1,FALSE) | M98: =L98-G98 | O98: =L99-B99 | P98: =J98-K98 | Q98: =D99-F99
A99: 基金 | B99: =VLOOKUP(A99,$A$423:$AX$475,$K$1,FALSE) | E99: 313 | F99: =J76 | G99: =B99+SUM(F99:F109)-SUM(D99:D109) | H99: 不動產、廠房及設備與遞延收入同額增加(+)或減少(-)之金額 | J99: =OFFSET(A572,0,$K$1-1) | K99: =K100 | L99: =VLOOKUP(A99,$A$253:$AX$305,$K$1,FALSE) | M99: =L99-G99 | O99: =L100-B100 | P99: =J99-K99 | Q99: =D100-F100
A100: 0 | E100: 314 | F100: =J77 | H100: 不動產、廠房及設備與遞延收入同額增加明細(+) | J100: =OFFSET(A573,0,$K$1-1) | K100: =K101+K102 | M100: =L100-G100 | O100: =L101-B101 | P100: =J100-K100 | Q100: =D101-F101
...

Sheet 中央
A1: =OFFSET(A139,0,K1-1) | K1: =L1+2 | L1: 6
A2: 預計平衡表與現金流量表勾稽底稿
A3: 中華民國115年度
A4: 科目 | B4: 114.12.31 | C4: 調整項目 | G4: 115.12.31 | H4: 現金流量表勾稽項目
B5: 預計數 | D5: 借方 | F5: 貸方 | G5: 預計數
A6: 資產 | H6: ▼業務活動之現金流量 | L6: 114年12月 | M6: 差異數要再加(減) | O6: 比較增減 | Q6: 調整項目
A7: 流動資產 | B7: =SUM(B8:B16) | G7: =SUM(G8:G16) | H7: 本期賸餘（短絀） | I7: A | J7: =OFFSET(A480,0,$K$1-1) | K7: =-SUMIF($C$7:$C$127,I7,$D$7:$D$127)+SUMIF($E$7:$E$127,I7,$F$7:$F$127) | L7: =VLOOKUP(A7,$A$140:$AX$249,$K$1,FALSE) | M7: =L7-G7 | O7: =L7-B7 | P7: =J7-K7 | Q7: =D7-F7
A8: 現金 | B8: =VLOOKUP(A8,$A$309:$AX$418,$K$1,FALSE) | C8: B | D8: =IF(G8-B8>0,G8-B8,"0") | E8: B | F8: =IF(G8-B8<0,B8-G8,"0") | G8: =J87 | H8: 利息股利之調整 | J8: =OFFSET(A481,0,$K$1-1) | K8: =SUM(K9:K11) | L8: =VLOOKUP(A8,$A$140:$AX$249,$K$1,FALSE) | M8: =L8-G8 | O8: =L8-B8 | P8: =J8-K8 | Q8: =D8-F8
A9: 流動金融資產 | B9: =VLOOKUP(A9,$A$309:$AX$418,$K$1,FALSE) | C9: 231 | D9: =J50*-1 | E9: 211 | F9: =J42 | G9: =B9+D9-F9+D10-F10 | H9: 利息收入 | J9: =OFFSET(A482,0,$K$1-1) | K9: =J9 | L9: =VLOOKUP(A9,$A$140:$AX$249,$K$1,FALSE) | M9: =L9-G9 | O9: =L9-B9 | P9: =J9-K9 | Q9: =D9-F9
C10: 125 | H10: 股利收入 | J10: =OFFSET(A483,0,$K$1-1) | K10: =J10 | M10: =L10-G10 | O10: =L10-B10 | P10: =J10-K10 | Q10: =D10-F10
A11: 應收款項 | B11: =VLOOKUP(A11,$A$309:$AX$418,$K$1,FALSE) | C11: 151 | E11: 151 | G11: =B11+D11-F11 | H11: 利息費用 | J11: =OFFSET(A484,0,$K$1-1) | K11: =J11 | L11: =VLOOKUP(A11,$A$140:$AX$249,$K$1,FALSE) | M11: =L11-G11 | O11: =L11-B11 | P11: =J11-K11 | Q11: =D11-F11
A12: 0 | H12: 未計利息股利之本期賸餘（短絀） | J12: =OFFSET(A485,0,$K$1-1) | K12: =K7+K8 | M12: =L12-G12 | O12: =L12-B12 | P12: =J12-K12 | Q12: =D12-F12
A13: 存貨 | B13: =VLOOKUP(A13,$A$309:$AX$418,$K$1,FALSE) | C13: 151 | E13: 151 | G13: =B13+D13-F13 | H13: 調整項目 | J13: =OFFSET(A486,0,$K$1-1) | K13: =SUM(K14,K24,K27,K34,K33) | L13: =VLOOKUP(A13,$A$140:$AX$249,$K$1,FALSE) | M13: =L13-G13 | O13: =L13-B13 | P13: =J13-K13 | Q13: =D13-F13
A14: 生產性生物資產－流動 | B14: =VLOOKUP(A14,$A$309:$AX$418,$K$1,FALSE) | C14: 151 | E14: 151 | G14: =B14+D14-F14 | H14: 折舊、減損及折耗 | J14: =OFFSET(A487,0,$K$1-1) | K14: =SUM(K15:K23) | L14: =VLOOKUP(A14,$A$140:$AX$249,$K$1,FALSE) | M14: =L14-G14 | O14: =L14-B14 | P14: =J14-K14 | Q14: =D14-F14
A15: 預付款項 | B15: =VLOOKUP(A15,$A$309:$AX$418,$K$1,FALSE) | C15: 151 | E15: 151 | G15: =B15+D15-F15 | H15: 土地改良物 | I15: 101 | J15: =OFFSET(A488,0,$K$1-1) | K15: =-SUMIF($C$7:$C$127,I15,$D$7:$D$127)+SUMIF($E$7:$E$127,I15,$F$7:$F$127) | L15: =VLOOKUP(A15,$A$140:$AX$249,$K$1,FALSE) | M15: =L15-G15 | O15: =L15-B15 | P15: =J15-K15 | Q15: =D15-F15
A16: 短期貸墊款 | B16: =VLOOKUP(A16,$A$309:$AX$418,$K$1,FALSE) | C16: 151 | E16: 212 | F16: =J43 | G16: =B16+D16-F16 | H16: 房屋及建築 | I16: 102 | J16: =OFFSET(A489,0,$K$1-1) | K16: =-SUMIF($C$7:$C$127,I16,$D$7:$D$127)+SUMIF($E$7:$E$127,I16,$F$7:$F$127) | L16: =VLOOKUP(A16,$A$140:$AX$249,$K$1,FALSE) | M16: =L16-G16 | O16: =L16-B16 | P16: =J16-K16 | Q16: =D16-F16
A17: 投資、長期應收款、貸墊款及準備金 | B17: =SUM(B18:B21) | G17: =SUM(G18:G21) | H17: 機械及設備 | I17: 103 | J17: =OFFSET(A490,0,$K$1-1) | K17: =-SUMIF($C$7:$C$127,I17,$D$7:$D$127)+SUMIF($E$7:$E$127,I17,$F$7:$F$127) | L17: =VLOOKUP(A17,$A$140:$AX$249,$K$1,FALSE) | M17: =L17-G17 | O17: =L17-B17 | P17: =J17-K17 | Q17: =D17-F17
A18: 採權益法之投資 | B18: =VLOOKUP(A18,$A$309:$AX$418,$K$1,FALSE) | G18: =D18+F18+B18 | H18: 交通及運輸設備 | I18: 104 | J18: =OFFSET(A491,0,$K$1-1) | K18: =-SUMIF($C$7:$C$127,I18,$D$7:$D$127)+SUMIF($E$7:$E$127,I18,$F$7:$F$127) | L18: =VLOOKUP(A18,$A$140:$AX$249,$K$1,FALSE) | M18: =L18-G18 | O18: =L18-B18 | P18: =J18-K18 | Q18: =D18-F18
A19: 非流動金融資產 | B19: =VLOOKUP(A19,$A$309:$AX$418,$K$1,FALSE) | C19: 241 | D19: =J52*-1 | E19: 221 | F19: =J45 | G19: =B19+D19-F19 | H19: 什項設備 | I19: 105 | J19: =OFFSET(A492,0,$K$1-1) | K19: =-SUMIF($C$7:$C$127,I19,$D$7:$D$127)+SUMIF($E$7:$E$127,I19,$F$7:$F$127) | L19: =VLOOKUP(A19,$A$140:$AX$249,$K$1,FALSE) | M19: =L19-G19 | O19: =L19-B19 | P19: =J19-K19 | Q19: =D19-F19
A20: 長期應收款 | B20: =VLOOKUP(A20,$A$309:$AX$418,$K$1,FALSE) | G20: =B20+D20-F20 | H20: 租賃資產 | I20: 106 | J20: =OFFSET(A493,0,$K$1-1) | K20: =-SUMIF($C$7:$C$127,I20,$D$7:$D$127)+SUMIF($E$7:$E$127,I20,$F$7:$F$127) | L20: =VLOOKUP(A20,$A$140:$AX$249,$K$1,FALSE) | M20: =L20-G20 | O20: =L20-B20 | P20: =J20-K20 | Q20: =D20-F20
A21: 準備金 | B21: =VLOOKUP(A21,$A$309:$AX$418,$K$1,FALSE) | C21: 242 | D21: =J53*-1 | E21: 222 | F21: =J46 | G21: =B21+SUM(D21:D25)-SUM(F21:F25) | H21: 租賃權益改良 | I21: 107 | J21: =OFFSET(A494,0,$K$1-1) | K21: =-SUMIF($C$7:$C$127,I21,$D$7:$D$127)+SUMIF($E$7:$E$127,I21,$F$7:$F$127) | L21: =VLOOKUP(A21,$A$140:$AX$249,$K$1,FALSE) | M21: =L21-G21 | O21: =L21-B21 | P21: =J21-K21 | Q21: =D21-F21
A22: 0 | C22: 401 | D22: =J90 | E22: 402 | F22: =-J91 | H22: 代管資產 | I22: 108 | J22: =OFFSET(A495,0,$K$1-1) | K22: =-SUMIF($C$7:$C$127,I22,$D$7:$D$127)+SUMIF($E$7:$E$127,I22,$F$7:$F$127) | M22: =L22-G22 | O22: =L22-B22 | P22: =J22-K22 | Q22: =D22-F22
A23: 0 | C23: 403 | D23: =J93 | H23: 生產性生物資產－非流動 | I23: 109 | J23: =OFFSET(A496,0,$K$1-1) | K23: =-SUMIF($C$7:$C$127,I23,$D$7:$D$127)+SUMIF($E$7:$E$127,I23,$F$7:$F$127) | M23: =L23-G23 | O23: =L23-B23 | P23: =J23-K23 | Q23: =D23-F23
A24: 0 | H24: 攤銷 | J24: =OFFSET(A497,0,$K$1-1) | K24: =SUM(K25:K26) | M24: =L24-G24 | O24: =L24-B24 | P24: =J24-K24 | Q24: =D24-F24
C25: 125 | D25: =J32*-1 | H25: 攤銷電腦軟體 | I25: 111 | J25: =OFFSET(A498,0,$K$1-1) | K25: =-SUMIF($C$7:$C$127,I25,$D$7:$D$127)+SUMIF($E$7:$E$127,I25,$F$7:$F$127) | M25: =L25-G25 | O25: =L25-B25 | P25: =J25-K25 | Q25: =D25-F25
A26: 不動產、廠房及設備 | B26: =SUM(B27:B52) | G26: =SUM(G27:G52) | H26: 其他攤銷費用 | I26: 112 | J26: =OFFSET(A499,0,$K$1-1) | K26: =-SUMIF($C$7:$C$127,I26,$D$7:$D$127)+SUMIF($E$7:$E$127,I26,$F$7:$F$127) | L26: =VLOOKUP(A26,$A$140:$AX$249,$K$1,FALSE) | M26: =L26-G26 | O26: =L26-B26 | P26: =J26-K26 | Q26: =D26-F26
A27: 土地 | B27: =VLOOKUP(A27,$A$309:$AX$418,$K$1,FALSE) | C27: 121 | G27: =B27+SUM(D27)-SUM(F27) | H27: 其他 | J27: =OFFSET(A500,0,$K$1-1) | K27: =K28+K29+K32 | L27: =VLOOKUP(A27,$A$140:$AX$249,$K$1,FALSE) | M27: =L27-G27 | O27: =L27-B27 | P27: =J27-K27 | Q27: =D27-F27
A28: 0 | H28: 應付退休及離職金 | I28: 122 | J28: =OFFSET(A501,0,$K$1-1) | K28: =-SUMIF($C$7:$C$127,I28,$D$7:$D$127)+SUMIF($E$7:$E$127,I28,$F$7:$F$127) | M28: =L28-G28 | O28: =L28-B28 | P28: =J28-K28 | Q28: =D28-F28
A29: 土地改良物 | B29: =VLOOKUP(A29,$A$309:$AX$418,$K$1,FALSE) | C29: 251 | D29: =J57*-1 | E29: 101 | F29: =J15 | G29: =B29+SUM(D29:D32)-SUM(F29:F32) | H29: 遞延收入 | J29: =OFFSET(A502,0,$K$1-1) | K29: =SUM(K30:K31) | L29: =VLOOKUP(A29,$A$140:$AX$249,$K$1,FALSE) | M29: =L29-G29 | O29: =L29-B29 | P29: =J29-K29 | Q29: =D29-F29
A30: 0 | C30: 404 | D30: =J96 | H30: 遞延收入-其他補助收入 | I30: 123 | J30: =OFFSET(A503,0,$K$1-1) | K30: =-SUMIF($C$7:$C$127,I30,$D$7:$D$127)+SUMIF($E$7:$E$127,I30,$F$7:$F$127) | M30: =L30-G30 | O30: =L30-B30 | P30: =J30-K30 | Q30: =D30-F30
A31: 0 | H31: 遞延收入-受贈收入 | I31: 124 | J31: =OFFSET(A504,0,$K$1-1) | K31: =-SUMIF($C$7:$C$127,I31,$D$7:$D$127)+SUMIF($E$7:$E$127,I31,$F$7:$F$127) | M31: =L31-G31 | O31: =L31-B31 | P31: =J31-K31 | Q31: =D31-F31
A32: 0 | H32: 其他 | I32: 125 | J32: =OFFSET(A505,0,$K$1-1) | M32: =L32-G32 | O32: =L32-B32 | P32: =J32-K32 | Q32: =D32-F32
A33: 房屋及建築 | B33: =VLOOKUP(A33,$A$309:$AX$418,$K$1,FALSE) | C33: 252 | D33: =J58*-1 | E33: 102 | F33: =J16 | G33: =B33+SUM(D33:D36)-SUM(F33:F36) | H33: 流動資產淨減（淨增） | I33: 151 | J33: =OFFSET(A506,0,$K$1-1) | K33: =-SUMIF($C$7:$C$127,I33,$D$7:$D$127)+SUMIF($E$7:$E$127,I33,$F$7:$F$127) | L33: =VLOOKUP(A33,$A$140:$AX$249,$K$1,FALSE) | M33: =L33-G33 | O33: =L33-B33 | P33: =J33-K33 | Q33: =D33-F33
A34: 0 | C34: 405 | D34: =J97 | H34: 流動負債淨增（淨減） | I34: 161 | J34: =OFFSET(A507,0,$K$1-1) | K34: =-SUMIF($C$7:$C$127,I34,$D$7:$D$127)+SUMIF($E$7:$E$127,I34,$F$7:$F$127) | M34: =L34-G34 | O34: =L34-B34 | P34: =J34-K34 | Q34: =D34-F34
A35: 0 | H35: 未計利息股利之現金流入（流出） | J35: =OFFSET(A508,0,$K$1-1) | K35: =K12+K13 | M35: =L35-G35 | O35: =L35-B35 | P35: =J35-K35 | Q35: =D35-F35
A36: 0 | H36: 收取利息 | J36: =OFFSET(A509,0,$K$1-1) | K36: =J36 | M36: =L36-G36 | O36: =L36-B36 | P36: =J36-K36 | Q36: =D36-F36
A37: 機械及設備 | B37: =VLOOKUP(A37,$A$309:$AX$418,$K$1,FALSE) | C37: 253 | D37: =J59*-1 | E37: 103 | F37: =J17 | G37: =B37+SUM(D37:D41)-SUM(F37:F41) | H37: 收取股利 | J37: =OFFSET(A510,0,$K$1-1) | K37: =J37 | L37: =VLOOKUP(A37,$A$140:$AX$249,$K$1,FALSE) | M37: =L37-G37 | O37: =L37-B37 | P37: =J37-K37 | Q37: =D37-F37
A38: 0 | C38: 407 | D38: =J101 | H38: 支付利息 | J38: =OFFSET(A511,0,$K$1-1) | K38: =J38 | M38: =L38-G38 | O38: =L38-B38 | P38: =J38-K38 | Q38: =D38-F38
A39: 0 | C39: 409 | D39: =J105 | E39: 412 | F39: =-J109 | H39: ▼業務活動之淨現金流入（流出） | J39: =OFFSET(A512,0,$K$1-1) | K39: =K36+K37+K38+K35 | M39: =L39-G39 | O39: =L39-B39 | P39: =J39-K39 | Q39: =D39-F39
A40: 0 | H40: ▼投資活動之現金流量 | J40: =OFFSET(A513,0,$K$1-1) | K40: =SUM(K41,K44,K47,K48,K49,K51,K54,K64) | M40: =L40-G40 | O40: =L40-B40 | P40: =J40-K40 | Q40: =D40-F40
H41: 減少流動金融資產及短期貸墊款 | J41: =OFFSET(A514,0,$K$1-1) | K41: =K42+K43 | M41: =L41-G41 | O41: =L41-B41 | P41: =J41-K41 | Q41: =D41-F41
A42: 交通及運輸設備 | B42: =VLOOKUP(A42,$A$309:$AX$418,$K$1,FALSE) | C42: 254 | D42: =J60*-1 | E42: 104 | F42: =J18 | G42: =B42+SUM(D42:D44)-SUM(F42:F44) | H42: 減少流動金融資產 | I42: 211 | J42: =OFFSET(A515,0,$K$1-1) | K42: =-SUMIF($C$7:$C$127,I42,$D$7:$D$127)+SUMIF($E$7:$E$135,I42,$F$7:$F$127) | L42: =VLOOKUP(A42,$A$140:$AX$249,$K$1,FALSE) | M42: =L42-G42 | O42: =L42-B42 | P42: =J42-K42 | Q42: =D42-F42
C43: 410 | D43: =J106 | E43: 413 | F43: =J110*-1 | H43: 減少短期墊款 | I43: 212 | J43: =OFFSET(A516,0,$K$1-1) | K43: =-SUMIF($C$7:$C$127,I43,$D$7:$D$127)+SUMIF($E$7:$E$135,I43,$F$7:$F$127) | M43: =L43-G43 | O43: =L43-B43 | P43: =J43-K43 | Q43: =D43-F43
H44: 減少投資、長期應收款、貸墊款及準備金 | J44: =OFFSET(A517,0,$K$1-1) | K44: =SUM(K45:K46) | M44: =L44-G44 | O44: =L44-B44 | P44: =J44-K44 | Q44: =D44-F44
A45: 什項設備 | B45: =VLOOKUP(A45,$A$309:$AX$418,$K$1,FALSE) | C45: 255 | D45: =J61*-1 | E45: 105 | F45: =J19 | G45: =B45+SUM(D45:D48)-SUM(F45:F48) | H45: 減少投資 | I45: 221 | J45: =OFFSET(A518,0,$K$1-1) | K45: =-SUMIF($C$7:$C$127,I45,$D$7:$D$127)+SUMIF($E$7:$E$135,I45,$F$7:$F$127) | L45: =VLOOKUP(A45,$A$140:$AX$249,$K$1,FALSE) | M45: =L45-G45 | O45: =L45-B45 | P45: =J45-K45 | Q45: =D45-F45
A46: 0 | C46: 408 | D46: =J102 | H46: 減少準備金 | I46: 222 | J46: =OFFSET(A519,0,$K$1-1) | K46: =-SUMIF($C$7:$C$127,I46,$D$7:$D$127)+SUMIF($E$7:$E$135,I46,$F$7:$F$127) | M46: =L46-G46 | O46: =L46-B46 | P46: =J46-K46 | Q46: =D46-F46
A47: 0 | C47: 411 | D47: =J107 | E47: 414 | F47: =-J111 | H47: 收取利息 | J47: =OFFSET(A520,0,$K$1-1) | K47: =J47 | M47: =L47-G47 | O47: =L47-B47 | P47: =J47-K47 | Q47: =D47-F47
A48: 0 | C48: 406 | D48: =J98 | H48: 收取股利 | J48: =OFFSET(A521,0,$K$1-1) | K48: =J48 | M48: =L48-G48 | O48: =L48-B48 | P48: =J48-K48 | Q48: =D48-F48
A49: 租賃資產 | B49: =VLOOKUP(A49,$A$309:$AX$413,$K$1,FALSE) | E49: 106 | F49: =J20 | G49: =B49+D49-F49 | H49: 增加流動金融資產及短期貸墊款 | J49: =OFFSET(A522,0,$K$1-1) | K49: =K50 | L49: =VLOOKUP(A49,$A$140:$AX$249,$K$1,FALSE) | M49: =L49-G49 | O49: =L49-B49 | P49: =J49-K49 | Q49: =D49-F49
A50: 租賃權益改良 | B50: =VLOOKUP(A50,$A$309:$AX$418,$K$1,FALSE) | C50: 257 | D50: =J63*-1 | E50: 107 | F50: =J21 | G50: =B50+D50-F50 | H50: 增加流動金融資產 | I50: 231 | J50: =OFFSET(A523,0,$K$1-1) | K50: =-SUMIF($C$7:$C$127,I50,$D$7:$D$127)+SUMIF($E$7:$E$135,I50,$F$7:$F$127) | L50: =VLOOKUP(A50,$A$140:$AX$249,$K$1,FALSE) | M50: =L50-G50 | O50: =L50-B49 | P50: =J50-K50 | Q50: =D49-F49
A51: 購建中固定資產 | B51: =VLOOKUP(A51,$A$309:$AX$418,$K$1,FALSE) | C51: 256 | D51: =J62*-1 | E51: 404 | F51: =J96 | G51: =B51+SUM(D51:D53)-SUM(F51:F53) | H51: 增加投資、長期應收款、貸墊款及準備金 | J51: =OFFSET(A524,0,$K$1-1) | K51: =SUM(K52:K53) | L51: =VLOOKUP(A51,$A$140:$AX$249,$K$1,FALSE) | M51: =L51-G51 | O51: =L51-B50 | P51: =J51-K51 | Q51: =D50-F50
E52: 405 | F52: =J97 | H52: 增加投資 | I52: 241 | J52: =OFFSET(A525,0,$K$1-1) | K52: =-SUMIF($C$7:$C$127,I52,$D$7:$D$127)+SUMIF($E$7:$E$135,I52,$F$7:$F$127) | M52: =L52-G52 | O52: =L52-B51 | P52: =J52-K52 | Q52: =D51-F51
E53: 406 | F53: =J98 | H53: 增加準備金 | I53: 242 | J53: =OFFSET(A526,0,$K$1-1) | K53: =-SUMIF($C$7:$C$127,I53,$D$7:$D$127)+SUMIF($E$7:$E$135,I53,$F$7:$F$127) | M53: =L53-G52 | O53: =L53-B52 | P53: =J53-K53 | Q53: =D52-F52
A54: 生物資產－非流動 | B54: =SUM(B55) | G54: =SUM(G55) | H54: 增加不動產、廠房及設備、礦產資源 | J54: =OFFSET(A527,0,$K$1-1) | K54: =K55 | L54: =VLOOKUP(A54,$A$140:$AX$249,$K$1,FALSE) | M54: =L54-G54 | O54: =L54-B54 | P54: =J54-K54 | Q54: =D54-F54
A55: 生產性生物資產－非流動 | B55: =VLOOKUP(A55,$A$309:$AX$418,$K$1,FALSE) | E55: 109 | F55: =J23 | G55: =B55+SUM(D55:D55)-SUM(F55:F55) | H55: 增加不動產、廠房及設備 | J55: =OFFSET(A528,0,$K$1-1) | K55: =K56 | L55: =VLOOKUP(A55,$A$140:$AX$249,$K$1,FALSE) | M55: =L55-G55 | O55: =L55-B55 | P55: =J55-K55 | Q55: =D55-F55
A56: 無形資產 | B56: =SUM(B57) | G56: =SUM(G57) | H56: 固定資產之增置 | J56: =OFFSET(A529,0,$K$1-1) | K56: =SUM(K57:K63) | L56: =VLOOKUP(A56,$A$140:$AX$249,$K$1,FALSE) | M56: =L56-G56 | O56: =L56-B56 | P56: =J56-K56 | Q56: =D56-F56
A57: 無形資產 | B57: =VLOOKUP(A57,$A$309:$AX$418,$K$1,FALSE) | E57: 111 | F57: =J25 | G57: =B57+SUM(D57:D59)-SUM(F57:F59) | H57: 土地改良物 | I57: 251 | J57: =OFFSET(A530,0,$K$1-1) | K57: =-SUMIF($C$7:$C$127,I57,$D$7:$D$127)+SUMIF($E$7:$E$127,I57,$F$7:$F$127) | L57: =VLOOKUP(A57,$A$140:$AX$249,$K$1,FALSE) | M57: =L57-G57 | O57: =L57-B57 | P57: =J57-K57 | Q57: =D57-F57
A58: 0 | C58: 415 | D58: =J113 | E58: 416 | F58: =J114*-1 | H58: 房屋及建築 | I58: 252 | J58: =OFFSET(A531,0,$K$1-1) | K58: =-SUMIF($C$7:$C$127,I58,$D$7:$D$127)+SUMIF($E$7:$E$127,I58,$F$7:$F$127) | M58: =L58-G58 | O58: =L58-B58 | P58: =J58-K58 | Q58: =D58-F58
A59: 0 | C59: 258 | D59: =J65*-1 | E59: 112 | H59: 機械及設備 | I59: 253 | J59: =OFFSET(A532,0,$K$1-1) | K59: =-SUMIF($C$7:$C$127,I59,$D$7:$D$127)+SUMIF($E$7:$E$127,I59,$F$7:$F$127) | M59: =L59-G59 | O59: =L59-B59 | P59: =J59-K59 | Q59: =D59-F59
A60: 0 | H60: 交通及運輸設備 | I60: 254 | J60: =OFFSET(A533,0,$K$1-1) | K60: =-SUMIF($C$7:$C$127,I60,$D$7:$D$127)+SUMIF($E$7:$E$127,I60,$F$7:$F$127) | M60: =L60-G60 | O60: =L60-B60 | P60: =J60-K60 | Q60: =D60-F60
A61: 其他資產 | B61: =SUM(B62,B65,B68) | G61: =SUM(G62,G65,G68) | H61: 什項設備 | I61: 255 | J61: =OFFSET(A534,0,$K$1-1) | K61: =-SUMIF($C$7:$C$127,I61,$D$7:$D$127)+SUMIF($E$7:$E$127,I61,$F$7:$F$127) | L61: =VLOOKUP(A61,$A$140:$AX$249,$K$1,FALSE) | M61: =L61-G61 | O61: =L61-B61 | P61: =J61-K61 | Q61: =D61-F61
A62: 遞延資產 | B62: =VLOOKUP(A62,$A$309:$AX$418,$K$1,FALSE) | E62: 112 | F62: =J26-F59 | G62: =B62+SUM(D62:D64)-SUM(F62:F64) | H62: 購建中固定資產 | I62: 256 | J62: =OFFSET(A535,0,$K$1-1) | K62: =-SUMIF($C$7:$C$127,I62,$D$7:$D$127)+SUMIF($E$7:$E$127,I62,$F$7:$F$127) | L62: =VLOOKUP(A62,$A$140:$AX$249,$K$1,FALSE) | M62: =L62-G62 | O62: =L62-B62 | P62: =J62-K62 | Q62: =D62-F62
A63: 0 | D63: =J126 | F63: =J127*-1 | H63: 租賃權益改良 | I63: 257 | J63: =OFFSET(A536,0,$K$1-1) | K63: =-SUMIF($C$7:$C$127,I63,$D$7:$D$127)+SUMIF($E$7:$E$127,I63,$F$7:$F$127) | M63: =L63-G63 | O63: =L63-B63 | P63: =J63-K63 | Q63: =D63-F63
A64: 0 | C64: 259 | D64: =J67*-1 | H64: 增加無形資產及其他資產 | J64: =OFFSET(A537,0,$K$1-1) | K64: =K65+K66 | M64: =L64-G64 | O64: =L64-B64 | P64: =J64-K64 | Q64: =D64-F64
A65: 什項資產 | B65: =VLOOKUP(A65,$A$309:$AX$418,$K$1,FALSE) | C65: 417 | D65: =F111 | E65: 108 | F65: =J22 | G65: =B65+SUM(D65:D67)-SUM(F65:F67) | H65: 增加無形資產 | I65: 258 | J65: =OFFSET(A538,0,$K$1-1) | K65: =-SUMIF($C$7:$C$127,I65,$D$7:$D$127)+SUMIF($E$7:$E$127,I65,$F$7:$F$127) | L65: =VLOOKUP(A65,$A$140:$AX$249,$K$1,FALSE) | M65: =L65-G65 | O65: =L65-B65 | P65: =J65-K65 | Q65: =D65-F65
A66: 0 | H66: 增加其他資產 | J66: =OFFSET(A539,0,$K$1-1) | K66: =K67 | M66: =L66-G66 | O66: =L66-B66 | P66: =J66-K66 | Q66: =D66-F66
A67: 0 | H67: 增加遞延費用 | I67: 259 | J67: =OFFSET(A540,0,$K$1-1) | K67: =-SUMIF($C$7:$C$127,I67,$D$7:$D$127)+SUMIF($E$7:$E$127,I67,$F$7:$F$127) | M67: =L67-G67 | O67: =L67-B67 | P67: =J67-K67 | Q67: =D67-F67
G68: =B68+D68-F68 | H68: ▼投資活動之淨現金流入（流出） | J68: =OFFSET(A541,0,$K$1-1) | K68: =K40 | P68: =J68-K68 | Q68: =D68-F68
A69: 合 計 | B69: =B7+B17+B26+B54+B56+B61 | G69: =G7+G17+G26+G54+G56+G61 | H69: ▼籌資活動之現金流量 | J69: =OFFSET(A542,0,$K$1-1) | K69: =K70+K72+K74+K81+K79+K83 | L69: =VLOOKUP(A69,$A$140:$AX$249,$K$1,FALSE) | M69: =L69-G69 | O69: =L69-B69 | P69: =J69-K69 | Q69: =D69-F69
A70: 負債 | B70: =B71+B78+B83 | G70: =G71+G78+G83 | H70: 增加短期債務、流動金融負債及其他負債 | J70: =OFFSET(A543,0,$K$1-1) | K70: =K71 | L70: =VLOOKUP(A70,$A$253:$AX$305,$K$1,FALSE) | M70: =L70-G70 | O70: =L70-B70 | P70: =J70-K70 | Q70: =D70-F70
A71: 流動負債 | B71: =SUM(B72:B77) | G71: =SUM(G72:G77) | H71: 增加其他負債 | I71: 311 | J71: =OFFSET(A544,0,$K$1-1) | K71: =-SUMIF($C$7:$C$127,I71,$D$7:$D$127)+SUMIF($E$7:$E$127,I71,$F$7:$F$127) | L71: =VLOOKUP(A71,$A$253:$AX$305,$K$1,FALSE) | M71: =L71-G71 | O71: =L71-B71 | P71: =J71-K71 | Q71: =D71-F71
A72: 短期債務 | B72: =VLOOKUP(A72,$A$423:$AX$475,$K$1,FALSE) | C72: 322 | D72: =J82*-1 | E72: 418 | F72: =D81 | G72: =B72+SUM(F72:F73)-SUM(D72:D73) | H72: 增加長期負債 | J72: =OFFSET(A545,0,$K$1-1) | K72: =K73 | L72: =VLOOKUP(A72,$A$253:$AX$305,$K$1,FALSE) | M72: =L72-G72 | O72: =L72-B72 | P72: =J72-K72 | Q72: =D72-F72
A73: 0 | C73: 316 | H73: 增加長期債務 | I73: 312 | J73: =OFFSET(A546,0,$K$1-1) | K73: =-SUMIF($C$7:$C$127,I73,$D$7:$D$127)+SUMIF($E$7:$E$127,I73,$F$7:$F$127) | M73: =L73-G73 | O73: =L73-B73 | P73: =J73-K73 | Q73: =D73-F73
A74: 應付款項 | B74: =VLOOKUP(A74,$A$423:$AX$475,$K$1,FALSE) | E74: 161 | G74: =B74+SUM(F74:F75)-SUM(D74:D75) | H74: 增加基金、公積及填補短絀 | J74: =OFFSET(A547,0,$K$1-1) | K74: =SUM(K75) | L74: =VLOOKUP(A74,$A$253:$AX$305,$K$1,FALSE) | M74: =L74-G74 | O74: =L74-B74 | P74: =J74-K74 | Q74: =D74-F74
A75: 0 | H75: 增加基金 | J75: =OFFSET(A548,0,$K$1-1) | K75: =SUM(K76:K78) | M75: =L75-G75 | O75: =L75-B75 | P75: =J75-K75 | Q75: =D75-F75
A76: 預收款項 | B76: =VLOOKUP(A76,$A$423:$AX$475,$K$1,FALSE) | E76: 161 | F76: =J34 | G76: =B76+SUM(F76:F77)-SUM(D76:D77) | H76: 國庫撥款增置固定資產 | I76: 313 | J76: =OFFSET(A549,0,$K$1-1) | K76: =-SUMIF($C$7:$C$127,I76,$D$7:$D$127)+SUMIF($E$7:$E$127,I76,$F$7:$F$127) | L76: =VLOOKUP(A76,$A$253:$AX$305,$K$1,FALSE) | M76: =L76-G76 | O76: =L76-B76 | P76: =J76-K76 | Q76: =D76-F76
A77: 0 | H77: 國庫增撥無形資產 | I77: 314 | J77: =OFFSET(A550,0,$K$1-1) | K77: =-SUMIF($C$7:$C$127,I77,$D$7:$D$127)+SUMIF($E$7:$E$127,I77,$F$7:$F$127) | M77: =L77-G77 | O77: =L77-B77 | P77: =J77-K77 | Q77: =D77-F77
A78: 長期負債 | B78: =SUM(B81) | G78: =SUM(G81) | H78: 國庫增撥遞延資產 | I78: 315 | J78: =OFFSET(A551,0,$K$1-1) | K78: =-SUMIF($C$7:$C$127,I78,$D$7:$D$127)+SUMIF($E$7:$E$127,I78,$F$7:$F$127) | L78: =VLOOKUP(A78,$A$253:$AX$305,$K$1,FALSE) | M78: =L78-G78 | O78: =L78-B78 | P78: =J78-K78 | Q78: =D78-F78
H79: 減少短期債務、流動金融負債及其他負債 | J79: =OFFSET(A552,0,$K$1-1)
H80: 減少短期債務 | I80: 316 | J80: =OFFSET(A553,0,$K$1-1) | K80: =-SUMIF($C$7:$C$127,I80,$D$7:$D$127)+SUMIF($E$7:$E$127,I80,$F$7:$F$127)
A81: 長期債務 | B81: =VLOOKUP(A81,$A$423:$AX$475,$K$1,FALSE) | C81: 418 | D81: =J116 | E81: 312 | F81: =J73 | G81: =B81+SUM(F81:F82)-SUM(D81:D82) | H81: 減少長期負債 | J81: =OFFSET(A554,0,$K$1-1) | K81: =K82 | L81: =VLOOKUP(A81,$A$253:$AX$305,$K$1,FALSE) | M81: =L81-G81 | O81: =L81-B81 | P81: =J81-K81 | Q81: =D81-F81
A82: 0 | C82: 322 | H82: 減少長期債務 | I82: 322 | J82: =OFFSET(A555,0,$K$1-1) | K82: =-SUMIF($C$7:$C$127,I82,$D$7:$D$127)+SUMIF($E$7:$E$127,I82,$F$7:$F$127) | M82: =L82-G82 | O82: =L82-B82 | P82: =J82-K82 | Q82: =D72-F82
A83: 其他負債 | B83: =SUM(B84,B90) | G83: =SUM(G84,G90) | H83: 支付利息 | J83: =OFFSET(A556,0,$K$1-1) | K83: =J83 | L83: =VLOOKUP(A83,$A$253:$AX$305,$K$1,FALSE) | M83: =L83-G83 | O83: =L83-B83 | P83: =J83-K83 | Q83: =D83-F83
A84: 什項負債 | B84: =VLOOKUP(A84,$A$423:$AX$475,$K$1,FALSE) | C84: 321 | G84: =B84+SUM(F84:F89)-SUM(D84:D89) | H84: ▼籌資活動之淨現金流入（流出） | J84: =OFFSET(A557,0,$K$1-1) | K84: =K69 | L84: =VLOOKUP(A84,$A$253:$AX$305,$K$1,FALSE) | M84: =L84-G84 | O84: =L84-B84 | P84: =J84-K84 | Q84: =D84-F84
A85: 0 | C85: 402 | D85: =J91*-1 | E85: 122 | F85: =J28 | H85: ▼現金及約當現金之淨增（淨減） | I85: B | J85: =OFFSET(A558,0,$K$1-1) | K85: =J85 | M85: =L85-G85 | O85: =L85-B85 | P85: =J85-K85 | Q85: =D85-F85
A86: 0 | E86: 401 | F86: =J90 | H86: ▼期初現金及約當現金 | J86: =OFFSET(A559,0,$K$1-1) | K86: =B8 | M86: =L86-G86 | O86: =L86-B86 | P86: =J86-K86 | Q86: =D86-F86
A87: 0 | H87: ▼期末現金及約當現金 | J87: =OFFSET(A560,0,$K$1-1) | K87: =G8 | M87: =L87-G87 | O87: =L87-B87 | P87: =J87-K87 | Q87: =D87-F87
A88: 0 | H88: ▼不影響現金流量之投資與籌資活動 | J88: =OFFSET(A561,0,$K$1-1) | M88: =L88-G88 | O88: =L88-B88 | P88: =J88-K88 | Q88: =D88-F88
A89: 0 | H89: 退休離職準備金與應付退休及離職金同額增加(+)或減少(-)之金額 | J89: =OFFSET(A562,0,$K$1-1) | K89: =K90+K91 | M89: =L89-G89 | O89: =L89-B89 | P89: =J89-K89 | Q89: =D89-F89
A90: 遞延負債 | B90: =VLOOKUP(A90,$A$423:$AX$475,$K$1,FALSE) | C90: 124 | D90: =J31*-1 | E90: 311 | F90: =J71 | G90: =B90+SUM(F90:F96)-SUM(D90:D96) | H90: 退休離職準備金與應付退休及離職金同額增加之金額(+) | I90: 401 | J90: =OFFSET(A563,0,$K$1-1) | K90: =(SUMIF($C$7:$C$127,I90,$D$7:$D$127)+SUMIF($E$7:$E$127,I90,$F$7:$F$127))/2 | L90: =VLOOKUP(A90,$A$253:$AX$305,$K$1,FALSE) | M90: =L90-G90 | O90: =L90-B90 | P90: =J90-K90 | Q90: =D90-F90
A91: 0 | C91: 123 | D91: =-J30 | E91: 403 | F91: =J93 | H91: 退休離職準備金與應付退休及離職金同額減少之金額(-) | I91: 402 | J91: =OFFSET(A564,0,$K$1-1) | K91: =(SUMIF($C$7:$C$127,I91,$D$7:$D$127)+SUMIF($E$7:$E$127,I91,$F$7:$F$127))/2*-1 | M91: =L91-G91 | O91: =L91-B91 | P91: =J91-K91 | Q91: =D91-F91
A92: 0 | E92: 407 | F92: =J101 | H92: 其他準備金與遞延收入同額增加之金額 | J92: =OFFSET(A565,0,$K$1-1) | K92: =K93 | M92: =L92-G92 | O92: =L92-B92 | P92: =J92-K92 | Q92: =D92-F92
A93: 0 | E93: 408 | F93: =J102 | H93: 其他準備金與遞延收入同額增加之金額 | I93: 403 | J93: =OFFSET(A566,0,$K$1-1) | K93: =(SUMIF($C$7:$C$127,I93,$D$7:$D$127)+SUMIF($E$7:$E$127,I93,$F$7:$F$127))/2 | M93: =L93-G93 | O93: =L93-B93 | P93: =J93-K93 | Q93: =D93-F93
E94: 410 | H94: 以前年度購建中固定資產科目，調整轉入不動產、廠房及設備科目之 | J94: =OFFSET(A567,0,$K$1-1) | K94: =K95 | P94: =J94-K94
H95: 調整轉入不動產、廠房及設備科目明細 | J95: =OFFSET(A568,0,$K$1-1) | K95: =K96+K97+K98 | O95: =L95-B96 | P95: =J95-K95 | Q95: =D96-F96
A96: 0 | H96: 土地改良物 | I96: 404 | J96: =OFFSET(A569,0,$K$1-1) | K96: =(SUMIF($C$7:$C$127,I96,$D$7:$D$127)+SUMIF($E$7:$E$127,I96,$F$7:$F$127))/2 | O96: =L97-B97 | P96: =J96-K96 | Q96: =D97-F97
A97: 淨值 | B97: =B98+B110+B116+B125 | G97: =G98+G110+G116+G125 | H97: 房屋及建築 | I97: 405 | J97: =OFFSET(A570,0,$K$1-1) | K97: =(SUMIF($C$7:$C$127,I97,$D$7:$D$127)+SUMIF($E$7:$E$127,I97,$F$7:$F$127))/2 | L97: =VLOOKUP(A97,$A$253:$AX$305,$K$1,FALSE) | M97: =L97-G97 | O97: =L98-B98 | P97: =J97-K97 | Q97: =D98-F98
A98: 基金 | B98: =SUM(B99:B101) | G98: =SUM(G99:G101) | H98: 什項設備 | I98: 406 | J98: =OFFSET(A571,0,$K$1-1) | K98: =(SUMIF($C$7:$C$127,I98,$D$7:$D$127)+SUMIF($E$7:$E$127,I98,$F$7:$F$127))/2 | L98: =VLOOKUP(A98,$A$253:$AX$305,$K$1,FALSE) | M98: =L98-G98 | O98: =L99-B99 | P98: =J98-K98 | Q98: =D99-F99
A99: 基金 | B99: =VLOOKUP(A99,$A$423:$AX$475,$K$1,FALSE) | E99: 313 | F99: =J76 | G99: =B99+SUM(F99:F109)-SUM(D99:D109) | H99: 不動產、廠房及設備與遞延收入同額增加(+)或減少(-)之金額 | J99: =OFFSET(A572,0,$K$1-1) | K99: =K100 | L99: =VLOOKUP(A99,$A$253:$AX$305,$K$1,FALSE) | M99: =L99-G99 | O99: =L100-B100 | P99: =J99-K99 | Q99: =D100-F100
A100: 0 | E100: 314 | F100: =J77 | H100: 不動產、廠房及設備與遞延收入同額增加明細(+) | J100: =OFFSET(A573,0,$K$1-1) | K100: =K101+K102 | M100: =L100-G100 | O100: =L101-B101 | P100: =J100-K100 | Q100: =D101-F101
...

Sheet 中山
A1: =OFFSET(A139,0,K1-1) | K1: =L1+2 | L1: 7
A2: 預計平衡表與現金流量表勾稽底稿
A3: 中華民國115年度
A4: 科目 | B4: 114.12.31 | C4: 調整項目 | G4: 115.12.31 | H4: 現金流量表勾稽項目
B5: 預計數 | D5: 借方 | F5: 貸方 | G5: 預計數
A6: 資產 | H6: ▼業務活動之現金流量 | L6: 114年12月 | M6: 差異數要再加(減) | O6: 比較增減 | Q6: 調整項目
A7: 流動資產 | B7: =SUM(B8:B16) | G7: =SUM(G8:G16) | H7: 本期賸餘（短絀） | I7: A | J7: =OFFSET(A480,0,$K$1-1) | K7: =-SUMIF($C$7:$C$127,I7,$D$7:$D$127)+SUMIF($E$7:$E$127,I7,$F$7:$F$127) | L7: =VLOOKUP(A7,$A$140:$AX$249,$K$1,FALSE) | M7: =L7-G7 | O7: =L7-B7 | P7: =J7-K7 | Q7: =D7-F7
A8: 現金 | B8: =VLOOKUP(A8,$A$309:$AX$418,$K$1,FALSE) | C8: B | D8: =IF(G8-B8>0,G8-B8,"0") | E8: B | F8: =IF(G8-B8<0,B8-G8,"0") | G8: =J87 | H8: 利息股利之調整 | J8: =OFFSET(A481,0,$K$1-1) | K8: =SUM(K9:K11) | L8: =VLOOKUP(A8,$A$140:$AX$249,$K$1,FALSE) | M8: =L8-G8 | O8: =L8-B8 | P8: =J8-K8 | Q8: =D8-F8
A9: 流動金融資產 | B9: =VLOOKUP(A9,$A$309:$AX$418,$K$1,FALSE) | C9: 231 | D9: =J50*-1 | E9: 211 | F9: =J42 | G9: =B9+D9-F9+D10-F10 | H9: 利息收入 | J9: =OFFSET(A482,0,$K$1-1) | K9: =J9 | L9: =VLOOKUP(A9,$A$140:$AX$249,$K$1,FALSE) | M9: =L9-G9 | O9: =L9-B9 | P9: =J9-K9 | Q9: =D9-F9
C10: 125 | H10: 股利收入 | J10: =OFFSET(A483,0,$K$1-1) | K10: =J10 | M10: =L10-G10 | O10: =L10-B10 | P10: =J10-K10 | Q10: =D10-F10
A11: 應收款項 | B11: =VLOOKUP(A11,$A$309:$AX$418,$K$1,FALSE) | C11: 151 | E11: 151 | G11: =B11+D11-F11 | H11: 利息費用 | J11: =OFFSET(A484,0,$K$1-1) | K11: =J11 | L11: =VLOOKUP(A11,$A$140:$AX$249,$K$1,FALSE) | M11: =L11-G11 | O11: =L11-B11 | P11: =J11-K11 | Q11: =D11-F11
A12: 0 | H12: 未計利息股利之本期賸餘（短絀） | J12: =OFFSET(A485,0,$K$1-1) | K12: =K7+K8 | M12: =L12-G12 | O12: =L12-B12 | P12: =J12-K12 | Q12: =D12-F12
A13: 存貨 | B13: =VLOOKUP(A13,$A$309:$AX$418,$K$1,FALSE) | C13: 151 | E13: 151 | G13: =B13+D13-F13 | H13: 調整項目 | J13: =OFFSET(A486,0,$K$1-1) | K13: =SUM(K14,K24,K27,K34,K33) | L13: =VLOOKUP(A13,$A$140:$AX$249,$K$1,FALSE) | M13: =L13-G13 | O13: =L13-B13 | P13: =J13-K13 | Q13: =D13-F13
A14: 生產性生物資產－流動 | B14: =VLOOKUP(A14,$A$309:$AX$418,$K$1,FALSE) | C14: 151 | E14: 151 | G14: =B14+D14-F14 | H14: 折舊、減損及折耗 | J14: =OFFSET(A487,0,$K$1-1) | K14: =SUM(K15:K23) | L14: =VLOOKUP(A14,$A$140:$AX$249,$K$1,FALSE) | M14: =L14-G14 | O14: =L14-B14 | P14: =J14-K14 | Q14: =D14-F14
A15: 預付款項 | B15: =VLOOKUP(A15,$A$309:$AX$418,$K$1,FALSE) | C15: 151 | E15: 151 | G15: =B15+D15-F15 | H15: 土地改良物 | I15: 101 | J15: =OFFSET(A488,0,$K$1-1) | K15: =-SUMIF($C$7:$C$127,I15,$D$7:$D$127)+SUMIF($E$7:$E$127,I15,$F$7:$F$127) | L15: =VLOOKUP(A15,$A$140:$AX$249,$K$1,FALSE) | M15: =L15-G15 | O15: =L15-B15 | P15: =J15-K15 | Q15: =D15-F15
A16: 短期貸墊款 | B16: =VLOOKUP(A16,$A$309:$AX$418,$K$1,FALSE) | C16: 151 | E16: 212 | F16: =J43 | G16: =B16+D16-F16 | H16: 房屋及建築 | I16: 102 | J16: =OFFSET(A489,0,$K$1-1) | K16: =-SUMIF($C$7:$C$127,I16,$D$7:$D$127)+SUMIF($E$7:$E$127,I16,$F$7:$F$127) | L16: =VLOOKUP(A16,$A$140:$AX$249,$K$1,FALSE) | M16: =L16-G16 | O16: =L16-B16 | P16: =J16-K16 | Q16: =D16-F16
A17: 投資、長期應收款、貸墊款及準備金 | B17: =SUM(B18:B21) | G17: =SUM(G18:G21) | H17: 機械及設備 | I17: 103 | J17: =OFFSET(A490,0,$K$1-1) | K17: =-SUMIF($C$7:$C$127,I17,$D$7:$D$127)+SUMIF($E$7:$E$127,I17,$F$7:$F$127) | L17: =VLOOKUP(A17,$A$140:$AX$249,$K$1,FALSE) | M17: =L17-G17 | O17: =L17-B17 | P17: =J17-K17 | Q17: =D17-F17
A18: 採權益法之投資 | B18: =VLOOKUP(A18,$A$309:$AX$418,$K$1,FALSE) | G18: =D18+F18+B18 | H18: 交通及運輸設備 | I18: 104 | J18: =OFFSET(A491,0,$K$1-1) | K18: =-SUMIF($C$7:$C$127,I18,$D$7:$D$127)+SUMIF($E$7:$E$127,I18,$F$7:$F$127) | L18: =VLOOKUP(A18,$A$140:$AX$249,$K$1,FALSE) | M18: =L18-G18 | O18: =L18-B18 | P18: =J18-K18 | Q18: =D18-F18
A19: 非流動金融資產 | B19: =VLOOKUP(A19,$A$309:$AX$418,$K$1,FALSE) | C19: 241 | D19: =J52*-1 | E19: 221 | F19: =J45 | G19: =B19+D19-F19 | H19: 什項設備 | I19: 105 | J19: =OFFSET(A492,0,$K$1-1) | K19: =-SUMIF($C$7:$C$127,I19,$D$7:$D$127)+SUMIF($E$7:$E$127,I19,$F$7:$F$127) | L19: =VLOOKUP(A19,$A$140:$AX$249,$K$1,FALSE) | M19: =L19-G19 | O19: =L19-B19 | P19: =J19-K19 | Q19: =D19-F19
A20: 長期應收款 | B20: =VLOOKUP(A20,$A$309:$AX$418,$K$1,FALSE) | G20: =B20+D20-F20 | H20: 租賃資產 | I20: 106 | J20: =OFFSET(A493,0,$K$1-1) | K20: =-SUMIF($C$7:$C$127,I20,$D$7:$D$127)+SUMIF($E$7:$E$127,I20,$F$7:$F$127) | L20: =VLOOKUP(A20,$A$140:$AX$249,$K$1,FALSE) | M20: =L20-G20 | O20: =L20-B20 | P20: =J20-K20 | Q20: =D20-F20
A21: 準備金 | B21: =VLOOKUP(A21,$A$309:$AX$418,$K$1,FALSE) | C21: 242 | D21: =J53*-1 | E21: 222 | F21: =J46 | G21: =B21+SUM(D21:D25)-SUM(F21:F25) | H21: 租賃權益改良 | I21: 107 | J21: =OFFSET(A494,0,$K$1-1) | K21: =-SUMIF($C$7:$C$127,I21,$D$7:$D$127)+SUMIF($E$7:$E$127,I21,$F$7:$F$127) | L21: =VLOOKUP(A21,$A$140:$AX$249,$K$1,FALSE) | M21: =L21-G21 | O21: =L21-B21 | P21: =J21-K21 | Q21: =D21-F21
A22: 0 | C22: 401 | D22: =J90 | E22: 402 | F22: =-J91 | H22: 代管資產 | I22: 108 | J22: =OFFSET(A495,0,$K$1-1) | K22: =-SUMIF($C$7:$C$127,I22,$D$7:$D$127)+SUMIF($E$7:$E$127,I22,$F$7:$F$127) | M22: =L22-G22 | O22: =L22-B22 | P22: =J22-K22 | Q22: =D22-F22
A23: 0 | C23: 403 | D23: =J93 | H23: 生產性生物資產－非流動 | I23: 109 | J23: =OFFSET(A496,0,$K$1-1) | K23: =-SUMIF($C$7:$C$127,I23,$D$7:$D$127)+SUMIF($E$7:$E$127,I23,$F$7:$F$127) | M23: =L23-G23 | O23: =L23-B23 | P23: =J23-K23 | Q23: =D23-F23
A24: 0 | H24: 攤銷 | J24: =OFFSET(A497,0,$K$1-1) | K24: =SUM(K25:K26) | M24: =L24-G24 | O24: =L24-B24 | P24: =J24-K24 | Q24: =D24-F24
C25: 125 | D25: =J32*-1 | H25: 攤銷電腦軟體 | I25: 111 | J25: =OFFSET(A498,0,$K$1-1) | K25: =-SUMIF($C$7:$C$127,I25,$D$7:$D$127)+SUMIF($E$7:$E$127,I25,$F$7:$F$127) | M25: =L25-G25 | O25: =L25-B25 | P25: =J25-K25 | Q25: =D25-F25
A26: 不動產、廠房及設備 | B26: =SUM(B27:B52) | G26: =SUM(G27:G52) | H26: 其他攤銷費用 | I26: 112 | J26: =OFFSET(A499,0,$K$1-1) | K26: =-SUMIF($C$7:$C$127,I26,$D$7:$D$127)+SUMIF($E$7:$E$127,I26,$F$7:$F$127) | L26: =VLOOKUP(A26,$A$140:$AX$249,$K$1,FALSE) | M26: =L26-G26 | O26: =L26-B26 | P26: =J26-K26 | Q26: =D26-F26
A27: 土地 | B27: =VLOOKUP(A27,$A$309:$AX$418,$K$1,FALSE) | C27: 121 | G27: =B27+SUM(D27)-SUM(F27) | H27: 其他 | J27: =OFFSET(A500,0,$K$1-1) | K27: =K28+K29+K32 | L27: =VLOOKUP(A27,$A$140:$AX$249,$K$1,FALSE) | M27: =L27-G27 | O27: =L27-B27 | P27: =J27-K27 | Q27: =D27-F27
A28: 0 | H28: 應付退休及離職金 | I28: 122 | J28: =OFFSET(A501,0,$K$1-1) | K28: =-SUMIF($C$7:$C$127,I28,$D$7:$D$127)+SUMIF($E$7:$E$127,I28,$F$7:$F$127) | M28: =L28-G28 | O28: =L28-B28 | P28: =J28-K28 | Q28: =D28-F28
A29: 土地改良物 | B29: =VLOOKUP(A29,$A$309:$AX$418,$K$1,FALSE) | C29: 251 | D29: =J57*-1 | E29: 101 | F29: =J15 | G29: =B29+SUM(D29:D32)-SUM(F29:F32) | H29: 遞延收入 | J29: =OFFSET(A502,0,$K$1-1) | K29: =SUM(K30:K31) | L29: =VLOOKUP(A29,$A$140:$AX$249,$K$1,FALSE) | M29: =L29-G29 | O29: =L29-B29 | P29: =J29-K29 | Q29: =D29-F29
A30: 0 | C30: 404 | D30: =J96 | H30: 遞延收入-其他補助收入 | I30: 123 | J30: =OFFSET(A503,0,$K$1-1) | K30: =-SUMIF($C$7:$C$127,I30,$D$7:$D$127)+SUMIF($E$7:$E$127,I30,$F$7:$F$127) | M30: =L30-G30 | O30: =L30-B30 | P30: =J30-K30 | Q30: =D30-F30
A31: 0 | H31: 遞延收入-受贈收入 | I31: 124 | J31: =OFFSET(A504,0,$K$1-1) | K31: =-SUMIF($C$7:$C$127,I31,$D$7:$D$127)+SUMIF($E$7:$E$127,I31,$F$7:$F$127) | M31: =L31-G31 | O31: =L31-B31 | P31: =J31-K31 | Q31: =D31-F31
A32: 0 | H32: 其他 | I32: 125 | J32: =OFFSET(A505,0,$K$1-1) | M32: =L32-G32 | O32: =L32-B32 | P32: =J32-K32 | Q32: =D32-F32
A33: 房屋及建築 | B33: =VLOOKUP(A33,$A$309:$AX$418,$K$1,FALSE) | C33: 252 | D33: =J58*-1 | E33: 102 | F33: =J16 | G33: =B33+SUM(D33:D36)-SUM(F33:F36) | H33: 流動資產淨減（淨增） | I33: 151 | J33: =OFFSET(A506,0,$K$1-1) | K33: =-SUMIF($C$7:$C$127,I33,$D$7:$D$127)+SUMIF($E$7:$E$127,I33,$F$7:$F$127) | L33: =VLOOKUP(A33,$A$140:$AX$249,$K$1,FALSE) | M33: =L33-G33 | O33: =L33-B33 | P33: =J33-K33 | Q33: =D33-F33
A34: 0 | C34: 405 | D34: =J97 | H34: 流動負債淨增（淨減） | I34: 161 | J34: =OFFSET(A507,0,$K$1-1) | K34: =-SUMIF($C$7:$C$127,I34,$D$7:$D$127)+SUMIF($E$7:$E$127,I34,$F$7:$F$127) | M34: =L34-G34 | O34: =L34-B34 | P34: =J34-K34 | Q34: =D34-F34
A35: 0 | H35: 未計利息股利之現金流入（流出） | J35: =OFFSET(A508,0,$K$1-1) | K35: =K12+K13 | M35: =L35-G35 | O35: =L35-B35 | P35: =J35-K35 | Q35: =D35-F35
A36: 0 | H36: 收取利息 | J36: =OFFSET(A509,0,$K$1-1) | K36: =J36 | M36: =L36-G36 | O36: =L36-B36 | P36: =J36-K36 | Q36: =D36-F36
A37: 機械及設備 | B37: =VLOOKUP(A37,$A$309:$AX$418,$K$1,FALSE) | C37: 253 | D37: =J59*-1 | E37: 103 | F37: =J17 | G37: =B37+SUM(D37:D41)-SUM(F37:F41) | H37: 收取股利 | J37: =OFFSET(A510,0,$K$1-1) | K37: =J37 | L37: =VLOOKUP(A37,$A$140:$AX$249,$K$1,FALSE) | M37: =L37-G37 | O37: =L37-B37 | P37: =J37-K37 | Q37: =D37-F37
A38: 0 | C38: 407 | D38: =J101 | H38: 支付利息 | J38: =OFFSET(A511,0,$K$1-1) | K38: =J38 | M38: =L38-G38 | O38: =L38-B38 | P38: =J38-K38 | Q38: =D38-F38
A39: 0 | C39: 409 | D39: =J105 | E39: 412 | F39: =-J109 | H39: ▼業務活動之淨現金流入（流出） | J39: =OFFSET(A512,0,$K$1-1) | K39: =K36+K37+K38+K35 | M39: =L39-G39 | O39: =L39-B39 | P39: =J39-K39 | Q39: =D39-F39
A40: 0 | H40: ▼投資活動之現金流量 | J40: =OFFSET(A513,0,$K$1-1) | K40: =SUM(K41,K44,K47,K48,K49,K51,K54,K64) | M40: =L40-G40 | O40: =L40-B40 | P40: =J40-K40 | Q40: =D40-F40
H41: 減少流動金融資產及短期貸墊款 | J41: =OFFSET(A514,0,$K$1-1) | K41: =K42+K43 | M41: =L41-G41 | O41: =L41-B41 | P41: =J41-K41 | Q41: =D41-F41
A42: 交通及運輸設備 | B42: =VLOOKUP(A42,$A$309:$AX$418,$K$1,FALSE) | C42: 254 | D42: =J60*-1 | E42: 104 | F42: =J18 | G42: =B42+SUM(D42:D44)-SUM(F42:F44) | H42: 減少流動金融資產 | I42: 211 | J42: =OFFSET(A515,0,$K$1-1) | K42: =-SUMIF($C$7:$C$127,I42,$D$7:$D$127)+SUMIF($E$7:$E$135,I42,$F$7:$F$127) | L42: =VLOOKUP(A42,$A$140:$AX$249,$K$1,FALSE) | M42: =L42-G42 | O42: =L42-B42 | P42: =J42-K42 | Q42: =D42-F42
C43: 410 | D43: =J106 | E43: 413 | F43: =J110*-1 | H43: 減少短期墊款 | I43: 212 | J43: =OFFSET(A516,0,$K$1-1) | K43: =-SUMIF($C$7:$C$127,I43,$D$7:$D$127)+SUMIF($E$7:$E$135,I43,$F$7:$F$127) | M43: =L43-G43 | O43: =L43-B43 | P43: =J43-K43 | Q43: =D43-F43
H44: 減少投資、長期應收款、貸墊款及準備金 | J44: =OFFSET(A517,0,$K$1-1) | K44: =SUM(K45:K46) | M44: =L44-G44 | O44: =L44-B44 | P44: =J44-K44 | Q44: =D44-F44
A45: 什項設備 | B45: =VLOOKUP(A45,$A$309:$AX$418,$K$1,FALSE) | C45: 255 | D45: =J61*-1 | E45: 105 | F45: =J19 | G45: =B45+SUM(D45:D48)-SUM(F45:F48) | H45: 減少投資 | I45: 221 | J45: =OFFSET(A518,0,$K$1-1) | K45: =-SUMIF($C$7:$C$127,I45,$D$7:$D$127)+SUMIF($E$7:$E$135,I45,$F$7:$F$127) | L45: =VLOOKUP(A45,$A$140:$AX$249,$K$1,FALSE) | M45: =L45-G45 | O45: =L45-B45 | P45: =J45-K45 | Q45: =D45-F45
A46: 0 | C46: 408 | D46: =J102 | H46: 減少準備金 | I46: 222 | J46: =OFFSET(A519,0,$K$1-1) | K46: =-SUMIF($C$7:$C$127,I46,$D$7:$D$127)+SUMIF($E$7:$E$135,I46,$F$7:$F$127) | M46: =L46-G46 | O46: =L46-B46 | P46: =J46-K46 | Q46: =D46-F46
A47: 0 | C47: 411 | D47: =J107 | E47: 414 | F47: =-J111 | H47: 收取利息 | J47: =OFFSET(A520,0,$K$1-1) | K47: =J47 | M47: =L47-G47 | O47: =L47-B47 | P47: =J47-K47 | Q47: =D47-F47
A48: 0 | C48: 406 | D48: =J98 | H48: 收取股利 | J48: =OFFSET(A521,0,$K$1-1) | K48: =J48 | M48: =L48-G48 | O48: =L48-B48 | P48: =J48-K48 | Q48: =D48-F48
A49: 租賃資產 | B49: =VLOOKUP(A49,$A$309:$AX$413,$K$1,FALSE) | E49: 106 | F49: =J20 | G49: =B49+D49-F49 | H49: 增加流動金融資產及短期貸墊款 | J49: =OFFSET(A522,0,$K$1-1) | K49: =K50 | L49: =VLOOKUP(A49,$A$140:$AX$249,$K$1,FALSE) | M49: =L49-G49 | O49: =L49-B49 | P49: =J49-K49 | Q49: =D49-F49
A50: 租賃權益改良 | B50: =VLOOKUP(A50,$A$309:$AX$418,$K$1,FALSE) | C50: 257 | D50: =J63*-1 | E50: 107 | F50: =J21 | G50: =B50+D50-F50 | H50: 增加流動金融資產 | I50: 231 | J50: =OFFSET(A523,0,$K$1-1) | K50: =-SUMIF($C$7:$C$127,I50,$D$7:$D$127)+SUMIF($E$7:$E$135,I50,$F$7:$F$127) | L50: =VLOOKUP(A50,$A$140:$AX$249,$K$1,FALSE) | M50: =L50-G50 | O50: =L50-B49 | P50: =J50-K50 | Q50: =D49-F49
A51: 購建中固定資產 | B51: =VLOOKUP(A51,$A$309:$AX$418,$K$1,FALSE) | C51: 256 | D51: =J62*-1 | E51: 404 | F51: =J96 | G51: =B51+SUM(D51:D53)-SUM(F51:F53) | H51: 增加投資、長期應收款、貸墊款及準備金 | J51: =OFFSET(A524,0,$K$1-1) | K51: =SUM(K52:K53) | L51: =VLOOKUP(A51,$A$140:$AX$249,$K$1,FALSE) | M51: =L51-G51 | O51: =L51-B50 | P51: =J51-K51 | Q51: =D50-F50
E52: 405 | F52: =J97 | H52: 增加投資 | I52: 241 | J52: =OFFSET(A525,0,$K$1-1) | K52: =-SUMIF($C$7:$C$127,I52,$D$7:$D$127)+SUMIF($E$7:$E$135,I52,$F$7:$F$127) | M52: =L52-G52 | O52: =L52-B51 | P52: =J52-K52 | Q52: =D51-F51
E53: 406 | F53: =J98 | H53: 增加準備金 | I53: 242 | J53: =OFFSET(A526,0,$K$1-1) | K53: =-SUMIF($C$7:$C$127,I53,$D$7:$D$127)+SUMIF($E$7:$E$135,I53,$F$7:$F$127) | M53: =L53-G52 | O53: =L53-B52 | P53: =J53-K53 | Q53: =D52-F52
A54: 生物資產－非流動 | B54: =SUM(B55) | G54: =SUM(G55) | H54: 增加不動產、廠房及設備、礦產資源 | J54: =OFFSET(A527,0,$K$1-1) | K54: =K55 | L54: =VLOOKUP(A54,$A$140:$AX$249,$K$1,FALSE) | M54: =L54-G54 | O54: =L54-B54 | P54: =J54-K54 | Q54: =D54-F54
A55: 生產性生物資產－非流動 | B55: =VLOOKUP(A55,$A$309:$AX$418,$K$1,FALSE) | E55: 109 | F55: =J23 | G55: =B55+SUM(D55:D55)-SUM(F55:F55) | H55: 增加不動產、廠房及設備 | J55: =OFFSET(A528,0,$K$1-1) | K55: =K56 | L55: =VLOOKUP(A55,$A$140:$AX$249,$K$1,FALSE) | M55: =L55-G55 | O55: =L55-B55 | P55: =J55-K55 | Q55: =D55-F55
A56: 無形資產 | B56: =SUM(B57) | G56: =SUM(G57) | H56: 固定資產之增置 | J56: =OFFSET(A529,0,$K$1-1) | K56: =SUM(K57:K63) | L56: =VLOOKUP(A56,$A$140:$AX$249,$K$1,FALSE) | M56: =L56-G56 | O56: =L56-B56 | P56: =J56-K56 | Q56: =D56-F56
A57: 無形資產 | B57: =VLOOKUP(A57,$A$309:$AX$418,$K$1,FALSE) | E57: 111 | F57: =J25 | G57: =B57+SUM(D57:D59)-SUM(F57:F59) | H57: 土地改良物 | I57: 251 | J57: =OFFSET(A530,0,$K$1-1) | K57: =-SUMIF($C$7:$C$127,I57,$D$7:$D$127)+SUMIF($E$7:$E$127,I57,$F$7:$F$127) | L57: =VLOOKUP(A57,$A$140:$AX$249,$K$1,FALSE) | M57: =L57-G57 | O57: =L57-B57 | P57: =J57-K57 | Q57: =D57-F57
A58: 0 | C58: 415 | D58: =J113 | E58: 416 | F58: =J114*-1 | H58: 房屋及建築 | I58: 252 | J58: =OFFSET(A531,0,$K$1-1) | K58: =-SUMIF($C$7:$C$127,I58,$D$7:$D$127)+SUMIF($E$7:$E$127,I58,$F$7:$F$127) | M58: =L58-G58 | O58: =L58-B58 | P58: =J58-K58 | Q58: =D58-F58
A59: 0 | C59: 258 | D59: =J65*-1 | E59: 112 | H59: 機械及設備 | I59: 253 | J59: =OFFSET(A532,0,$K$1-1) | K59: =-SUMIF($C$7:$C$127,I59,$D$7:$D$127)+SUMIF($E$7:$E$127,I59,$F$7:$F$127) | M59: =L59-G59 | O59: =L59-B59 | P59: =J59-K59 | Q59: =D59-F59
A60: 0 | H60: 交通及運輸設備 | I60: 254 | J60: =OFFSET(A533,0,$K$1-1) | K60: =-SUMIF($C$7:$C$127,I60,$D$7:$D$127)+SUMIF($E$7:$E$127,I60,$F$7:$F$127) | M60: =L60-G60 | O60: =L60-B60 | P60: =J60-K60 | Q60: =D60-F60
A61: 其他資產 | B61: =SUM(B62,B65,B68) | G61: =SUM(G62,G65,G68) | H61: 什項設備 | I61: 255 | J61: =OFFSET(A534,0,$K$1-1) | K61: =-SUMIF($C$7:$C$127,I61,$D$7:$D$127)+SUMIF($E$7:$E$127,I61,$F$7:$F$127) | L61: =VLOOKUP(A61,$A$140:$AX$249,$K$1,FALSE) | M61: =L61-G61 | O61: =L61-B61 | P61: =J61-K61 | Q61: =D61-F61
A62: 遞延資產 | B62: =VLOOKUP(A62,$A$309:$AX$418,$K$1,FALSE) | E62: 112 | F62: =J26-F59 | G62: =B62+SUM(D62:D64)-SUM(F62:F64) | H62: 購建中固定資產 | I62: 256 | J62: =OFFSET(A535,0,$K$1-1) | K62: =-SUMIF($C$7:$C$127,I62,$D$7:$D$127)+SUMIF($E$7:$E$127,I62,$F$7:$F$127) | L62: =VLOOKUP(A62,$A$140:$AX$249,$K$1,FALSE) | M62: =L62-G62 | O62: =L62-B62 | P62: =J62-K62 | Q62: =D62-F62
A63: 0 | D63: =J126 | F63: =J127*-1 | H63: 租賃權益改良 | I63: 257 | J63: =OFFSET(A536,0,$K$1-1) | K63: =-SUMIF($C$7:$C$127,I63,$D$7:$D$127)+SUMIF($E$7:$E$127,I63,$F$7:$F$127) | M63: =L63-G63 | O63: =L63-B63 | P63: =J63-K63 | Q63: =D63-F63
A64: 0 | C64: 259 | D64: =J67*-1 | H64: 增加無形資產及其他資產 | J64: =OFFSET(A537,0,$K$1-1) | K64: =K65+K66 | M64: =L64-G64 | O64: =L64-B64 | P64: =J64-K64 | Q64: =D64-F64
A65: 什項資產 | B65: =VLOOKUP(A65,$A$309:$AX$418,$K$1,FALSE) | C65: 417 | D65: =F111 | E65: 108 | F65: =J22 | G65: =B65+SUM(D65:D67)-SUM(F65:F67) | H65: 增加無形資產 | I65: 258 | J65: =OFFSET(A538,0,$K$1-1) | K65: =-SUMIF($C$7:$C$127,I65,$D$7:$D$127)+SUMIF($E$7:$E$127,I65,$F$7:$F$127) | L65: =VLOOKUP(A65,$A$140:$AX$249,$K$1,FALSE) | M65: =L65-G65 | O65: =L65-B65 | P65: =J65-K65 | Q65: =D65-F65
A66: 0 | H66: 增加其他資產 | J66: =OFFSET(A539,0,$K$1-1) | K66: =K67 | M66: =L66-G66 | O66: =L66-B66 | P66: =J66-K66 | Q66: =D66-F66
A67: 0 | H67: 增加遞延費用 | I67: 259 | J67: =OFFSET(A540,0,$K$1-1) | K67: =-SUMIF($C$7:$C$127,I67,$D$7:$D$127)+SUMIF($E$7:$E$127,I67,$F$7:$F$127) | M67: =L67-G67 | O67: =L67-B67 | P67: =J67-K67 | Q67: =D67-F67
G68: =B68+D68-F68 | H68: ▼投資活動之淨現金流入（流出） | J68: =OFFSET(A541,0,$K$1-1) | K68: =K40 | P68: =J68-K68 | Q68: =D68-F68
A69: 合 計 | B69: =B7+B17+B26+B54+B56+B61 | G69: =G7+G17+G26+G54+G56+G61 | H69: ▼籌資活動之現金流量 | J69: =OFFSET(A542,0,$K$1-1) | K69: =K70+K72+K74+K81+K79+K83 | L69: =VLOOKUP(A69,$A$140:$AX$249,$K$1,FALSE) | M69: =L69-G69 | O69: =L69-B69 | P69: =J69-K69 | Q69: =D69-F69
A70: 負債 | B70: =B71+B78+B83 | G70: =G71+G78+G83 | H70: 增加短期債務、流動金融負債及其他負債 | J70: =OFFSET(A543,0,$K$1-1) | K70: =K71 | L70: =VLOOKUP(A70,$A$253:$AX$305,$K$1,FALSE) | M70: =L70-G70 | O70: =L70-B70 | P70: =J70-K70 | Q70: =D70-F70
A71: 流動負債 | B71: =SUM(B72:B77) | G71: =SUM(G72:G77) | H71: 增加其他負債 | I71: 311 | J71: =OFFSET(A544,0,$K$1-1) | K71: =-SUMIF($C$7:$C$127,I71,$D$7:$D$127)+SUMIF($E$7:$E$127,I71,$F$7:$F$127) | L71: =VLOOKUP(A71,$A$253:$AX$305,$K$1,FALSE) | M71: =L71-G71 | O71: =L71-B71 | P71: =J71-K71 | Q71: =D71-F71
A72: 短期債務 | B72: =VLOOKUP(A72,$A$423:$AX$475,$K$1,FALSE) | C72: 322 | D72: =J82*-1 | E72: 418 | F72: =D81 | G72: =B72+SUM(F72:F73)-SUM(D72:D73) | H72: 增加長期負債 | J72: =OFFSET(A545,0,$K$1-1) | K72: =K73 | L72: =VLOOKUP(A72,$A$253:$AX$305,$K$1,FALSE) | M72: =L72-G72 | O72: =L72-B72 | P72: =J72-K72 | Q72: =D72-F72
A73: 0 | C73: 316 | H73: 增加長期債務 | I73: 312 | J73: =OFFSET(A546,0,$K$1-1) | K73: =-SUMIF($C$7:$C$127,I73,$D$7:$D$127)+SUMIF($E$7:$E$127,I73,$F$7:$F$127) | M73: =L73-G73 | O73: =L73-B73 | P73: =J73-K73 | Q73: =D73-F73
A74: 應付款項 | B74: =VLOOKUP(A74,$A$423:$AX$475,$K$1,FALSE) | E74: 161 | G74: =B74+SUM(F74:F75)-SUM(D74:D75) | H74: 增加基金、公積及填補短絀 | J74: =OFFSET(A547,0,$K$1-1) | K74: =SUM(K75) | L74: =VLOOKUP(A74,$A$253:$AX$305,$K$1,FALSE) | M74: =L74-G74 | O74: =L74-B74 | P74: =J74-K74 | Q74: =D74-F74
A75: 0 | H75: 增加基金 | J75: =OFFSET(A548,0,$K$1-1) | K75: =SUM(K76:K78) | M75: =L75-G75 | O75: =L75-B75 | P75: =J75-K75 | Q75: =D75-F75
A76: 預收款項 | B76: =VLOOKUP(A76,$A$423:$AX$475,$K$1,FALSE) | E76: 161 | F76: =J34 | G76: =B76+SUM(F76:F77)-SUM(D76:D77) | H76: 國庫撥款增置固定資產 | I76: 313 | J76: =OFFSET(A549,0,$K$1-1) | K76: =-SUMIF($C$7:$C$127,I76,$D$7:$D$127)+SUMIF($E$7:$E$127,I76,$F$7:$F$127) | L76: =VLOOKUP(A76,$A$253:$AX$305,$K$1,FALSE) | M76: =L76-G76 | O76: =L76-B76 | P76: =J76-K76 | Q76: =D76-F76
A77: 0 | H77: 國庫增撥無形資產 | I77: 314 | J77: =OFFSET(A550,0,$K$1-1) | K77: =-SUMIF($C$7:$C$127,I77,$D$7:$D$127)+SUMIF($E$7:$E$127,I77,$F$7:$F$127) | M77: =L77-G77 | O77: =L77-B77 | P77: =J77-K77 | Q77: =D77-F77
A78: 長期負債 | B78: =SUM(B81) | G78: =SUM(G81) | H78: 國庫增撥遞延資產 | I78: 315 | J78: =OFFSET(A551,0,$K$1-1) | K78: =-SUMIF($C$7:$C$127,I78,$D$7:$D$127)+SUMIF($E$7:$E$127,I78,$F$7:$F$127) | L78: =VLOOKUP(A78,$A$253:$AX$305,$K$1,FALSE) | M78: =L78-G78 | O78: =L78-B78 | P78: =J78-K78 | Q78: =D78-F78
H79: 減少短期債務、流動金融負債及其他負債 | J79: =OFFSET(A552,0,$K$1-1)
H80: 減少短期債務 | I80: 316 | J80: =OFFSET(A553,0,$K$1-1) | K80: =-SUMIF($C$7:$C$127,I80,$D$7:$D$127)+SUMIF($E$7:$E$127,I80,$F$7:$F$127)
A81: 長期債務 | B81: =VLOOKUP(A81,$A$423:$AX$475,$K$1,FALSE) | C81: 418 | D81: =J116 | E81: 312 | F81: =J73 | G81: =B81+SUM(F81:F82)-SUM(D81:D82) | H81: 減少長期負債 | J81: =OFFSET(A554,0,$K$1-1) | K81: =K82 | L81: =VLOOKUP(A81,$A$253:$AX$305,$K$1,FALSE) | M81: =L81-G81 | O81: =L81-B81 | P81: =J81-K81 | Q81: =D81-F81
A82: 0 | C82: 322 | H82: 減少長期債務 | I82: 322 | J82: =OFFSET(A555,0,$K$1-1) | K82: =-SUMIF($C$7:$C$127,I82,$D$7:$D$127)+SUMIF($E$7:$E$127,I82,$F$7:$F$127) | M82: =L82-G82 | O82: =L82-B82 | P82: =J82-K82 | Q82: =D72-F82
A83: 其他負債 | B83: =SUM(B84,B90) | G83: =SUM(G84,G90) | H83: 支付利息 | J83: =OFFSET(A556,0,$K$1-1) | K83: =J83 | L83: =VLOOKUP(A83,$A$253:$AX$305,$K$1,FALSE) | M83: =L83-G83 | O83: =L83-B83 | P83: =J83-K83 | Q83: =D83-F83
A84: 什項負債 | B84: =VLOOKUP(A84,$A$423:$AX$475,$K$1,FALSE) | C84: 321 | G84: =B84+SUM(F84:F89)-SUM(D84:D89) | H84: ▼籌資活動之淨現金流入（流出） | J84: =OFFSET(A557,0,$K$1-1) | K84: =K69 | L84: =VLOOKUP(A84,$A$253:$AX$305,$K$1,FALSE) | M84: =L84-G84 | O84: =L84-B84 | P84: =J84-K84 | Q84: =D84-F84
A85: 0 | C85: 402 | D85: =J91*-1 | E85: 122 | F85: =J28 | H85: ▼現金及約當現金之淨增（淨減） | I85: B | J85: =OFFSET(A558,0,$K$1-1) | K85: =J85 | M85: =L85-G85 | O85: =L85-B85 | P85: =J85-K85 | Q85: =D85-F85
A86: 0 | E86: 401 | F86: =J90 | H86: ▼期初現金及約當現金 | J86: =OFFSET(A559,0,$K$1-1) | K86: =B8 | M86: =L86-G86 | O86: =L86-B86 | P86: =J86-K86 | Q86: =D86-F86
A87: 0 | H87: ▼期末現金及約當現金 | J87: =OFFSET(A560,0,$K$1-1) | K87: =G8 | M87: =L87-G87 | O87: =L87-B87 | P87: =J87-K87 | Q87: =D87-F87
A88: 0 | H88: ▼不影響現金流量之投資與籌資活動 | J88: =OFFSET(A561,0,$K$1-1) | M88: =L88-G88 | O88: =L88-B88 | P88: =J88-K88 | Q88: =D88-F88
A89: 0 | H89: 退休離職準備金與應付退休及離職金同額增加(+)或減少(-)之金額 | J89: =OFFSET(A562,0,$K$1-1) | K89: =K90+K91 | M89: =L89-G89 | O89: =L89-B89 | P89: =J89-K89 | Q89: =D89-F89
A90: 遞延負債 | B90: =VLOOKUP(A90,$A$423:$AX$475,$K$1,FALSE) | C90: 124 | D90: =J31*-1 | E90: 311 | F90: =J71 | G90: =B90+SUM(F90:F96)-SUM(D90:D96) | H90: 退休離職準備金與應付退休及離職金同額增加之金額(+) | I90: 401 | J90: =OFFSET(A563,0,$K$1-1) | K90: =(SUMIF($C$7:$C$127,I90,$D$7:$D$127)+SUMIF($E$7:$E$127,I90,$F$7:$F$127))/2 | L90: =VLOOKUP(A90,$A$253:$AX$305,$K$1,FALSE) | M90: =L90-G90 | O90: =L90-B90 | P90: =J90-K90 | Q90: =D90-F90
A91: 0 | C91: 123 | D91: =-J30 | E91: 403 | F91: =J93 | H91: 退休離職準備金與應付退休及離職金同額減少之金額(-) | I91: 402 | J91: =OFFSET(A564,0,$K$1-1) | K91: =(SUMIF($C$7:$C$127,I91,$D$7:$D$127)+SUMIF($E$7:$E$127,I91,$F$7:$F$127))/2*-1 | M91: =L91-G91 | O91: =L91-B91 | P91: =J91-K91 | Q91: =D91-F91
A92: 0 | E92: 407 | F92: =J101 | H92: 其他準備金與遞延收入同額增加之金額 | J92: =OFFSET(A565,0,$K$1-1) | K92: =K93 | M92: =L92-G92 | O92: =L92-B92 | P92: =J92-K92 | Q92: =D92-F92
A93: 0 | E93: 408 | F93: =J102 | H93: 其他準備金與遞延收入同額增加之金額 | I93: 403 | J93: =OFFSET(A566,0,$K$1-1) | K93: =(SUMIF($C$7:$C$127,I93,$D$7:$D$127)+SUMIF($E$7:$E$127,I93,$F$7:$F$127))/2 | M93: =L93-G93 | O93: =L93-B93 | P93: =J93-K93 | Q93: =D93-F93
E94: 410 | H94: 以前年度購建中固定資產科目，調整轉入不動產、廠房及設備科目之 | J94: =OFFSET(A567,0,$K$1-1) | K94: =K95 | P94: =J94-K94
H95: 調整轉入不動產、廠房及設備科目明細 | J95: =OFFSET(A568,0,$K$1-1) | K95: =K96+K97+K98 | O95: =L95-B96 | P95: =J95-K95 | Q95: =D96-F96
A96: 0 | H96: 土地改良物 | I96: 404 | J96: =OFFSET(A569,0,$K$1-1) | K96: =(SUMIF($C$7:$C$127,I96,$D$7:$D$127)+SUMIF($E$7:$E$127,I96,$F$7:$F$127))/2 | O96: =L97-B97 | P96: =J96-K96 | Q96: =D97-F97
A97: 淨值 | B97: =B98+B110+B116+B125 | G97: =G98+G110+G116+G125 | H97: 房屋及建築 | I97: 405 | J97: =OFFSET(A570,0,$K$1-1) | K97: =(SUMIF($C$7:$C$127,I97,$D$7:$D$127)+SUMIF($E$7:$E$127,I97,$F$7:$F$127))/2 | L97: =VLOOKUP(A97,$A$253:$AX$305,$K$1,FALSE) | M97: =L97-G97 | O97: =L98-B98 | P97: =J97-K97 | Q97: =D98-F98
A98: 基金 | B98: =SUM(B99:B101) | G98: =SUM(G99:G101) | H98: 什項設備 | I98: 406 | J98: =OFFSET(A571,0,$K$1-1) | K98: =(SUMIF($C$7:$C$127,I98,$D$7:$D$127)+SUMIF($E$7:$E$127,I98,$F$7:$F$127))/2 | L98: =VLOOKUP(A98,$A$253:$AX$305,$K$1,FALSE) | M98: =L98-G98 | O98: =L99-B99 | P98: =J98-K98 | Q98: =D99-F99
A99: 基金 | B99: =VLOOKUP(A99,$A$423:$AX$475,$K$1,FALSE) | E99: 313 | F99: =J76 | G99: =B99+SUM(F99:F109)-SUM(D99:D109) | H99: 不動產、廠房及設備與遞延收入同額增加(+)或減少(-)之金額 | J99: =OFFSET(A572,0,$K$1-1) | K99: =K100 | L99: =VLOOKUP(A99,$A$253:$AX$305,$K$1,FALSE) | M99: =L99-G99 | O99: =L100-B100 | P99: =J99-K99 | Q99: =D100-F100
A100: 0 | E100: 314 | F100: =J77 | H100: 不動產、廠房及設備與遞延收入同額增加明細(+) | J100: =OFFSET(A573,0,$K$1-1) | K100: =K101+K102 | M100: =L100-G100 | O100: =L101-B101 | P100: =J100-K100 | Q100: =D101-F101
...

Sheet 中正
A1: =OFFSET(A139,0,K1-1) | K1: =L1+2 | L1: 8
A2: 預計平衡表與現金流量表勾稽底稿
A3: 中華民國115年度
A4: 科目 | B4: 114.12.31 | C4: 調整項目 | G4: 115.12.31 | H4: 現金流量表勾稽項目
B5: 預計數 | D5: 借方 | F5: 貸方 | G5: 預計數
A6: 資產 | H6: ▼業務活動之現金流量 | L6: 114年12月 | M6: 差異數要再加(減) | O6: 比較增減 | Q6: 調整項目
A7: 流動資產 | B7: =SUM(B8:B16) | G7: =SUM(G8:G16) | H7: 本期賸餘（短絀） | I7: A | J7: =OFFSET(A480,0,$K$1-1) | K7: =-SUMIF($C$7:$C$127,I7,$D$7:$D$127)+SUMIF($E$7:$E$127,I7,$F$7:$F$127) | L7: =VLOOKUP(A7,$A$140:$AX$249,$K$1,FALSE) | M7: =L7-G7 | O7: =L7-B7 | P7: =J7-K7 | Q7: =D7-F7
A8: 現金 | B8: =VLOOKUP(A8,$A$309:$AX$418,$K$1,FALSE) | C8: B | D8: =IF(G8-B8>0,G8-B8,"0") | E8: B | F8: =IF(G8-B8<0,B8-G8,"0") | G8: =J87 | H8: 利息股利之調整 | J8: =OFFSET(A481,0,$K$1-1) | K8: =SUM(K9:K11) | L8: =VLOOKUP(A8,$A$140:$AX$249,$K$1,FALSE) | M8: =L8-G8 | O8: =L8-B8 | P8: =J8-K8 | Q8: =D8-F8
A9: 流動金融資產 | B9: =VLOOKUP(A9,$A$309:$AX$418,$K$1,FALSE) | C9: 231 | D9: =J50*-1 | E9: 211 | F9: =J42 | G9: =B9+D9-F9+D10-F10 | H9: 利息收入 | J9: =OFFSET(A482,0,$K$1-1) | K9: =J9 | L9: =VLOOKUP(A9,$A$140:$AX$249,$K$1,FALSE) | M9: =L9-G9 | O9: =L9-B9 | P9: =J9-K9 | Q9: =D9-F9
C10: 125 | H10: 股利收入 | J10: =OFFSET(A483,0,$K$1-1) | K10: =J10 | M10: =L10-G10 | O10: =L10-B10 | P10: =J10-K10 | Q10: =D10-F10
A11: 應收款項 | B11: =VLOOKUP(A11,$A$309:$AX$418,$K$1,FALSE) | C11: 151 | E11: 151 | G11: =B11+D11-F11 | H11: 利息費用 | J11: =OFFSET(A484,0,$K$1-1) | K11: =J11 | L11: =VLOOKUP(A11,$A$140:$AX$249,$K$1,FALSE) | M11: =L11-G11 | O11: =L11-B11 | P11: =J11-K11 | Q11: =D11-F11
A12: 0 | H12: 未計利息股利之本期賸餘（短絀） | J12: =OFFSET(A485,0,$K$1-1) | K12: =K7+K8 | M12: =L12-G12 | O12: =L12-B12 | P12: =J12-K12 | Q12: =D12-F12
A13: 存貨 | B13: =VLOOKUP(A13,$A$309:$AX$418,$K$1,FALSE) | C13: 151 | E13: 151 | G13: =B13+D13-F13 | H13: 調整項目 | J13: =OFFSET(A486,0,$K$1-1) | K13: =SUM(K14,K24,K27,K34,K33) | L13: =VLOOKUP(A13,$A$140:$AX$249,$K$1,FALSE) | M13: =L13-G13 | O13: =L13-B13 | P13: =J13-K13 | Q13: =D13-F13
A14: 生產性生物資產－流動 | B14: =VLOOKUP(A14,$A$309:$AX$418,$K$1,FALSE) | C14: 151 | E14: 151 | G14: =B14+D14-F14 | H14: 折舊、減損及折耗 | J14: =OFFSET(A487,0,$K$1-1) | K14: =SUM(K15:K23) | L14: =VLOOKUP(A14,$A$140:$AX$249,$K$1,FALSE) | M14: =L14-G14 | O14: =L14-B14 | P14: =J14-K14 | Q14: =D14-F14
A15: 預付款項 | B15: =VLOOKUP(A15,$A$309:$AX$418,$K$1,FALSE) | C15: 151 | E15: 151 | G15: =B15+D15-F15 | H15: 土地改良物 | I15: 101 | J15: =OFFSET(A488,0,$K$1-1) | K15: =-SUMIF($C$7:$C$127,I15,$D$7:$D$127)+SUMIF($E$7:$E$127,I15,$F$7:$F$127) | L15: =VLOOKUP(A15,$A$140:$AX$249,$K$1,FALSE) | M15: =L15-G15 | O15: =L15-B15 | P15: =J15-K15 | Q15: =D15-F15
A16: 短期貸墊款 | B16: =VLOOKUP(A16,$A$309:$AX$418,$K$1,FALSE) | C16: 151 | E16: 212 | F16: =J43 | G16: =B16+D16-F16 | H16: 房屋及建築 | I16: 102 | J16: =OFFSET(A489,0,$K$1-1) | K16: =-SUMIF($C$7:$C$127,I16,$D$7:$D$127)+SUMIF($E$7:$E$127,I16,$F$7:$F$127) | L16: =VLOOKUP(A16,$A$140:$AX$249,$K$1,FALSE) | M16: =L16-G16 | O16: =L16-B16 | P16: =J16-K16 | Q16: =D16-F16
A17: 投資、長期應收款、貸墊款及準備金 | B17: =SUM(B18:B21) | G17: =SUM(G18:G21) | H17: 機械及設備 | I17: 103 | J17: =OFFSET(A490,0,$K$1-1) | K17: =-SUMIF($C$7:$C$127,I17,$D$7:$D$127)+SUMIF($E$7:$E$127,I17,$F$7:$F$127) | L17: =VLOOKUP(A17,$A$140:$AX$249,$K$1,FALSE) | M17: =L17-G17 | O17: =L17-B17 | P17: =J17-K17 | Q17: =D17-F17
A18: 採權益法之投資 | B18: =VLOOKUP(A18,$A$309:$AX$418,$K$1,FALSE) | G18: =D18+F18+B18 | H18: 交通及運輸設備 | I18: 104 | J18: =OFFSET(A491,0,$K$1-1) | K18: =-SUMIF($C$7:$C$127,I18,$D$7:$D$127)+SUMIF($E$7:$E$127,I18,$F$7:$F$127) | L18: =VLOOKUP(A18,$A$140:$AX$249,$K$1,FALSE) | M18: =L18-G18 | O18: =L18-B18 | P18: =J18-K18 | Q18: =D18-F18
A19: 非流動金融資產 | B19: =VLOOKUP(A19,$A$309:$AX$418,$K$1,FALSE) | C19: 241 | D19: =J52*-1 | E19: 221 | F19: =J45 | G19: =B19+D19-F19 | H19: 什項設備 | I19: 105 | J19: =OFFSET(A492,0,$K$1-1) | K19: =-SUMIF($C$7:$C$127,I19,$D$7:$D$127)+SUMIF($E$7:$E$127,I19,$F$7:$F$127) | L19: =VLOOKUP(A19,$A$140:$AX$249,$K$1,FALSE) | M19: =L19-G19 | O19: =L19-B19 | P19: =J19-K19 | Q19: =D19-F19
A20: 長期應收款 | B20: =VLOOKUP(A20,$A$309:$AX$418,$K$1,FALSE) | G20: =B20+D20-F20 | H20: 租賃資產 | I20: 106 | J20: =OFFSET(A493,0,$K$1-1) | K20: =-SUMIF($C$7:$C$127,I20,$D$7:$D$127)+SUMIF($E$7:$E$127,I20,$F$7:$F$127) | L20: =VLOOKUP(A20,$A$140:$AX$249,$K$1,FALSE) | M20: =L20-G20 | O20: =L20-B20 | P20: =J20-K20 | Q20: =D20-F20
A21: 準備金 | B21: =VLOOKUP(A21,$A$309:$AX$418,$K$1,FALSE) | C21: 242 | D21: =J53*-1 | E21: 222 | F21: =J46 | G21: =B21+SUM(D21:D25)-SUM(F21:F25) | H21: 租賃權益改良 | I21: 107 | J21: =OFFSET(A494,0,$K$1-1) | K21: =-SUMIF($C$7:$C$127,I21,$D$7:$D$127)+SUMIF($E$7:$E$127,I21,$F$7:$F$127) | L21: =VLOOKUP(A21,$A$140:$AX$249,$K$1,FALSE) | M21: =L21-G21 | O21: =L21-B21 | P21: =J21-K21 | Q21: =D21-F21
A22: 0 | C22: 401 | D22: =J90 | E22: 402 | F22: =-J91 | H22: 代管資產 | I22: 108 | J22: =OFFSET(A495,0,$K$1-1) | K22: =-SUMIF($C$7:$C$127,I22,$D$7:$D$127)+SUMIF($E$7:$E$127,I22,$F$7:$F$127) | M22: =L22-G22 | O22: =L22-B22 | P22: =J22-K22 | Q22: =D22-F22
A23: 0 | C23: 403 | D23: =J93 | H23: 生產性生物資產－非流動 | I23: 109 | J23: =OFFSET(A496,0,$K$1-1) | K23: =-SUMIF($C$7:$C$127,I23,$D$7:$D$127)+SUMIF($E$7:$E$127,I23,$F$7:$F$127) | M23: =L23-G23 | O23: =L23-B23 | P23: =J23-K23 | Q23: =D23-F23
A24: 0 | H24: 攤銷 | J24: =OFFSET(A497,0,$K$1-1) | K24: =SUM(K25:K26) | M24: =L24-G24 | O24: =L24-B24 | P24: =J24-K24 | Q24: =D24-F24
C25: 125 | D25: =J32*-1 | H25: 攤銷電腦軟體 | I25: 111 | J25: =OFFSET(A498,0,$K$1-1) | K25: =-SUMIF($C$7:$C$127,I25,$D$7:$D$127)+SUMIF($E$7:$E$127,I25,$F$7:$F$127) | M25: =L25-G25 | O25: =L25-B25 | P25: =J25-K25 | Q25: =D25-F25
A26: 不動產、廠房及設備 | B26: =SUM(B27:B52) | G26: =SUM(G27:G52) | H26: 其他攤銷費用 | I26: 112 | J26: =OFFSET(A499,0,$K$1-1) | K26: =-SUMIF($C$7:$C$127,I26,$D$7:$D$127)+SUMIF($E$7:$E$127,I26,$F$7:$F$127) | L26: =VLOOKUP(A26,$A$140:$AX$249,$K$1,FALSE) | M26: =L26-G26 | O26: =L26-B26 | P26: =J26-K26 | Q26: =D26-F26
A27: 土地 | B27: =VLOOKUP(A27,$A$309:$AX$418,$K$1,FALSE) | C27: 121 | G27: =B27+SUM(D27)-SUM(F27) | H27: 其他 | J27: =OFFSET(A500,0,$K$1-1) | K27: =K28+K29+K32 | L27: =VLOOKUP(A27,$A$140:$AX$249,$K$1,FALSE) | M27: =L27-G27 | O27: =L27-B27 | P27: =J27-K27 | Q27: =D27-F27
A28: 0 | H28: 應付退休及離職金 | I28: 122 | J28: =OFFSET(A501,0,$K$1-1) | K28: =-SUMIF($C$7:$C$127,I28,$D$7:$D$127)+SUMIF($E$7:$E$127,I28,$F$7:$F$127) | M28: =L28-G28 | O28: =L28-B28 | P28: =J28-K28 | Q28: =D28-F28
A29: 土地改良物 | B29: =VLOOKUP(A29,$A$309:$AX$418,$K$1,FALSE) | C29: 251 | D29: =J57*-1 | E29: 101 | F29: =J15 | G29: =B29+SUM(D29:D32)-SUM(F29:F32) | H29: 遞延收入 | J29: =OFFSET(A502,0,$K$1-1) | K29: =SUM(K30:K31) | L29: =VLOOKUP(A29,$A$140:$AX$249,$K$1,FALSE) | M29: =L29-G29 | O29: =L29-B29 | P29: =J29-K29 | Q29: =D29-F29
A30: 0 | C30: 404 | D30: =J96 | H30: 遞延收入-其他補助收入 | I30: 123 | J30: =OFFSET(A503,0,$K$1-1) | K30: =-SUMIF($C$7:$C$127,I30,$D$7:$D$127)+SUMIF($E$7:$E$127,I30,$F$7:$F$127) | M30: =L30-G30 | O30: =L30-B30 | P30: =J30-K30 | Q30: =D30-F30
A31: 0 | H31: 遞延收入-受贈收入 | I31: 124 | J31: =OFFSET(A504,0,$K$1-1) | K31: =-SUMIF($C$7:$C$127,I31,$D$7:$D$127)+SUMIF($E$7:$E$127,I31,$F$7:$F$127) | M31: =L31-G31 | O31: =L31-B31 | P31: =J31-K31 | Q31: =D31-F31
A32: 0 | H32: 其他 | I32: 125 | J32: =OFFSET(A505,0,$K$1-1) | M32: =L32-G32 | O32: =L32-B32 | P32: =J32-K32 | Q32: =D32-F32
A33: 房屋及建築 | B33: =VLOOKUP(A33,$A$309:$AX$418,$K$1,FALSE) | C33: 252 | D33: =J58*-1 | E33: 102 | F33: =J16 | G33: =B33+SUM(D33:D36)-SUM(F33:F36) | H33: 流動資產淨減（淨增） | I33: 151 | J33: =OFFSET(A506,0,$K$1-1) | K33: =-SUMIF($C$7:$C$127,I33,$D$7:$D$127)+SUMIF($E$7:$E$127,I33,$F$7:$F$127) | L33: =VLOOKUP(A33,$A$140:$AX$249,$K$1,FALSE) | M33: =L33-G33 | O33: =L33-B33 | P33: =J33-K33 | Q33: =D33-F33
A34: 0 | C34: 405 | D34: =J97 | H34: 流動負債淨增（淨減） | I34: 161 | J34: =OFFSET(A507,0,$K$1-1) | K34: =-SUMIF($C$7:$C$127,I34,$D$7:$D$127)+SUMIF($E$7:$E$127,I34,$F$7:$F$127) | M34: =L34-G34 | O34: =L34-B34 | P34: =J34-K34 | Q34: =D34-F34
A35: 0 | H35: 未計利息股利之現金流入（流出） | J35: =OFFSET(A508,0,$K$1-1) | K35: =K12+K13 | M35: =L35-G35 | O35: =L35-B35 | P35: =J35-K35 | Q35: =D35-F35
A36: 0 | H36: 收取利息 | J36: =OFFSET(A509,0,$K$1-1) | K36: =J36 | M36: =L36-G36 | O36: =L36-B36 | P36: =J36-K36 | Q36: =D36-F36
A37: 機械及設備 | B37: =VLOOKUP(A37,$A$309:$AX$418,$K$1,FALSE) | C37: 253 | D37: =J59*-1 | E37: 103 | F37: =J17 | G37: =B37+SUM(D37:D41)-SUM(F37:F41) | H37: 收取股利 | J37: =OFFSET(A510,0,$K$1-1) | K37: =J37 | L37: =VLOOKUP(A37,$A$140:$AX$249,$K$1,FALSE) | M37: =L37-G37 | O37: =L37-B37 | P37: =J37-K37 | Q37: =D37-F37
A38: 0 | C38: 407 | D38: =J101 | H38: 支付利息 | J38: =OFFSET(A511,0,$K$1-1) | K38: =J38 | M38: =L38-G38 | O38: =L38-B38 | P38: =J38-K38 | Q38: =D38-F38
A39: 0 | C39: 409 | D39: =J105 | E39: 412 | F39: =-J109 | H39: ▼業務活動之淨現金流入（流出） | J39: =OFFSET(A512,0,$K$1-1) | K39: =K36+K37+K38+K35 | M39: =L39-G39 | O39: =L39-B39 | P39: =J39-K39 | Q39: =D39-F39
A40: 0 | H40: ▼投資活動之現金流量 | J40: =OFFSET(A513,0,$K$1-1) | K40: =SUM(K41,K44,K47,K48,K49,K51,K54,K64) | M40: =L40-G40 | O40: =L40-B40 | P40: =J40-K40 | Q40: =D40-F40
H41: 減少流動金融資產及短期貸墊款 | J41: =OFFSET(A514,0,$K$1-1) | K41: =K42+K43 | M41: =L41-G41 | O41: =L41-B41 | P41: =J41-K41 | Q41: =D41-F41
A42: 交通及運輸設備 | B42: =VLOOKUP(A42,$A$309:$AX$418,$K$1,FALSE) | C42: 254 | D42: =J60*-1 | E42: 104 | F42: =J18 | G42: =B42+SUM(D42:D44)-SUM(F42:F44) | H42: 減少流動金融資產 | I42: 211 | J42: =OFFSET(A515,0,$K$1-1) | K42: =-SUMIF($C$7:$C$127,I42,$D$7:$D$127)+SUMIF($E$7:$E$135,I42,$F$7:$F$127) | L42: =VLOOKUP(A42,$A$140:$AX$249,$K$1,FALSE) | M42: =L42-G42 | O42: =L42-B42 | P42: =J42-K42 | Q42: =D42-F42
C43: 410 | D43: =J106 | E43: 413 | F43: =J110*-1 | H43: 減少短期墊款 | I43: 212 | J43: =OFFSET(A516,0,$K$1-1) | K43: =-SUMIF($C$7:$C$127,I43,$D$7:$D$127)+SUMIF($E$7:$E$135,I43,$F$7:$F$127) | M43: =L43-G43 | O43: =L43-B43 | P43: =J43-K43 | Q43: =D43-F43
H44: 減少投資、長期應收款、貸墊款及準備金 | J44: =OFFSET(A517,0,$K$1-1) | K44: =SUM(K45:K46) | M44: =L44-G44 | O44: =L44-B44 | P44: =J44-K44 | Q44: =D44-F44
A45: 什項設備 | B45: =VLOOKUP(A45,$A$309:$AX$418,$K$1,FALSE) | C45: 255 | D45: =J61*-1 | E45: 105 | F45: =J19 | G45: =B45+SUM(D45:D48)-SUM(F45:F48) | H45: 減少投資 | I45: 221 | J45: =OFFSET(A518,0,$K$1-1) | K45: =-SUMIF($C$7:$C$127,I45,$D$7:$D$127)+SUMIF($E$7:$E$135,I45,$F$7:$F$127) | L45: =VLOOKUP(A45,$A$140:$AX$249,$K$1,FALSE) | M45: =L45-G45 | O45: =L45-B45 | P45: =J45-K45 | Q45: =D45-F45
A46: 0 | C46: 408 | D46: =J102 | H46: 減少準備金 | I46: 222 | J46: =OFFSET(A519,0,$K$1-1) | K46: =-SUMIF($C$7:$C$127,I46,$D$7:$D$127)+SUMIF($E$7:$E$135,I46,$F$7:$F$127) | M46: =L46-G46 | O46: =L46-B46 | P46: =J46-K46 | Q46: =D46-F46
A47: 0 | C47: 411 | D47: =J107 | E47: 414 | F47: =-J111 | H47: 收取利息 | J47: =OFFSET(A520,0,$K$1-1) | K47: =J47 | M47: =L47-G47 | O47: =L47-B47 | P47: =J47-K47 | Q47: =D47-F47
A48: 0 | C48: 406 | D48: =J98 | H48: 收取股利 | J48: =OFFSET(A521,0,$K$1-1) | K48: =J48 | M48: =L48-G48 | O48: =L48-B48 | P48: =J48-K48 | Q48: =D48-F48
A49: 租賃資產 | B49: =VLOOKUP(A49,$A$309:$AX$413,$K$1,FALSE) | E49: 106 | F49: =J20 | G49: =B49+D49-F49 | H49: 增加流動金融資產及短期貸墊款 | J49: =OFFSET(A522,0,$K$1-1) | K49: =K50 | L49: =VLOOKUP(A49,$A$140:$AX$249,$K$1,FALSE) | M49: =L49-G49 | O49: =L49-B49 | P49: =J49-K49 | Q49: =D49-F49
A50: 租賃權益改良 | B50: =VLOOKUP(A50,$A$309:$AX$418,$K$1,FALSE) | C50: 257 | D50: =J63*-1 | E50: 107 | F50: =J21 | G50: =B50+D50-F50 | H50: 增加流動金融資產 | I50: 231 | J50: =OFFSET(A523,0,$K$1-1) | K50: =-SUMIF($C$7:$C$127,I50,$D$7:$D$127)+SUMIF($E$7:$E$135,I50,$F$7:$F$127) | L50: =VLOOKUP(A50,$A$140:$AX$249,$K$1,FALSE) | M50: =L50-G50 | O50: =L50-B49 | P50: =J50-K50 | Q50: =D49-F49
A51: 購建中固定資產 | B51: =VLOOKUP(A51,$A$309:$AX$418,$K$1,FALSE) | C51: 256 | D51: =J62*-1 | E51: 404 | F51: =J96 | G51: =B51+SUM(D51:D53)-SUM(F51:F53) | H51: 增加投資、長期應收款、貸墊款及準備金 | J51: =OFFSET(A524,0,$K$1-1) | K51: =SUM(K52:K53) | L51: =VLOOKUP(A51,$A$140:$AX$249,$K$1,FALSE) | M51: =L51-G51 | O51: =L51-B50 | P51: =J51-K51 | Q51: =D50-F50
E52: 405 | F52: =J97 | H52: 增加投資 | I52: 241 | J52: =OFFSET(A525,0,$K$1-1) | K52: =-SUMIF($C$7:$C$127,I52,$D$7:$D$127)+SUMIF($E$7:$E$135,I52,$F$7:$F$127) | M52: =L52-G52 | O52: =L52-B51 | P52: =J52-K52 | Q52: =D51-F51
E53: 406 | F53: =J98 | H53: 增加準備金 | I53: 242 | J53: =OFFSET(A526,0,$K$1-1) | K53: =-SUMIF($C$7:$C$127,I53,$D$7:$D$127)+SUMIF($E$7:$E$135,I53,$F$7:$F$127) | M53: =L53-G52 | O53: =L53-B52 | P53: =J53-K53 | Q53: =D52-F52
A54: 生物資產－非流動 | B54: =SUM(B55) | G54: =SUM(G55) | H54: 增加不動產、廠房及設備、礦產資源 | J54: =OFFSET(A527,0,$K$1-1) | K54: =K55 | L54: =VLOOKUP(A54,$A$140:$AX$249,$K$1,FALSE) | M54: =L54-G54 | O54: =L54-B54 | P54: =J54-K54 | Q54: =D54-F54
A55: 生產性生物資產－非流動 | B55: =VLOOKUP(A55,$A$309:$AX$418,$K$1,FALSE) | E55: 109 | F55: =J23 | G55: =B55+SUM(D55:D55)-SUM(F55:F55) | H55: 增加不動產、廠房及設備 | J55: =OFFSET(A528,0,$K$1-1) | K55: =K56 | L55: =VLOOKUP(A55,$A$140:$AX$249,$K$1,FALSE) | M55: =L55-G55 | O55: =L55-B55 | P55: =J55-K55 | Q55: =D55-F55
